Workbook

Sheet delhi_business_cleaned
A1: area | B1: category_searched | C1: name | D1: address | E1: rating | F1: review_count | G1: website | H1: phone | I1: types | J1: checking_duplicates_to_remove | K1: Digital Presence | L1: rating_band | M1: Review_band | N1: Opportunity_Level
A2: Saket, Delhi | B2: mobile shops | C2: Vardaan Mobile | D2: J-1/9A, Gupta Colony, Khirki Extension, Malviya Nagar, New Delhi, Delhi 110017, India | E2: 5 | F2: 1017 | H2: 099903 24096 | I2: cell_phone_store, catering_service, food_delivery, store, finance, service, food, point_of_interest, establishment | J2: =IF(COUNTIFS($C$2:C2,C2,$D$2:D2,D2)=1,"Unique","Duplicate") -> Unique | K2: =IF(TRIM(G2)="","No Website", IF(OR( ISNUMBER(SEARCH("facebook",LOWER(G2))), ISNUMBER(SEARCH("instagram",LOWER(G2))), ISNUMBER(SEARCH("wa.me",LOWER(G2))), ISNUMBER(SEARCH("whatsapp",LOWER(G2))), ISNUMBER(SEARCH("youtube",LOWER(G2))), ISNUMBER(SEARCH("twitter",LOWER(G2))), ISNUMBER(SEARCH("x.com",LOWER(G2))), ISNUMBER(SEARCH("linkedin",LOWER(G2))), ISNUMBER(SEARCH("linktr.ee",LOWER(G2))), ISNUMBER(SEARCH("g.page",LOWER(G2))), ISNUMBER(SEARCH("maps.app.goo.gl",LOWER(G2))), ISNUMBER(SEARCH("goo.gl",LOWER(G2))) ), "Social Media", "Official Website")) -> No Website | L2: =IF(E2>=4.5,"Excellent", IF(E2>=4,"Good", IF(E2>=3,"Average","Poor"))) -> Excellent | M2: =IF(F2>=1000,"1000+ Reviews", IF(F2>=500,"500-999 Reviews", IF(F2>=100,"100-499 Reviews", "Below 100 Reviews"))) -> 1000+ Reviews | N2: =IF(K2="Official Website","Low Opportunity", IF(AND(K2="No Website",E2>=4.5,F2>=500),"Very High Opportunity", IF(AND(K2="No Website",E2>=4.5),"High Opportunity", IF(K2="Social Media","Medium Opportunity","Low Opportunity")))) -> Very High Opportunity
A3: Burari, Delhi | B3: restaurants | C3: Road Bench Cafe family restaurant | D3: 1st floor, near Medlife hospital and Bata showroom, Block D, Kamal Pur, Burari, Delhi, 110084, India | E3: 4.3 | F3: 337 | H3: 085859 57900 | I3: family_restaurant, restaurant, food, point_of_interest, establishment | J3: =IF(COUNTIFS($C$2:C3,C3,$D$2:D3,D3)=1,"Unique","Duplicate") -> Unique | K3: =IF(TRIM(G3)="","No Website", IF(OR( ISNUMBER(SEARCH("facebook",LOWER(G3))), ISNUMBER(SEARCH("instagram",LOWER(G3))), ISNUMBER(SEARCH("wa.me",LOWER(G3))), ISNUMBER(SEARCH("whatsapp",LOWER(G3))), ISNUMBER(SEARCH("youtube",LOWER(G3))), ISNUMBER(SEARCH("twitter",LOWER(G3))), ISNUMBER(SEARCH("x.com",LOWER(G3))), ISNUMBER(SEARCH("linkedin",LOWER(G3))), ISNUMBER(SEARCH("linktr.ee",LOWER(G3))), ISNUMBER(SEARCH("g.page",LOWER(G3))), ISNUMBER(SEARCH("maps.app.goo.gl",LOWER(G3))), ISNUMBER(SEARCH("goo.gl",LOWER(G3))) ), "Social Media", "Official Website")) -> No Website | L3: =IF(E3>=4.5,"Excellent", IF(E3>=4,"Good", IF(E3>=3,"Average","Poor"))) -> Good | M3: =IF(F3>=1000,"1000+ Reviews", IF(F3>=500,"500-999 Reviews", IF(F3>=100,"100-499 Reviews", "Below 100 Reviews"))) -> 100-499 Reviews | N3: =IF(K3="Official Website","Low Opportunity", IF(AND(K3="No Website",E3>=4.5,F3>=500),"Very High Opportunity", IF(AND(K3="No Website",E3>=4.5),"High Opportunity", IF(K3="Social Media","Medium Opportunity","Low Opportunity")))) -> Low Opportunity
A4: Burari, Delhi | B4: restaurants | C4: FOOD PITARRA | D4: Kh. No- 457/1, near Shalimar Palace, opposite Vindhya Shree Appartment, Indraprasth Colony, Burari, Delhi, 110084, India | E4: 4.2 | F4: 451 | G4: https://www.facebook.com/FoodPitarra/ | H4: 073037 70072 | I4: family_restaurant, restaurant, food, point_of_interest, establishment | J4: =IF(COUNTIFS($C$2:C4,C4,$D$2:D4,D4)=1,"Unique","Duplicate") -> Unique | K4: =IF(TRIM(G4)="","No Website", IF(OR( ISNUMBER(SEARCH("facebook",LOWER(G4))), ISNUMBER(SEARCH("instagram",LOWER(G4))), ISNUMBER(SEARCH("wa.me",LOWER(G4))), ISNUMBER(SEARCH("whatsapp",LOWER(G4))), ISNUMBER(SEARCH("youtube",LOWER(G4))), ISNUMBER(SEARCH("twitter",LOWER(G4))), ISNUMBER(SEARCH("x.com",LOWER(G4))), ISNUMBER(SEARCH("linkedin",LOWER(G4))), ISNUMBER(SEARCH("linktr.ee",LOWER(G4))), ISNUMBER(SEARCH("g.page",LOWER(G4))), ISNUMBER(SEARCH("maps.app.goo.gl",LOWER(G4))), ISNUMBER(SEARCH("goo.gl",LOWER(G4))) ), "Social Media", "Official Website")) -> Social Media | L4: =IF(E4>=4.5,"Excellent", IF(E4>=4,"Good", IF(E4>=3,"Average","Poor"))) -> Good | M4: =IF(F4>=1000,"1000+ Reviews", IF(F4>=500,"500-999 Reviews", IF(F4>=100,"100-499 Reviews", "Below 100 Reviews"))) -> 100-499 Reviews | N4: =IF(K4="Official Website","Low Opportunity", IF(AND(K4="No Website",E4>=4.5,F4>=500),"Very High Opportunity", IF(AND(K4="No Website",E4>=4.5),"High Opportunity", IF(K4="Social Media","Medium Opportunity","Low Opportunity")))) -> Medium Opportunity
A5: Burari, Delhi | B5: restaurants | C5: Mittal Sweets and Snacks | D5: Kh. No. 828, 100, Futta Main Road, Prem Nagar, Baba Colony, Burari, Delhi, 110084, India | E5: 4.6 | F5: 1276 | G5: https://www.mittalsweetandsnacks.com/ | H5: 098997 73223 | I5: restaurant, gift_shop, banquet_hall, fine_dining_restaurant, swimming_pool, bakery, event_venue, sports_activity_location, service, food_store, store, food, point_of_interest, establishment | J5: =IF(COUNTIFS($C$2:C5,C5,$D$2:D5,D5)=1,"Unique","Duplicate") -> Unique | K5: =IF(TRIM(G5)="","No Website", IF(OR( ISNUMBER(SEARCH("facebook",LOWER(G5))), ISNUMBER(SEARCH("instagram",LOWER(G5))), ISNUMBER(SEARCH("wa.me",LOWER(G5))), ISNUMBER(SEARCH("whatsapp",LOWER(G5))), ISNUMBER(SEARCH("youtube",LOWER(G5))), ISNUMBER(SEARCH("twitter",LOWER(G5))), ISNUMBER(SEARCH("x.com",LOWER(G5))), ISNUMBER(SEARCH("linkedin",LOWER(G5))), ISNUMBER(SEARCH("linktr.ee",LOWER(G5))), ISNUMBER(SEARCH("g.page",LOWER(G5))), ISNUMBER(SEARCH("maps.app.goo.gl",LOWER(G5))), ISNUMBER(SEARCH("goo.gl",LOWER(G5))) ), "Social Media", "Official Website")) -> Official Website | L5: =IF(E5>=4.5,"Excellent", IF(E5>=4,"Good", IF(E5>=3,"Average","Poor"))) -> Excellent | M5: =IF(F5>=1000,"1000+ Reviews", IF(F5>=500,"500-999 Reviews", IF(F5>=100,"100-499 Reviews", "Below 100 Reviews"))) -> 1000+ Reviews | N5: =IF(K5="Official Website","Low Opportunity", IF(AND(K5="No Website",E5>=4.5,F5>=500),"Very High Opportunity", IF(AND(K5="No Website",E5>=4.5),"High Opportunity", IF(K5="Social Media","Medium Opportunity","Low Opportunity")))) -> Low Opportunity
A6: Burari, Delhi | B6: restaurants | C6: Meet and Treat Cafe | D6: Street Number 4, near by Muthoot finance, A-2 Block, Virendar Nagar, Block B, West Sant Nagar, Burari, Delhi, 110084, India | E6: 4.6 | F6: 504 | G6: https://meet-and-treat-cafe.grexa.site/ | H6: 090131 61184 | I6: restaurant, food, point_of_interest, establishment | J6: =IF(COUNTIFS($C$2:C6,C6,$D$2:D6,D6)=1,"Unique","Duplicate") -> Unique | K6: =IF(TRIM(G6)="","No Website", IF(OR( ISNUMBER(SEARCH("facebook",LOWER(G6))), ISNUMBER(SEARCH("instagram",LOWER(G6))), ISNUMBER(SEARCH("wa.me",LOWER(G6))), ISNUMBER(SEARCH("whatsapp",LOWER(G6))), ISNUMBER(SEARCH("youtube",LOWER(G6))), ISNUMBER(SEARCH("twitter",LOWER(G6))), ISNUMBER(SEARCH("x.com",LOWER(G6))), ISNUMBER(SEARCH("linkedin",LOWER(G6))), ISNUMBER(SEARCH("linktr.ee",LOWER(G6))), ISNUMBER(SEARCH("g.page",LOWER(G6))), ISNUMBER(SEARCH("maps.app.goo.gl",LOWER(G6))), ISNUMBER(SEARCH("goo.gl",LOWER(G6))) ), "Social Media", "Official Website")) -> Official Website | L6: =IF(E6>=4.5,"Excellent", IF(E6>=4,"Good", IF(E6>=3,"Average","Poor"))) -> Excellent | M6: =IF(F6>=1000,"1000+ Reviews", IF(F6>=500,"500-999 Reviews", IF(F6>=100,"100-499 Reviews", "Below 100 Reviews"))) -> 500-999 Reviews | N6: =IF(K6="Official Website","Low Opportunity", IF(AND(K6="No Website",E6>=4.5,F6>=500),"Very High Opportunity", IF(AND(K6="No Website",E6>=4.5),"High Opportunity", IF(K6="Social Media","Medium Opportunity","Low Opportunity")))) -> Low Opportunity
A7: Connaught Place, New Delhi | B7: clothing stores | C7: Fashion Craft | D7: Shop no 74, Municipal Market, opp. Pizza Hut, Janpath, Connaught Place, New Delhi, Delhi 110001, India | E7: 5 | F7: 987 | H7: 084474 99885 | I7: clothing_store, wholesaler, store, manufacturer, point_of_interest, establishment | J7: =IF(COUNTIFS($C$2:C7,C7,$D$2:D7,D7)=1,"Unique","Duplicate") -> Unique | K7: =IF(TRIM(G7)="","No Website", IF(OR( ISNUMBER(SEARCH("facebook",LOWER(G7))), ISNUMBER(SEARCH("instagram",LOWER(G7))), ISNUMBER(SEARCH("wa.me",LOWER(G7))), ISNUMBER(SEARCH("whatsapp",LOWER(G7))), ISNUMBER(SEARCH("youtube",LOWER(G7))), ISNUMBER(SEARCH("twitter",LOWER(G7))), ISNUMBER(SEARCH("x.com",LOWER(G7))), ISNUMBER(SEARCH("linkedin",LOWER(G7))), ISNUMBER(SEARCH("linktr.ee",LOWER(G7))), ISNUMBER(SEARCH("g.page",LOWER(G7))), ISNUMBER(SEARCH("maps.app.goo.gl",LOWER(G7))), ISNUMBER(SEARCH("goo.gl",LOWER(G7))) ), "Social Media", "Official Website")) -> No Website | L7: =IF(E7>=4.5,"Excellent", IF(E7>=4,"Good", IF(E7>=3,"Average","Poor"))) -> Excellent | M7: =IF(F7>=1000,"1000+ Reviews", IF(F7>=500,"500-999 Reviews", IF(F7>=100,"100-499 Reviews", "Below 100 Reviews"))) -> 500-999 Reviews | N7: =IF(K7="Official Website","Low Opportunity", IF(AND(K7="No Website",E7>=4.5,F7>=500),"Very High Opportunity", IF(AND(K7="No Website",E7>=4.5),"High Opportunity", IF(K7="Social Media","Medium Opportunity","Low Opportunity")))) -> Very High Opportunity
A8: Burari, Delhi | B8: restaurants | C8: Zaiyka Punjab | D8: Labour chowk, Sant Nagar Marg, Parvatiya Anchal, Block B, Sant Nagar, Burari, New Delhi, Delhi, 110084, India | E8: 3.9 | F8: 1454 | G8: https://zaikarestaurant.org/ | H8: 099901 07009 | I8: pakistani_restaurant, north_indian_restaurant, indian_restaurant, restaurant, food, point_of_interest, establishment | J8: =IF(COUNTIFS($C$2:C8,C8,$D$2:D8,D8)=1,"Unique","Duplicate") -> Unique | K8: =IF(TRIM(G8)="","No Website", IF(OR( ISNUMBER(SEARCH("facebook",LOWER(G8))), ISNUMBER(SEARCH("instagram",LOWER(G8))), ISNUMBER(SEARCH("wa.me",LOWER(G8))), ISNUMBER(SEARCH("whatsapp",LOWER(G8))), ISNUMBER(SEARCH("youtube",LOWER(G8))), ISNUMBER(SEARCH("twitter",LOWER(G8))), ISNUMBER(SEARCH("x.com",LOWER(G8))), ISNUMBER(SEARCH("linkedin",LOWER(G8))), ISNUMBER(SEARCH("linktr.ee",LOWER(G8))), ISNUMBER(SEARCH("g.page",LOWER(G8))), ISNUMBER(SEARCH("maps.app.goo.gl",LOWER(G8))), ISNUMBER(SEARCH("goo.gl",LOWER(G8))) ), "Social Media", "Official Website")) -> Official Website | L8: =IF(E8>=4.5,"Excellent", IF(E8>=4,"Good", IF(E8>=3,"Average","Poor"))) -> Average | M8: =IF(F8>=1000,"1000+ Reviews", IF(F8>=500,"500-999 Reviews", IF(F8>=100,"100-499 Reviews", "Below 100 Reviews"))) -> 1000+ Reviews | N8: =IF(K8="Official Website","Low Opportunity", IF(AND(K8="No Website",E8>=4.5,F8>=500),"Very High Opportunity", IF(AND(K8="No Website",E8>=4.5),"High Opportunity", IF(K8="Social Media","Medium Opportunity","Low Opportunity")))) -> Low Opportunity
A9: Burari, Delhi | B9: restaurants | C9: Utsav Dhaba | D9: Kh.No. 47/1 ,Gali No. 01 , Kaushik Enclave Main, 100ft, Road, opposite Burari Government hospital, Block D, Indraprasth Colony, Burari, Delhi, 110084, India | E9: 4.4 | F9: 193 | H9: 088088 80900 | I9: indian_restaurant, restaurant, food, point_of_interest, establishment | J9: =IF(COUNTIFS($C$2:C9,C9,$D$2:D9,D9)=1,"Unique","Duplicate") -> Unique | K9: =IF(TRIM(G9)="","No Website", IF(OR( ISNUMBER(SEARCH("facebook",LOWER(G9))), ISNUMBER(SEARCH("instagram",LOWER(G9))), ISNUMBER(SEARCH("wa.me",LOWER(G9))), ISNUMBER(SEARCH("whatsapp",LOWER(G9))), ISNUMBER(SEARCH("youtube",LOWER(G9))), ISNUMBER(SEARCH("twitter",LOWER(G9))), ISNUMBER(SEARCH("x.com",LOWER(G9))), ISNUMBER(SEARCH("linkedin",LOWER(G9))), ISNUMBER(SEARCH("linktr.ee",LOWER(G9))), ISNUMBER(SEARCH("g.page",LOWER(G9))), ISNUMBER(SEARCH("maps.app.goo.gl",LOWER(G9))), ISNUMBER(SEARCH("goo.gl",LOWER(G9))) ), "Social Media", "Official Website")) -> No Website | L9: =IF(E9>=4.5,"Excellent", IF(E9>=4,"Good", IF(E9>=3,"Average","Poor"))) -> Good | M9: =IF(F9>=1000,"1000+ Reviews", IF(F9>=500,"500-999 Reviews", IF(F9>=100,"100-499 Reviews", "Below 100 Reviews"))) -> 100-499 Reviews | N9: =IF(K9="Official Website","Low Opportunity", IF(AND(K9="No Website",E9>=4.5,F9>=500),"Very High Opportunity", IF(AND(K9="No Website",E9>=4.5),"High Opportunity", IF(K9="Social Media","Medium Opportunity","Low Opportunity")))) -> Low Opportunity
A10: Burari, Delhi | B10: restaurants | C10: Roms Pizza Burari | D10: 108, 100 Feet Rd, Virendar Nagar, Block B, Sant Nagar, Burari, Delhi, 110084, India | E10: 4.8 | F10: 1520 | G10: https://romspizzaburari.edgeone.app/ | H10: 097187 07077 | I10: pizza_restaurant, restaurant, food, point_of_interest, establishment | J10: =IF(COUNTIFS($C$2:C10,C10,$D$2:D10,D10)=1,"Unique","Duplicate") -> Unique | K10: =IF(TRIM(G10)="","No Website", IF(OR( ISNUMBER(SEARCH("facebook",LOWER(G10))), ISNUMBER(SEARCH("instagram",LOWER(G10))), ISNUMBER(SEARCH("wa.me",LOWER(G10))), ISNUMBER(SEARCH("whatsapp",LOWER(G10))), ISNUMBER(SEARCH("youtube",LOWER(G10))), ISNUMBER(SEARCH("twitter",LOWER(G10))), ISNUMBER(SEARCH("x.com",LOWER(G10))), ISNUMBER(SEARCH("linkedin",LOWER(G10))), ISNUMBER(SEARCH("linktr.ee",LOWER(G10))), ISNUMBER(SEARCH("g.page",LOWER(G10))), ISNUMBER(SEARCH("maps.app.goo.gl",LOWER(G10))), ISNUMBER(SEARCH("goo.gl",LOWER(G10))) ), "Social Media", "Official Website")) -> Official Website | L10: =IF(E10>=4.5,"Excellent", IF(E10>=4,"Good", IF(E10>=3,"Average","Poor"))) -> Excellent | M10: =IF(F10>=1000,"1000+ Reviews", IF(F10>=500,"500-999 Reviews", IF(F10>=100,"100-499 Reviews", "Below 100 Reviews"))) -> 1000+ Reviews | N10: =IF(K10="Official Website","Low Opportunity", IF(AND(K10="No Website",E10>=4.5,F10>=500),"Very High Opportunity", IF(AND(K10="No Website",E10>=4.5),"High Opportunity", IF(K10="Social Media","Medium Opportunity","Low Opportunity")))) -> Low Opportunity
A11: Burari, Delhi | B11: restaurants | C11: Royal Delhi Family Restaurant | D11: Shop No 5 Ground Floor, Main 100, Foota Rd, opp. Raj Mandir, Vijay Colony, Block B, West Sant Nagar, Burari, Delhi, 110084, India | E11: 4.8 | F11: 21 | G11: https://g.page/r/CfFeR9pYUVdqEBM/review | H11: 088008 75466 | I11: restaurant, food, point_of_interest, establishment | J11: =IF(COUNTIFS($C$2:C11,C11,$D$2:D11,D11)=1,"Unique","Duplicate") -> Unique | K11: =IF(TRIM(G11)="","No Website", IF(OR( ISNUMBER(SEARCH("facebook",LOWER(G11))), ISNUMBER(SEARCH("instagram",LOWER(G11))), ISNUMBER(SEARCH("wa.me",LOWER(G11))), ISNUMBER(SEARCH("whatsapp",LOWER(G11))), ISNUMBER(SEARCH("youtube",LOWER(G11))), ISNUMBER(SEARCH("twitter",LOWER(G11))), ISNUMBER(SEARCH("x.com",LOWER(G11))), ISNUMBER(SEARCH("linkedin",LOWER(G11))), ISNUMBER(SEARCH("linktr.ee",LOWER(G11))), ISNUMBER(SEARCH("g.page",LOWER(G11))), ISNUMBER(SEARCH("maps.app.goo.gl",LOWER(G11))), ISNUMBER(SEARCH("goo.gl",LOWER(G11))) ), "Social Media", "Official Website")) -> Social Media | L11: =IF(E11>=4.5,"Excellent", IF(E11>=4,"Good", IF(E11>=3,"Average","Poor"))) -> Excellent | M11: =IF(F11>=1000,"1000+ Reviews", IF(F11>=500,"500-999 Reviews", IF(F11>=100,"100-499 Reviews", "Below 100 Reviews"))) -> Below 100 Reviews | N11: =IF(K11="Official Website","Low Opportunity", IF(AND(K11="No Website",E11>=4.5,F11>=500),"Very High Opportunity", IF(AND(K11="No Website",E11>=4.5),"High Opportunity", IF(K11="Social Media","Medium Opportunity","Low Opportunity")))) -> Medium Opportunity
A12: Burari, Delhi | B12: restaurants | C12: MISHRI LAL JI KI RASOI BURARI | D12: Parvati Anchal, 870/3, Gali No. 2, B Block, Shami Park, Sant Nagar, Burari, Delhi, 110084, India | E12: 4.9 | F12: 43 | G12: https://link.zomato.com/xqzv/rshare?id=11117118730563605 | H12: 070119 39626 | I12: restaurant, food, point_of_interest, establishment | J12: =IF(COUNTIFS($C$2:C12,C12,$D$2:D12,D12)=1,"Unique","Duplicate") -> Unique | K12: =IF(TRIM(G12)="","No Website", IF(OR( ISNUMBER(SEARCH("facebook",LOWER(G12))), ISNUMBER(SEARCH("instagram",LOWER(G12))), ISNUMBER(SEARCH("wa.me",LOWER(G12))), ISNUMBER(SEARCH("whatsapp",LOWER(G12))), ISNUMBER(SEARCH("youtube",LOWER(G12))), ISNUMBER(SEARCH("twitter",LOWER(G12))), ISNUMBER(SEARCH("x.com",LOWER(G12))), ISNUMBER(SEARCH("linkedin",LOWER(G12))), ISNUMBER(SEARCH("linktr.ee",LOWER(G12))), ISNUMBER(SEARCH("g.page",LOWER(G12))), ISNUMBER(SEARCH("maps.app.goo.gl",LOWER(G12))), ISNUMBER(SEARCH("goo.gl",LOWER(G12))) ), "Social Media", "Official Website")) -> Official Website | L12: =IF(E12>=4.5,"Excellent", IF(E12>=4,"Good", IF(E12>=3,"Average","Poor"))) -> Excellent | M12: =IF(F12>=1000,"1000+ Reviews", IF(F12>=500,"500-999 Reviews", IF(F12>=100,"100-499 Reviews", "Below 100 Reviews"))) -> Below 100 Reviews | N12: =IF(K12="Official Website","Low Opportunity", IF(AND(K12="No Website",E12>=4.5,F12>=500),"Very High Opportunity", IF(AND(K12="No Website",E12>=4.5),"High Opportunity", IF(K12="Social Media","Medium Opportunity","Low Opportunity")))) -> Low Opportunity
A13: Burari, Delhi | B13: restaurants | C13: GARHWAL PUNJABI TADKA | D13: Labour Chowk, 100 Feet Rd, Block B, Sant Nagar, Burari, Delhi, 110084, India | E13: 3.7 | F13: 268 | G13: https://garhwalpunjabitadka.co.in/ | H13: 070425 10609 | I13: pakistani_restaurant, north_indian_restaurant, indian_restaurant, restaurant, food, point_of_interest, establishment | J13: =IF(COUNTIFS($C$2:C13,C13,$D$2:D13,D13)=1,"Unique","Duplicate") -> Unique | K13: =IF(TRIM(G13)="","No Website", IF(OR( ISNUMBER(SEARCH("facebook",LOWER(G13))), ISNUMBER(SEARCH("instagram",LOWER(G13))), ISNUMBER(SEARCH("wa.me",LOWER(G13))), ISNUMBER(SEARCH("whatsapp",LOWER(G13))), ISNUMBER(SEARCH("youtube",LOWER(G13))), ISNUMBER(SEARCH("twitter",LOWER(G13))), ISNUMBER(SEARCH("x.com",LOWER(G13))), ISNUMBER(SEARCH("linkedin",LOWER(G13))), ISNUMBER(SEARCH("linktr.ee",LOWER(G13))), ISNUMBER(SEARCH("g.page",LOWER(G13))), ISNUMBER(SEARCH("maps.app.goo.gl",LOWER(G13))), ISNUMBER(SEARCH("goo.gl",LOWER(G13))) ), "Social Media", "Official Website")) -> Official Website | L13: =IF(E13>=4.5,"Excellent", IF(E13>=4,"Good", IF(E13>=3,"Average","Poor"))) -> Average | M13: =IF(F13>=1000,"1000+ Reviews", IF(F13>=500,"500-999 Reviews", IF(F13>=100,"100-499 Reviews", "Below 100 Reviews"))) -> 100-499 Reviews | N13: =IF(K13="Official Website","Low Opportunity", IF(AND(K13="No Website",E13>=4.5,F13>=500),"Very High Opportunity", IF(AND(K13="No Website",E13>=4.5),"High Opportunity", IF(K13="Social Media","Medium Opportunity","Low Opportunity")))) -> Low Opportunity
A14: Burari, Delhi | B14: restaurants | C14: Tasty bite restaurant | D14: Maurya Enclave, Upakar Colony, Burari, New delhi, Delhi, 110084, India | E14: 3.7 | F14: 1127 | H14: 075308 08188 | I14: restaurant, fast_food_restaurant, food, point_of_interest, establishment | J14: =IF(COUNTIFS($C$2:C14,C14,$D$2:D14,D14)=1,"Unique","Duplicate") -> Unique | K14: =IF(TRIM(G14)="","No Website", IF(OR( ISNUMBER(SEARCH("facebook",LOWER(G14))), ISNUMBER(SEARCH("instagram",LOWER(G14))), ISNUMBER(SEARCH("wa.me",LOWER(G14))), ISNUMBER(SEARCH("whatsapp",LOWER(G14))), ISNUMBER(SEARCH("youtube",LOWER(G14))), ISNUMBER(SEARCH("twitter",LOWER(G14))), ISNUMBER(SEARCH("x.com",LOWER(G14))), ISNUMBER(SEARCH("linkedin",LOWER(G14))), ISNUMBER(SEARCH("linktr.ee",LOWER(G14))), ISNUMBER(SEARCH("g.page",LOWER(G14))), ISNUMBER(SEARCH("maps.app.goo.gl",LOWER(G14))), ISNUMBER(SEARCH("goo.gl",LOWER(G14))) ), "Social Media", "Official Website")) -> No Website | L14: =IF(E14>=4.5,"Excellent", IF(E14>=4,"Good", IF(E14>=3,"Average","Poor"))) -> Average | M14: =IF(F14>=1000,"1000+ Reviews", IF(F14>=500,"500-999 Reviews", IF(F14>=100,"100-499 Reviews", "Below 100 Reviews"))) -> 1000+ Reviews | N14: =IF(K14="Official Website","Low Opportunity", IF(AND(K14="No Website",E14>=4.5,F14>=500),"Very High Opportunity", IF(AND(K14="No Website",E14>=4.5),"High Opportunity", IF(K14="Social Media","Medium Opportunity","Low Opportunity")))) -> Low Opportunity
A15: Pitampura, Delhi | B15: mobile shops | C15: GUPTA MOBILE TELECOM | D15: I-262, Block I, Shakurpur Colony, Pitampura, Delhi, 110034, India | E15: 5 | F15: 814 | H15: 078383 30007 | I15: cell_phone_store, electronics_store, store, service, point_of_interest, establishment | J15: =IF(COUNTIFS($C$2:C15,C15,$D$2:D15,D15)=1,"Unique","Duplicate") -> Unique | K15: =IF(TRIM(G15)="","No Website", IF(OR( ISNUMBER(SEARCH("facebook",LOWER(G15))), ISNUMBER(SEARCH("instagram",LOWER(G15))), ISNUMBER(SEARCH("wa.me",LOWER(G15))), ISNUMBER(SEARCH("whatsapp",LOWER(G15))), ISNUMBER(SEARCH("youtube",LOWER(G15))), ISNUMBER(SEARCH("twitter",LOWER(G15))), ISNUMBER(SEARCH("x.com",LOWER(G15))), ISNUMBER(SEARCH("linkedin",LOWER(G15))), ISNUMBER(SEARCH("linktr.ee",LOWER(G15))), ISNUMBER(SEARCH("g.page",LOWER(G15))), ISNUMBER(SEARCH("maps.app.goo.gl",LOWER(G15))), ISNUMBER(SEARCH("goo.gl",LOWER(G15))) ), "Social Media", "Official Website")) -> No Website | L15: =IF(E15>=4.5,"Excellent", IF(E15>=4,"Good", IF(E15>=3,"Average","Poor"))) -> Excellent | M15: =IF(F15>=1000,"1000+ Reviews", IF(F15>=500,"500-999 Reviews", IF(F15>=100,"100-499 Reviews", "Below 100 Reviews"))) -> 500-999 Reviews | N15: =IF(K15="Official Website","Low Opportunity", IF(AND(K15="No Website",E15>=4.5,F15>=500),"Very High Opportunity", IF(AND(K15="No Website",E15>=4.5),"High Opportunity", IF(K15="Social Media","Medium Opportunity","Low Opportunity")))) -> Very High Opportunity
A16: Burari, Delhi | B16: restaurants | C16: Delhi Grillz restaurant | D16: A-9, Extension Colony, Burari, Delhi, 110084, India | E16: 4 | F16: 530 | H16: 098115 11612 | I16: north_indian_restaurant, indian_restaurant, restaurant, food, point_of_interest, establishment | J16: =IF(COUNTIFS($C$2:C16,C16,$D$2:D16,D16)=1,"Unique","Duplicate") -> Unique | K16: =IF(TRIM(G16)="","No Website", IF(OR( ISNUMBER(SEARCH("facebook",LOWER(G16))), ISNUMBER(SEARCH("instagram",LOWER(G16))), ISNUMBER(SEARCH("wa.me",LOWER(G16))), ISNUMBER(SEARCH("whatsapp",LOWER(G16))), ISNUMBER(SEARCH("youtube",LOWER(G16))), ISNUMBER(SEARCH("twitter",LOWER(G16))), ISNUMBER(SEARCH("x.com",LOWER(G16))), ISNUMBER(SEARCH("linkedin",LOWER(G16))), ISNUMBER(SEARCH("linktr.ee",LOWER(G16))), ISNUMBER(SEARCH("g.page",LOWER(G16))), ISNUMBER(SEARCH("maps.app.goo.gl",LOWER(G16))), ISNUMBER(SEARCH("goo.gl",LOWER(G16))) ), "Social Media", "Official Website")) -> No Website | L16: =IF(E16>=4.5,"Excellent", IF(E16>=4,"Good", IF(E16>=3,"Average","Poor"))) -> Good | M16: =IF(F16>=1000,"1000+ Reviews", IF(F16>=500,"500-999 Reviews", IF(F16>=100,"100-499 Reviews", "Below 100 Reviews"))) -> 500-999 Reviews | N16: =IF(K16="Official Website","Low Opportunity", IF(AND(K16="No Website",E16>=4.5,F16>=500),"Very High Opportunity", IF(AND(K16="No Website",E16>=4.5),"High Opportunity", IF(K16="Social Media","Medium Opportunity","Low Opportunity")))) -> Low Opportunity
A17: Kamla Nagar, Delhi | B17: clothing stores | C17: Libas | D17: Shop No. 42, 43, Jawahar Nagar - Malka Ganj Rd, Block UB, Jawahar Nagar, Kamla Nagar, New Delhi, Delhi, 110007, India | E17: 5 | F17: 782 | H17: 099108 53530 | I17: clothing_store, store, point_of_interest, establishment | J17: =IF(COUNTIFS($C$2:C17,C17,$D$2:D17,D17)=1,"Unique","Duplicate") -> Unique | K17: =IF(TRIM(G17)="","No Website", IF(OR( ISNUMBER(SEARCH("facebook",LOWER(G17))), ISNUMBER(SEARCH("instagram",LOWER(G17))), ISNUMBER(SEARCH("wa.me",LOWER(G17))), ISNUMBER(SEARCH("whatsapp",LOWER(G17))), ISNUMBER(SEARCH("youtube",LOWER(G17))), ISNUMBER(SEARCH("twitter",LOWER(G17))), ISNUMBER(SEARCH("x.com",LOWER(G17))), ISNUMBER(SEARCH("linkedin",LOWER(G17))), ISNUMBER(SEARCH("linktr.ee",LOWER(G17))), ISNUMBER(SEARCH("g.page",LOWER(G17))), ISNUMBER(SEARCH("maps.app.goo.gl",LOWER(G17))), ISNUMBER(SEARCH("goo.gl",LOWER(G17))) ), "Social Media", "Official Website")) -> No Website | L17: =IF(E17>=4.5,"Excellent", IF(E17>=4,"Good", IF(E17>=3,"Average","Poor"))) -> Excellent | M17: =IF(F17>=1000,"1000+ Reviews", IF(F17>=500,"500-999 Reviews", IF(F17>=100,"100-499 Reviews", "Below 100 Reviews"))) -> 500-999 Reviews | N17: =IF(K17="Official Website","Low Opportunity", IF(AND(K17="No Website",E17>=4.5,F17>=500),"Very High Opportunity", IF(AND(K17="No Website",E17>=4.5),"High Opportunity", IF(K17="Social Media","Medium Opportunity","Low Opportunity")))) -> Very High Opportunity
A18: Burari, Delhi | B18: restaurants | C18: WAH JI WAH restaurant Burari | D18: Main 100, Kh.no.19/26, Foota Rd, b block, Kaushik Enclave, Shankarpura, Burari, Delhi, 110084, India | E18: 3.7 | F18: 49 | H18: 070110 46566 | I18: restaurant, food, point_of_interest, establishment | J18: =IF(COUNTIFS($C$2:C18,C18,$D$2:D18,D18)=1,"Unique","Duplicate") -> Unique | K18: =IF(TRIM(G18)="","No Website", IF(OR( ISNUMBER(SEARCH("facebook",LOWER(G18))), ISNUMBER(SEARCH("instagram",LOWER(G18))), ISNUMBER(SEARCH("wa.me",LOWER(G18))), ISNUMBER(SEARCH("whatsapp",LOWER(G18))), ISNUMBER(SEARCH("youtube",LOWER(G18))), ISNUMBER(SEARCH("twitter",LOWER(G18))), ISNUMBER(SEARCH("x.com",LOWER(G18))), ISNUMBER(SEARCH("linkedin",LOWER(G18))), ISNUMBER(SEARCH("linktr.ee",LOWER(G18))), ISNUMBER(SEARCH("g.page",LOWER(G18))), ISNUMBER(SEARCH("maps.app.goo.gl",LOWER(G18))), ISNUMBER(SEARCH("goo.gl",LOWER(G18))) ), "Social Media", "Official Website")) -> No Website | L18: =IF(E18>=4.5,"Excellent", IF(E18>=4,"Good", IF(E18>=3,"Average","Poor"))) -> Average | M18: =IF(F18>=1000,"1000+ Reviews", IF(F18>=500,"500-999 Reviews", IF(F18>=100,"100-499 Reviews", "Below 100 Reviews"))) -> Below 100 Reviews | N18: =IF(K18="Official Website","Low Opportunity", IF(AND(K18="No Website",E18>=4.5,F18>=500),"Very High Opportunity", IF(AND(K18="No Website",E18>=4.5),"High Opportunity", IF(K18="Social Media","Medium Opportunity","Low Opportunity")))) -> Low Opportunity
A19: Burari, Delhi | B19: restaurants | C19: JAI SHREE RESTAURANT BANQUET HOTEL | D19: Nathupura Rd, Saroop Vihar, A Block, Indraprasth Colony, Burari, Delhi, 110084, India | E19: 4.1 | F19: 1129 | H19: 073037 20692 | I19: vegetarian_restaurant, banquet_hall, north_indian_restaurant, south_indian_restaurant, hotel, indian_restaurant, chinese_restaurant, event_venue, lodging, restaurant, food, point_of_interest, establishment | J19: =IF(COUNTIFS($C$2:C19,C19,$D$2:D19,D19)=1,"Unique","Duplicate") -> Unique | K19: =IF(TRIM(G19)="","No Website", IF(OR( ISNUMBER(SEARCH("facebook",LOWER(G19))), ISNUMBER(SEARCH("instagram",LOWER(G19))), ISNUMBER(SEARCH("wa.me",LOWER(G19))), ISNUMBER(SEARCH("whatsapp",LOWER(G19))), ISNUMBER(SEARCH("youtube",LOWER(G19))), ISNUMBER(SEARCH("twitter",LOWER(G19))), ISNUMBER(SEARCH("x.com",LOWER(G19))), ISNUMBER(SEARCH("linkedin",LOWER(G19))), ISNUMBER(SEARCH("linktr.ee",LOWER(G19))), ISNUMBER(SEARCH("g.page",LOWER(G19))), ISNUMBER(SEARCH("maps.app.goo.gl",LOWER(G19))), ISNUMBER(SEARCH("goo.gl",LOWER(G19))) ), "Social Media", "Official Website")) -> No Website | L19: =IF(E19>=4.5,"Excellent", IF(E19>=4,"Good", IF(E19>=3,"Average","Poor"))) -> Good | M19: =IF(F19>=1000,"1000+ Reviews", IF(F19>=500,"500-999 Reviews", IF(F19>=100,"100-499 Reviews", "Below 100 Reviews"))) -> 1000+ Reviews | N19: =IF(K19="Official Website","Low Opportunity", IF(AND(K19="No Website",E19>=4.5,F19>=500),"Very High Opportunity", IF(AND(K19="No Website",E19>=4.5),"High Opportunity", IF(K19="Social Media","Medium Opportunity","Low Opportunity")))) -> Low Opportunity
A20: Burari, Delhi | B20: restaurants | C20: Burari 84, The Authentic Indian Kitchen | D20: Shop No 4, Ground Floor, Vinayak Apartments, Vijay Colony, Block B, Sant Nagar, Burari, New Delhi, Delhi, 110084, India | E20: 3.2 | F20: 52 | H20: 085880 03009 | I20: pizza_restaurant, restaurant, food, point_of_interest, establishment | J20: =IF(COUNTIFS($C$2:C20,C20,$D$2:D20,D20)=1,"Unique","Duplicate") -> Unique | K20: =IF(TRIM(G20)="","No Website", IF(OR( ISNUMBER(SEARCH("facebook",LOWER(G20))), ISNUMBER(SEARCH("instagram",LOWER(G20))), ISNUMBER(SEARCH("wa.me",LOWER(G20))), ISNUMBER(SEARCH("whatsapp",LOWER(G20))), ISNUMBER(SEARCH("youtube",LOWER(G20))), ISNUMBER(SEARCH("twitter",LOWER(G20))), ISNUMBER(SEARCH("x.com",LOWER(G20))), ISNUMBER(SEARCH("linkedin",LOWER(G20))), ISNUMBER(SEARCH("linktr.ee",LOWER(G20))), ISNUMBER(SEARCH("g.page",LOWER(G20))), ISNUMBER(SEARCH("maps.app.goo.gl",LOWER(G20))), ISNUMBER(SEARCH("goo.gl",LOWER(G20))) ), "Social Media", "Official Website")) -> No Website | L20: =IF(E20>=4.5,"Excellent", IF(E20>=4,"Good", IF(E20>=3,"Average","Poor"))) -> Average | M20: =IF(F20>=1000,"1000+ Reviews", IF(F20>=500,"500-999 Reviews", IF(F20>=100,"100-499 Reviews", "Below 100 Reviews"))) -> Below 100 Reviews | N20: =IF(K20="Official Website","Low Opportunity", IF(AND(K20="No Website",E20>=4.5,F20>=500),"Very High Opportunity", IF(AND(K20="No Website",E20>=4.5),"High Opportunity", IF(K20="Social Media","Medium Opportunity","Low Opportunity")))) -> Low Opportunity
A21: Mayur Vihar, Delhi | B21: bakeries | C21: Bakingham - The Bake Town | D21: Shop No. 18 & 25, DDA LSC, Block A, Acharya Niketan, Mayur Vihar, Delhi, 110091, India | E21: 5 | F21: 679 | H21: 093157 86908 | I21: bakery, food_store, store, food, point_of_interest, establishment | J21: =IF(COUNTIFS($C$2:C21,C21,$D$2:D21,D21)=1,"Unique","Duplicate") -> Unique | K21: =IF(TRIM(G21)="","No Website", IF(OR( ISNUMBER(SEARCH("facebook",LOWER(G21))), ISNUMBER(SEARCH("instagram",LOWER(G21))), ISNUMBER(SEARCH("wa.me",LOWER(G21))), ISNUMBER(SEARCH("whatsapp",LOWER(G21))), ISNUMBER(SEARCH("youtube",LOWER(G21))), ISNUMBER(SEARCH("twitter",LOWER(G21))), ISNUMBER(SEARCH("x.com",LOWER(G21))), ISNUMBER(SEARCH("linkedin",LOWER(G21))), ISNUMBER(SEARCH("linktr.ee",LOWER(G21))), ISNUMBER(SEARCH("g.page",LOWER(G21))), ISNUMBER(SEARCH("maps.app.goo.gl",LOWER(G21))), ISNUMBER(SEARCH("goo.gl",LOWER(G21))) ), "Social Media", "Official Website")) -> No Website | L21: =IF(E21>=4.5,"Excellent", IF(E21>=4,"Good", IF(E21>=3,"Average","Poor"))) -> Excellent | M21: =IF(F21>=1000,"1000+ Reviews", IF(F21>=500,"500-999 Reviews", IF(F21>=100,"100-499 Reviews", "Below 100 Reviews"))) -> 500-999 Reviews | N21: =IF(K21="Official Website","Low Opportunity", IF(AND(K21="No Website",E21>=4.5,F21>=500),"Very High Opportunity", IF(AND(K21="No Website",E21>=4.5),"High Opportunity", IF(K21="Social Media","Medium Opportunity","Low Opportunity")))) -> Very High Opportunity
A22: Burari, Delhi | B22: cafes | C22: Tealogy Cafe Burari | D22: Khasra 137/23/2/2 Shop number 1, gate no 2, 100 Feet Rd, behind Rani public school, A-2 Block, Block B, Sant Nagar, Burari, New Delhi, Delhi, 110084, India | E22: 4.8 | F22: 641 | G22: https://tealogy.in/city/tea-cafe-franchise-burari | H22: 098211 94456 | I22: cafe, food, point_of_interest, establishment | J22: =IF(COUNTIFS($C$2:C22,C22,$D$2:D22,D22)=1,"Unique","Duplicate") -> Unique | K22: =IF(TRIM(G22)="","No Website", IF(OR( ISNUMBER(SEARCH("facebook",LOWER(G22))), ISNUMBER(SEARCH("instagram",LOWER(G22))), ISNUMBER(SEARCH("wa.me",LOWER(G22))), ISNUMBER(SEARCH("whatsapp",LOWER(G22))), ISNUMBER(SEARCH("youtube",LOWER(G22))), ISNUMBER(SEARCH("twitter",LOWER(G22))), ISNUMBER(SEARCH("x.com",LOWER(G22))), ISNUMBER(SEARCH("linkedin",LOWER(G22))), ISNUMBER(SEARCH("linktr.ee",LOWER(G22))), ISNUMBER(SEARCH("g.page",LOWER(G22))), ISNUMBER(SEARCH("maps.app.goo.gl",LOWER(G22))), ISNUMBER(SEARCH("goo.gl",LOWER(G22))) ), "Social Media", "Official Website")) -> Official Website | L22: =IF(E22>=4.5,"Excellent", IF(E22>=4,"Good", IF(E22>=3,"Average","Poor"))) -> Excellent | M22: =IF(F22>=1000,"1000+ Reviews", IF(F22>=500,"500-999 Reviews", IF(F22>=100,"100-499 Reviews", "Below 100 Reviews"))) -> 500-999 Reviews | N22: =IF(K22="Official Website","Low Opportunity", IF(AND(K22="No Website",E22>=4.5,F22>=500),"Very High Opportunity", IF(AND(K22="No Website",E22>=4.5),"High Opportunity", IF(K22="Social Media","Medium Opportunity","Low Opportunity")))) -> Low Opportunity
A23: Kalkaji, Delhi | B23: jewellery shops | C23: GURU NANAK GEMS & JEWELS | D23: 339, Gali Number 4, Govind Puri, Kalkaji, New Delhi, Delhi 110019, India | E23: 5 | F23: 654 | H23: 078385 45144 | I23: jewelry_store, store, point_of_interest, establishment | J23: =IF(COUNTIFS($C$2:C23,C23,$D$2:D23,D23)=1,"Unique","Duplicate") -> Unique | K23: =IF(TRIM(G23)="","No Website", IF(OR( ISNUMBER(SEARCH("facebook",LOWER(G23))), ISNUMBER(SEARCH("instagram",LOWER(G23))), ISNUMBER(SEARCH("wa.me",LOWER(G23))), ISNUMBER(SEARCH("whatsapp",LOWER(G23))), ISNUMBER(SEARCH("youtube",LOWER(G23))), ISNUMBER(SEARCH("twitter",LOWER(G23))), ISNUMBER(SEARCH("x.com",LOWER(G23))), ISNUMBER(SEARCH("linkedin",LOWER(G23))), ISNUMBER(SEARCH("linktr.ee",LOWER(G23))), ISNUMBER(SEARCH("g.page",LOWER(G23))), ISNUMBER(SEARCH("maps.app.goo.gl",LOWER(G23))), ISNUMBER(SEARCH("goo.gl",LOWER(G23))) ), "Social Media", "Official Website")) -> No Website | L23: =IF(E23>=4.5,"Excellent", IF(E23>=4,"Good", IF(E23>=3,"Average","Poor"))) -> Excellent | M23: =IF(F23>=1000,"1000+ Reviews", IF(F23>=500,"500-999 Reviews", IF(F23>=100,"100-499 Reviews", "Below 100 Reviews"))) -> 500-999 Reviews | N23: =IF(K23="Official Website","Low Opportunity", IF(AND(K23="No Website",E23>=4.5,F23>=500),"Very High Opportunity", IF(AND(K23="No Website",E23>=4.5),"High Opportunity", IF(K23="Social Media","Medium Opportunity","Low Opportunity")))) -> Very High Opportunity
A24: Burari, Delhi | B24: cafes | C24: Delhi Foodie Cafe (DFC) | D24: chowk, Burari, Delhi, 110084, India | E24: 4.4 | F24: 57 | H24: 099582 49957 | I24: restaurant, food, point_of_interest, establishment | J24: =IF(COUNTIFS($C$2:C24,C24,$D$2:D24,D24)=1,"Unique","Duplicate") -> Unique | K24: =IF(TRIM(G24)="","No Website", IF(OR( ISNUMBER(SEARCH("facebook",LOWER(G24))), ISNUMBER(SEARCH("instagram",LOWER(G24))), ISNUMBER(SEARCH("wa.me",LOWER(G24))), ISNUMBER(SEARCH("whatsapp",LOWER(G24))), ISNUMBER(SEARCH("youtube",LOWER(G24))), ISNUMBER(SEARCH("twitter",LOWER(G24))), ISNUMBER(SEARCH("x.com",LOWER(G24))), ISNUMBER(SEARCH("linkedin",LOWER(G24))), ISNUMBER(SEARCH("linktr.ee",LOWER(G24))), ISNUMBER(SEARCH("g.page",LOWER(G24))), ISNUMBER(SEARCH("maps.app.goo.gl",LOWER(G24))), ISNUMBER(SEARCH("goo.gl",LOWER(G24))) ), "Social Media", "Official Website")) -> No Website | L24: =IF(E24>=4.5,"Excellent", IF(E24>=4,"Good", IF(E24>=3,"Average","Poor"))) -> Good | M24: =IF(F24>=1000,"1000+ Reviews", IF(F24>=500,"500-999 Reviews", IF(F24>=100,"100-499 Reviews", "Below 100 Reviews"))) -> Below 100 Reviews | N24: =IF(K24="Official Website","Low Opportunity", IF(AND(K24="No Website",E24>=4.5,F24>=500),"Very High Opportunity", IF(AND(K24="No Website",E24>=4.5),"High Opportunity", IF(K24="Social Media","Medium Opportunity","Low Opportunity")))) -> Low Opportunity
A25: Uttam Nagar, Delhi | B25: tutoring centers | C25: Mathematics Specialist- Dwar (@RatanKumarGupta) | D25: A-13, Shish Ram Park, Block C, Uttam Nagar East, Uttam Nagar, New Delhi, Delhi, 110059, India | E25: 5 | F25: 516 | H25: 095555 55136 | I25: point_of_interest, establishment | J25: =IF(COUNTIFS($C$2:C25,C25,$D$2:D25,D25)=1,"Unique","Duplicate") -> Unique | K25: =IF(TRIM(G25)="","No Website", IF(OR( ISNUMBER(SEARCH("facebook",LOWER(G25))), ISNUMBER(SEARCH("instagram",LOWER(G25))), ISNUMBER(SEARCH("wa.me",LOWER(G25))), ISNUMBER(SEARCH("whatsapp",LOWER(G25))), ISNUMBER(SEARCH("youtube",LOWER(G25))), ISNUMBER(SEARCH("twitter",LOWER(G25))), ISNUMBER(SEARCH("x.com",LOWER(G25))), ISNUMBER(SEARCH("linkedin",LOWER(G25))), ISNUMBER(SEARCH("linktr.ee",LOWER(G25))), ISNUMBER(SEARCH("g.page",LOWER(G25))), ISNUMBER(SEARCH("maps.app.goo.gl",LOWER(G25))), ISNUMBER(SEARCH("goo.gl",LOWER(G25))) ), "Social Media", "Official Website")) -> No Website | L25: =IF(E25>=4.5,"Excellent", IF(E25>=4,"Good", IF(E25>=3,"Average","Poor"))) -> Excellent | M25: =IF(F25>=1000,"1000+ Reviews", IF(F25>=500,"500-999 Reviews", IF(F25>=100,"100-499 Reviews", "Below 100 Reviews"))) -> 500-999 Reviews | N25: =IF(K25="Official Website","Low Opportunity", IF(AND(K25="No Website",E25>=4.5,F25>=500),"Very High Opportunity", IF(AND(K25="No Website",E25>=4.5),"High Opportunity", IF(K25="Social Media","Medium Opportunity","Low Opportunity")))) -> Very High Opportunity
A26: Burari, Delhi | B26: cafes | C26: The old smoke cafe | D26: 109, Sant Nagar Marg, Block B, Sant Nagar, Burari, Delhi, 110084, India | E26: 3.4 | F26: 97 | I26: bar, point_of_interest, establishment | J26: =IF(COUNTIFS($C$2:C26,C26,$D$2:D26,D26)=1,"Unique","Duplicate") -> Unique | K26: =IF(TRIM(G26)="","No Website", IF(OR( ISNUMBER(SEARCH("facebook",LOWER(G26))), ISNUMBER(SEARCH("instagram",LOWER(G26))), ISNUMBER(SEARCH("wa.me",LOWER(G26))), ISNUMBER(SEARCH("whatsapp",LOWER(G26))), ISNUMBER(SEARCH("youtube",LOWER(G26))), ISNUMBER(SEARCH("twitter",LOWER(G26))), ISNUMBER(SEARCH("x.com",LOWER(G26))), ISNUMBER(SEARCH("linkedin",LOWER(G26))), ISNUMBER(SEARCH("linktr.ee",LOWER(G26))), ISNUMBER(SEARCH("g.page",LOWER(G26))), ISNUMBER(SEARCH("maps.app.goo.gl",LOWER(G26))), ISNUMBER(SEARCH("goo.gl",LOWER(G26))) ), "Social Media", "Official Website")) -> No Website | L26: =IF(E26>=4.5,"Excellent", IF(E26>=4,"Good", IF(E26>=3,"Average","Poor"))) -> Average | M26: =IF(F26>=1000,"1000+ Reviews", IF(F26>=500,"500-999 Reviews", IF(F26>=100,"100-499 Reviews", "Below 100 Reviews"))) -> Below 100 Reviews | N26: =IF(K26="Official Website","Low Opportunity", IF(AND(K26="No Website",E26>=4.5,F26>=500),"Very High Opportunity", IF(AND(K26="No Website",E26>=4.5),"High Opportunity", IF(K26="Social Media","Medium Opportunity","Low Opportunity")))) -> Low Opportunity
A27: Burari, Delhi | B27: cafes | C27: The Delicious Cafe | D27: 1st floor, CHARAN SINGH PLAZA, Main 100, Futa Road, opposite kapil Public school, near Shalimar Palace, Conductor Colony, Burari Garhi, Burari, Delhi, 110084, India | E27: 4.4 | F27: 39 | G27: https://thedeliciouscafe.landinghero.app/ | H27: 088511 59031 | I27: restaurant, cafe, food, point_of_interest, establishment | J27: =IF(COUNTIFS($C$2:C27,C27,$D$2:D27,D27)=1,"Unique","Duplicate") -> Unique | K27: =IF(TRIM(G27)="","No Website", IF(OR( ISNUMBER(SEARCH("facebook",LOWER(G27))), ISNUMBER(SEARCH("instagram",LOWER(G27))), ISNUMBER(SEARCH("wa.me",LOWER(G27))), ISNUMBER(SEARCH("whatsapp",LOWER(G27))), ISNUMBER(SEARCH("youtube",LOWER(G27))), ISNUMBER(SEARCH("twitter",LOWER(G27))), ISNUMBER(SEARCH("x.com",LOWER(G27))), ISNUMBER(SEARCH("linkedin",LOWER(G27))), ISNUMBER(SEARCH("linktr.ee",LOWER(G27))), ISNUMBER(SEARCH("g.page",LOWER(G27))), ISNUMBER(SEARCH("maps.app.goo.gl",LOWER(G27))), ISNUMBER(SEARCH("goo.gl",LOWER(G27))) ), "Social Media", "Official Website")) -> Official Website | L27: =IF(E27>=4.5,"Excellent", IF(E27>=4,"Good", IF(E27>=3,"Average","Poor"))) -> Good | M27: =IF(F27>=1000,"1000+ Reviews", IF(F27>=500,"500-999 Reviews", IF(F27>=100,"100-499 Reviews", "Below 100 Reviews"))) -> Below 100 Reviews | N27: =IF(K27="Official Website","Low Opportunity", IF(AND(K27="No Website",E27>=4.5,F27>=500),"Very High Opportunity", IF(AND(K27="No Website",E27>=4.5),"High Opportunity", IF(K27="Social Media","Medium Opportunity","Low Opportunity")))) -> Low Opportunity
A28: Burari, Delhi | B28: cafes | C28: URBAN EATS CAFE | D28: House Number 1 Gali Number 20 Block 8A Swami dayanand Colony, On, Oscar Public School Rd, Block 8A, Kaushik Enclave, Swami Dayanand Enclave, Burari, Delhi, 110084, India | E28: 4.9 | F28: 123 | G28: https://urban-eats-cafe.grexa.site/ | H28: 083768 56474 | I28: food_court, cafe, fast_food_restaurant, chinese_restaurant, restaurant, food, point_of_interest, establishment | J28: =IF(COUNTIFS($C$2:C28,C28,$D$2:D28,D28)=1,"Unique","Duplicate") -> Unique | K28: =IF(TRIM(G28)="","No Website", IF(OR( ISNUMBER(SEARCH("facebook",LOWER(G28))), ISNUMBER(SEARCH("instagram",LOWER(G28))), ISNUMBER(SEARCH("wa.me",LOWER(G28))), ISNUMBER(SEARCH("whatsapp",LOWER(G28))), ISNUMBER(SEARCH("youtube",LOWER(G28))), ISNUMBER(SEARCH("twitter",LOWER(G28))), ISNUMBER(SEARCH("x.com",LOWER(G28))), ISNUMBER(SEARCH("linkedin",LOWER(G28))), ISNUMBER(SEARCH("linktr.ee",LOWER(G28))), ISNUMBER(SEARCH("g.page",LOWER(G28))), ISNUMBER(SEARCH("maps.app.goo.gl",LOWER(G28))), ISNUMBER(SEARCH("goo.gl",LOWER(G28))) ), "Social Media", "Official Website")) -> Official Website | L28: =IF(E28>=4.5,"Excellent", IF(E28>=4,"Good", IF(E28>=3,"Average","Poor"))) -> Excellent | M28: =IF(F28>=1000,"1000+ Reviews", IF(F28>=500,"500-999 Reviews", IF(F28>=100,"100-499 Reviews", "Below 100 Reviews"))) -> 100-499 Reviews | N28: =IF(K28="Official Website","Low Opportunity", IF(AND(K28="No Website",E28>=4.5,F28>=500),"Very High Opportunity", IF(AND(K28="No Website",E28>=4.5),"High Opportunity", IF(K28="Social Media","Medium Opportunity","Low Opportunity")))) -> Low Opportunity
A29: Burari, Delhi | B29: salons | C29: AD BEAUTY LOUNGE LADIES PARLOUR | D29: Gali Number 8, Block B, Sant Nagar, Burari, Delhi, 110084, India | E29: 5 | F29: 506 | H29: 081788 66123 | I29: beauty_salon, point_of_interest, service, establishment | J29: =IF(COUNTIFS($C$2:C29,C29,$D$2:D29,D29)=1,"Unique","Duplicate") -> Unique | K29: =IF(TRIM(G29)="","No Website", IF(OR( ISNUMBER(SEARCH("facebook",LOWER(G29))), ISNUMBER(SEARCH("instagram",LOWER(G29))), ISNUMBER(SEARCH("wa.me",LOWER(G29))), ISNUMBER(SEARCH("whatsapp",LOWER(G29))), ISNUMBER(SEARCH("youtube",LOWER(G29))), ISNUMBER(SEARCH("twitter",LOWER(G29))), ISNUMBER(SEARCH("x.com",LOWER(G29))), ISNUMBER(SEARCH("linkedin",LOWER(G29))), ISNUMBER(SEARCH("linktr.ee",LOWER(G29))), ISNUMBER(SEARCH("g.page",LOWER(G29))), ISNUMBER(SEARCH("maps.app.goo.gl",LOWER(G29))), ISNUMBER(SEARCH("goo.gl",LOWER(G29))) ), "Social Media", "Official Website")) -> No Website | L29: =IF(E29>=4.5,"Excellent", IF(E29>=4,"Good", IF(E29>=3,"Average","Poor"))) -> Excellent | M29: =IF(F29>=1000,"1000+ Reviews", IF(F29>=500,"500-999 Reviews", IF(F29>=100,"100-499 Reviews", "Below 100 Reviews"))) -> 500-999 Reviews | N29: =IF(K29="Official Website","Low Opportunity", IF(AND(K29="No Website",E29>=4.5,F29>=500),"Very High Opportunity", IF(AND(K29="No Website",E29>=4.5),"High Opportunity", IF(K29="Social Media","Medium Opportunity","Low Opportunity")))) -> Very High Opportunity
A30: Mukherjee Nagar, Delhi | B30: tutoring centers | C30: Maths Mantra Best Maths Institute(Maths by Puneet chaudhary) | D30: Shop No-1, building 29/30, jaina complex, dr. Mukherjee nagar_09, near Batra Cinema, Mukherjee Nagar, New Delhi, Delhi, 110033, India | E30: 5 | F30: 499 | H30: 099177 77707 | I30: educational_institution, point_of_interest, establishment | J30: =IF(COUNTIFS($C$2:C30,C30,$D$2:D30,D30)=1,"Unique","Duplicate") -> Unique | K30: =IF(TRIM(G30)="","No Website", IF(OR( ISNUMBER(SEARCH("facebook",LOWER(G30))), ISNUMBER(SEARCH("instagram",LOWER(G30))), ISNUMBER(SEARCH("wa.me",LOWER(G30))), ISNUMBER(SEARCH("whatsapp",LOWER(G30))), ISNUMBER(SEARCH("youtube",LOWER(G30))), ISNUMBER(SEARCH("twitter",LOWER(G30))), ISNUMBER(SEARCH("x.com",LOWER(G30))), ISNUMBER(SEARCH("linkedin",LOWER(G30))), ISNUMBER(SEARCH("linktr.ee",LOWER(G30))), ISNUMBER(SEARCH("g.page",LOWER(G30))), ISNUMBER(SEARCH("maps.app.goo.gl",LOWER(G30))), ISNUMBER(SEARCH("goo.gl",LOWER(G30))) ), "Social Media", "Official Website")) -> No Website | L30: =IF(E30>=4.5,"Excellent", IF(E30>=4,"Good", IF(E30>=3,"Average","Poor"))) -> Excellent | M30: =IF(F30>=1000,"1000+ Reviews", IF(F30>=500,"500-999 Reviews", IF(F30>=100,"100-499 Reviews", "Below 100 Reviews"))) -> 100-499 Reviews | N30: =IF(K30="Official Website","Low Opportunity", IF(AND(K30="No Website",E30>=4.5,F30>=500),"Very High Opportunity", IF(AND(K30="No Website",E30>=4.5),"High Opportunity", IF(K30="Social Media","Medium Opportunity","Low Opportunity")))) -> High Opportunity
A31: Mukherjee Nagar, Delhi | B31: tutoring centers | C31: Shresth PCS Academy, Best PCS Test Series Coaching in Mukharjee nagar delhi | D31: 2nd floor, Mukherjee Tower, near Satija Building, Mukherjee Nagar, Delhi, 110033, India | E31: 5 | F31: 447 | H31: 093138 83336 | I31: educational_institution, point_of_interest, establishment | J31: =IF(COUNTIFS($C$2:C31,C31,$D$2:D31,D31)=1,"Unique","Duplicate") -> Unique | K31: =IF(TRIM(G31)="","No Website", IF(OR( ISNUMBER(SEARCH("facebook",LOWER(G31))), ISNUMBER(SEARCH("instagram",LOWER(G31))), ISNUMBER(SEARCH("wa.me",LOWER(G31))), ISNUMBER(SEARCH("whatsapp",LOWER(G31))), ISNUMBER(SEARCH("youtube",LOWER(G31))), ISNUMBER(SEARCH("twitter",LOWER(G31))), ISNUMBER(SEARCH("x.com",LOWER(G31))), ISNUMBER(SEARCH("linkedin",LOWER(G31))), ISNUMBER(SEARCH("linktr.ee",LOWER(G31))), ISNUMBER(SEARCH("g.page",LOWER(G31))), ISNUMBER(SEARCH("maps.app.goo.gl",LOWER(G31))), ISNUMBER(SEARCH("goo.gl",LOWER(G31))) ), "Social Media", "Official Website")) -> No Website | L31: =IF(E31>=4.5,"Excellent", IF(E31>=4,"Good", IF(E31>=3,"Average","Poor"))) -> Excellent | M31: =IF(F31>=1000,"1000+ Reviews", IF(F31>=500,"500-999 Reviews", IF(F31>=100,"100-499 Reviews", "Below 100 Reviews"))) -> 100-499 Reviews | N31: =IF(K31="Official Website","Low Opportunity", IF(AND(K31="No Website",E31>=4.5,F31>=500),"Very High Opportunity", IF(AND(K31="No Website",E31>=4.5),"High Opportunity", IF(K31="Social Media","Medium Opportunity","Low Opportunity")))) -> High Opportunity
A32: Preet Vihar, Delhi | B32: electronics shops | C32: SHREE BALAJI ELECTRONICS | D32: Chauhan Tower, A-25, Vihar Road, Madhu Vihar, I.P.Extension, Patparganj, New Delhi, Delhi, 110092, India | E32: 5 | F32: 423 | H32: 096676 32924 | I32: wholesaler, point_of_interest, establishment | J32: =IF(COUNTIFS($C$2:C32,C32,$D$2:D32,D32)=1,"Unique","Duplicate") -> Unique | K32: =IF(TRIM(G32)="","No Website", IF(OR( ISNUMBER(SEARCH("facebook",LOWER(G32))), ISNUMBER(SEARCH("instagram",LOWER(G32))), ISNUMBER(SEARCH("wa.me",LOWER(G32))), ISNUMBER(SEARCH("whatsapp",LOWER(G32))), ISNUMBER(SEARCH("youtube",LOWER(G32))), ISNUMBER(SEARCH("twitter",LOWER(G32))), ISNUMBER(SEARCH("x.com",LOWER(G32))), ISNUMBER(SEARCH("linkedin",LOWER(G32))), ISNUMBER(SEARCH("linktr.ee",LOWER(G32))), ISNUMBER(SEARCH("g.page",LOWER(G32))), ISNUMBER(SEARCH("maps.app.goo.gl",LOWER(G32))), ISNUMBER(SEARCH("goo.gl",LOWER(G32))) ), "Social Media", "Official Website")) -> No Website | L32: =IF(E32>=4.5,"Excellent", IF(E32>=4,"Good", IF(E32>=3,"Average","Poor"))) -> Excellent | M32: =IF(F32>=1000,"1000+ Reviews", IF(F32>=500,"500-999 Reviews", IF(F32>=100,"100-499 Reviews", "Below 100 Reviews"))) -> 100-499 Reviews | N32: =IF(K32="Official Website","Low Opportunity", IF(AND(K32="No Website",E32>=4.5,F32>=500),"Very High Opportunity", IF(AND(K32="No Website",E32>=4.5),"High Opportunity", IF(K32="Social Media","Medium Opportunity","Low Opportunity")))) -> High Opportunity
A33: Connaught Place, New Delhi | B33: mobile shops | C33: Hotspot Mobile Store | D33: No E21, Ground Floor, Maharaja Agrasen Marg, Block E, Kamla Nagar, New Delhi, Delhi, 110007, India | E33: 5 | F33: 417 | H33: 070423 43404 | I33: cell_phone_store, store, point_of_interest, establishment | J33: =IF(COUNTIFS($C$2:C33,C33,$D$2:D33,D33)=1,"Unique","Duplicate") -> Unique | K33: =IF(TRIM(G33)="","No Website", IF(OR( ISNUMBER(SEARCH("facebook",LOWER(G33))), ISNUMBER(SEARCH("instagram",LOWER(G33))), ISNUMBER(SEARCH("wa.me",LOWER(G33))), ISNUMBER(SEARCH("whatsapp",LOWER(G33))), ISNUMBER(SEARCH("youtube",LOWER(G33))), ISNUMBER(SEARCH("twitter",LOWER(G33))), ISNUMBER(SEARCH("x.com",LOWER(G33))), ISNUMBER(SEARCH("linkedin",LOWER(G33))), ISNUMBER(SEARCH("linktr.ee",LOWER(G33))), ISNUMBER(SEARCH("g.page",LOWER(G33))), ISNUMBER(SEARCH("maps.app.goo.gl",LOWER(G33))), ISNUMBER(SEARCH("goo.gl",LOWER(G33))) ), "Social Media", "Official Website")) -> No Website | L33: =IF(E33>=4.5,"Excellent", IF(E33>=4,"Good", IF(E33>=3,"Average","Poor"))) -> Excellent | M33: =IF(F33>=1000,"1000+ Reviews", IF(F33>=500,"500-999 Reviews", IF(F33>=100,"100-499 Reviews", "Below 100 Reviews"))) -> 100-499 Reviews | N33: =IF(K33="Official Website","Low Opportunity", IF(AND(K33="No Website",E33>=4.5,F33>=500),"Very High Opportunity", IF(AND(K33="No Website",E33>=4.5),"High Opportunity", IF(K33="Social Media","Medium Opportunity","Low Opportunity")))) -> High Opportunity
A34: Burari, Delhi | B34: cafes | C34: Le Food Gallery | D34: 701, Main Burari Chowk, near Union Bank, Conductor Colony, Baba Colony, Burari, Delhi, 110084, India | E34: 4.4 | F34: 33 | H34: 099107 23448 | I34: cafe, restaurant, food, point_of_interest, establishment | J34: =IF(COUNTIFS($C$2:C34,C34,$D$2:D34,D34)=1,"Unique","Duplicate") -> Unique | K34: =IF(TRIM(G34)="","No Website", IF(OR( ISNUMBER(SEARCH("facebook",LOWER(G34))), ISNUMBER(SEARCH("instagram",LOWER(G34))), ISNUMBER(SEARCH("wa.me",LOWER(G34))), ISNUMBER(SEARCH("whatsapp",LOWER(G34))), ISNUMBER(SEARCH("youtube",LOWER(G34))), ISNUMBER(SEARCH("twitter",LOWER(G34))), ISNUMBER(SEARCH("x.com",LOWER(G34))), ISNUMBER(SEARCH("linkedin",LOWER(G34))), ISNUMBER(SEARCH("linktr.ee",LOWER(G34))), ISNUMBER(SEARCH("g.page",LOWER(G34))), ISNUMBER(SEARCH("maps.app.goo.gl",LOWER(G34))), ISNUMBER(SEARCH("goo.gl",LOWER(G34))) ), "Social Media", "Official Website")) -> No Website | L34: =IF(E34>=4.5,"Excellent", IF(E34>=4,"Good", IF(E34>=3,"Average","Poor"))) -> Good | M34: =IF(F34>=1000,"1000+ Reviews", IF(F34>=500,"500-999 Reviews", IF(F34>=100,"100-499 Reviews", "Below 100 Reviews"))) -> Below 100 Reviews | N34: =IF(K34="Official Website","Low Opportunity", IF(AND(K34="No Website",E34>=4.5,F34>=500),"Very High Opportunity", IF(AND(K34="No Website",E34>=4.5),"High Opportunity", IF(K34="Social Media","Medium Opportunity","Low Opportunity")))) -> Low Opportunity
A35: Uttam Nagar, Delhi | B35: salons | C35: Oneness Salon & Academy | D35: G-62, School Rd, Vijay Vihar, Block G, Uttam Nagar, Delhi, 110059, India | E35: 5 | F35: 417 | H35: 099582 39925 | I35: beauty_salon, beautician, point_of_interest, service, establishment | J35: =IF(COUNTIFS($C$2:C35,C35,$D$2:D35,D35)=1,"Unique","Duplicate") -> Unique | K35: =IF(TRIM(G35)="","No Website", IF(OR( ISNUMBER(SEARCH("facebook",LOWER(G35))), ISNUMBER(SEARCH("instagram",LOWER(G35))), ISNUMBER(SEARCH("wa.me",LOWER(G35))), ISNUMBER(SEARCH("whatsapp",LOWER(G35))), ISNUMBER(SEARCH("youtube",LOWER(G35))), ISNUMBER(SEARCH("twitter",LOWER(G35))), ISNUMBER(SEARCH("x.com",LOWER(G35))), ISNUMBER(SEARCH("linkedin",LOWER(G35))), ISNUMBER(SEARCH("linktr.ee",LOWER(G35))), ISNUMBER(SEARCH("g.page",LOWER(G35))), ISNUMBER(SEARCH("maps.app.goo.gl",LOWER(G35))), ISNUMBER(SEARCH("goo.gl",LOWER(G35))) ), "Social Media", "Official Website")) -> No Website | L35: =IF(E35>=4.5,"Excellent", IF(E35>=4,"Good", IF(E35>=3,"Average","Poor"))) -> Excellent | M35: =IF(F35>=1000,"1000+ Reviews", IF(F35>=500,"500-999 Reviews", IF(F35>=100,"100-499 Reviews", "Below 100 Reviews"))) -> 100-499 Reviews | N35: =IF(K35="Official Website","Low Opportunity", IF(AND(K35="No Website",E35>=4.5,F35>=500),"Very High Opportunity", IF(AND(K35="No Website",E35>=4.5),"High Opportunity", IF(K35="Social Media","Medium Opportunity","Low Opportunity")))) -> High Opportunity
A36: Shahdara, Delhi | B36: mobile shops | C36: MOBILE ADDICTION - BEST MOBILE SHOP DELHI | D36: C-240, Main 100 Feet Rd, Durgapuri Extension, Hardevpuri, Shahdara, Delhi, 110032, India | E36: 5 | F36: 407 | H36: 087009 19018 | I36: cell_phone_store, store, point_of_interest, establishment | J36: =IF(COUNTIFS($C$2:C36,C36,$D$2:D36,D36)=1,"Unique","Duplicate") -> Unique | K36: =IF(TRIM(G36)="","No Website", IF(OR( ISNUMBER(SEARCH("facebook",LOWER(G36))), ISNUMBER(SEARCH("instagram",LOWER(G36))), ISNUMBER(SEARCH("wa.me",LOWER(G36))), ISNUMBER(SEARCH("whatsapp",LOWER(G36))), ISNUMBER(SEARCH("youtube",LOWER(G36))), ISNUMBER(SEARCH("twitter",LOWER(G36))), ISNUMBER(SEARCH("x.com",LOWER(G36))), ISNUMBER(SEARCH("linkedin",LOWER(G36))), ISNUMBER(SEARCH("linktr.ee",LOWER(G36))), ISNUMBER(SEARCH("g.page",LOWER(G36))), ISNUMBER(SEARCH("maps.app.goo.gl",LOWER(G36))), ISNUMBER(SEARCH("goo.gl",LOWER(G36))) ), "Social Media", "Official Website")) -> No Website | L36: =IF(E36>=4.5,"Excellent", IF(E36>=4,"Good", IF(E36>=3,"Average","Poor"))) -> Excellent | M36: =IF(F36>=1000,"1000+ Reviews", IF(F36>=500,"500-999 Reviews", IF(F36>=100,"100-499 Reviews", "Below 100 Reviews"))) -> 100-499 Reviews | N36: =IF(K36="Official Website","Low Opportunity", IF(AND(K36="No Website",E36>=4.5,F36>=500),"Very High Opportunity", IF(AND(K36="No Website",E36>=4.5),"High Opportunity", IF(K36="Social Media","Medium Opportunity","Low Opportunity")))) -> High Opportunity
A37: Burari, Delhi | B37: salons | C37: Tress Trends Unisex Salon | D37: Main, Burari Rd, opposite Shalimar Banquet Hall, Data Ram Tyagi Enclave, Block A, Extension Colony, Burari, Delhi, 110084, India | E37: 4.7 | F37: 562 | G37: https://tress-trends-salon.respark.in/tress-trends-salon-240/burari | H37: 093550 55561 | I37: makeup_artist, hair_salon, hair_care, nail_salon, beauty_salon, point_of_interest, service, establishment | J37: =IF(COUNTIFS($C$2:C37,C37,$D$2:D37,D37)=1,"Unique","Duplicate") -> Unique | K37: =IF(TRIM(G37)="","No Website", IF(OR( ISNUMBER(SEARCH("facebook",LOWER(G37))), ISNUMBER(SEARCH("instagram",LOWER(G37))), ISNUMBER(SEARCH("wa.me",LOWER(G37))), ISNUMBER(SEARCH("whatsapp",LOWER(G37))), ISNUMBER(SEARCH("youtube",LOWER(G37))), ISNUMBER(SEARCH("twitter",LOWER(G37))), ISNUMBER(SEARCH("x.com",LOWER(G37))), ISNUMBER(SEARCH("linkedin",LOWER(G37))), ISNUMBER(SEARCH("linktr.ee",LOWER(G37))), ISNUMBER(SEARCH("g.page",LOWER(G37))), ISNUMBER(SEARCH("maps.app.goo.gl",LOWER(G37))), ISNUMBER(SEARCH("goo.gl",LOWER(G37))) ), "Social Media", "Official Website")) -> Official Website | L37: =IF(E37>=4.5,"Excellent", IF(E37>=4,"Good", IF(E37>=3,"Average","Poor"))) -> Excellent | M37: =IF(F37>=1000,"1000+ Reviews", IF(F37>=500,"500-999 Reviews", IF(F37>=100,"100-499 Reviews", "Below 100 Reviews"))) -> 500-999 Reviews | N37: =IF(K37="Official Website","Low Opportunity", IF(AND(K37="No Website",E37>=4.5,F37>=500),"Very High Opportunity", IF(AND(K37="No Website",E37>=4.5),"High Opportunity", IF(K37="Social Media","Medium Opportunity","Low Opportunity")))) -> Low Opportunity
A38: Rohini, Delhi | B38: gyms | C38: Swag Fit Gym and Studio | D38: S-38, CSC -13,BLOCK D-3 DDA Market Rohini Sec-16 near Motherdairy booth 510, D, 3, DDA Market, Pocket 2, Sector 16, Rohini, Delhi, 110089, India | E38: 5 | F38: 368 | H38: 098184 87484 | I38: fitness_center, gym, sports_activity_location, health, point_of_interest, establishment | J38: =IF(COUNTIFS($C$2:C38,C38,$D$2:D38,D38)=1,"Unique","Duplicate") -> Unique | K38: =IF(TRIM(G38)="","No Website", IF(OR( ISNUMBER(SEARCH("facebook",LOWER(G38))), ISNUMBER(SEARCH("instagram",LOWER(G38))), ISNUMBER(SEARCH("wa.me",LOWER(G38))), ISNUMBER(SEARCH("whatsapp",LOWER(G38))), ISNUMBER(SEARCH("youtube",LOWER(G38))), ISNUMBER(SEARCH("twitter",LOWER(G38))), ISNUMBER(SEARCH("x.com",LOWER(G38))), ISNUMBER(SEARCH("linkedin",LOWER(G38))), ISNUMBER(SEARCH("linktr.ee",LOWER(G38))), ISNUMBER(SEARCH("g.page",LOWER(G38))), ISNUMBER(SEARCH("maps.app.goo.gl",LOWER(G38))), ISNUMBER(SEARCH("goo.gl",LOWER(G38))) ), "Social Media", "Official Website")) -> No Website | L38: =IF(E38>=4.5,"Excellent", IF(E38>=4,"Good", IF(E38>=3,"Average","Poor"))) -> Excellent | M38: =IF(F38>=1000,"1000+ Reviews", IF(F38>=500,"500-999 Reviews", IF(F38>=100,"100-499 Reviews", "Below 100 Reviews"))) -> 100-499 Reviews | N38: =IF(K38="Official Website","Low Opportunity", IF(AND(K38="No Website",E38>=4.5,F38>=500),"Very High Opportunity", IF(AND(K38="No Website",E38>=4.5),"High Opportunity", IF(K38="Social Media","Medium Opportunity","Low Opportunity")))) -> High Opportunity
A39: Burari, Delhi | B39: salons | C39: The Valid Unisex Salon - Best Makeup Artist in Delhi, Bridal Makeup Artist, Nail Extension & Beauty Parlour in Burari, Delhi | D39: Plot No Pvt- 4 Khasra No- 122, Ground Floor Extanded, 5/1, Laldora, Sant Nagar, Burari, Delhi, 110084, India | E39: 4.5 | F39: 91 | G39: https://thevalidunisexsalon.com/ | H39: 092056 56721 | I39: beauty_salon, makeup_artist, beautician, massage_spa, massage, spa, hair_salon, hair_care, nail_salon, store, point_of_interest, service, establishment | J39: =IF(COUNTIFS($C$2:C39,C39,$D$2:D39,D39)=1,"Unique","Duplicate") -> Unique | K39: =IF(TRIM(G39)="","No Website", IF(OR( ISNUMBER(SEARCH("facebook",LOWER(G39))), ISNUMBER(SEARCH("instagram",LOWER(G39))), ISNUMBER(SEARCH("wa.me",LOWER(G39))), ISNUMBER(SEARCH("whatsapp",LOWER(G39))), ISNUMBER(SEARCH("youtube",LOWER(G39))), ISNUMBER(SEARCH("twitter",LOWER(G39))), ISNUMBER(SEARCH("x.com",LOWER(G39))), ISNUMBER(SEARCH("linkedin",LOWER(G39))), ISNUMBER(SEARCH("linktr.ee",LOWER(G39))), ISNUMBER(SEARCH("g.page",LOWER(G39))), ISNUMBER(SEARCH("maps.app.goo.gl",LOWER(G39))), ISNUMBER(SEARCH("goo.gl",LOWER(G39))) ), "Social Media", "Official Website")) -> Official Website | L39: =IF(E39>=4.5,"Excellent", IF(E39>=4,"Good", IF(E39>=3,"Average","Poor"))) -> Excellent | M39: =IF(F39>=1000,"1000+ Reviews", IF(F39>=500,"500-999 Reviews", IF(F39>=100,"100-499 Reviews", "Below 100 Reviews"))) -> Below 100 Reviews | N39: =IF(K39="Official Website","Low Opportunity", IF(AND(K39="No Website",E39>=4.5,F39>=500),"Very High Opportunity", IF(AND(K39="No Website",E39>=4.5),"High Opportunity", IF(K39="Social Media","Medium Opportunity","Low Opportunity")))) -> Low Opportunity
A40: Burari, Delhi | B40: salons | C40: Swanky unisex salon | D40: 775, Vijay Colony, Block B, Sant Nagar, Burari, Delhi, 110084, India | E40: 4.4 | F40: 188 | H40: 093101 06196 | I40: beauty_salon, point_of_interest, service, establishment | J40: =IF(COUNTIFS($C$2:C40,C40,$D$2:D40,D40)=1,"Unique","Duplicate") -> Unique | K40: =IF(TRIM(G40)="","No Website", IF(OR( ISNUMBER(SEARCH("facebook",LOWER(G40))), ISNUMBER(SEARCH("instagram",LOWER(G40))), ISNUMBER(SEARCH("wa.me",LOWER(G40))), ISNUMBER(SEARCH("whatsapp",LOWER(G40))), ISNUMBER(SEARCH("youtube",LOWER(G40))), ISNUMBER(SEARCH("twitter",LOWER(G40))), ISNUMBER(SEARCH("x.com",LOWER(G40))), ISNUMBER(SEARCH("linkedin",LOWER(G40))), ISNUMBER(SEARCH("linktr.ee",LOWER(G40))), ISNUMBER(SEARCH("g.page",LOWER(G40))), ISNUMBER(SEARCH("maps.app.goo.gl",LOWER(G40))), ISNUMBER(SEARCH("goo.gl",LOWER(G40))) ), "Social Media", "Official Website")) -> No Website | L40: =IF(E40>=4.5,"Excellent", IF(E40>=4,"Good", IF(E40>=3,"Average","Poor"))) -> Good | M40: =IF(F40>=1000,"1000+ Reviews", IF(F40>=500,"500-999 Reviews", IF(F40>=100,"100-499 Reviews", "Below 100 Reviews"))) -> 100-499 Reviews | N40: =IF(K40="Official Website","Low Opportunity", IF(AND(K40="No Website",E40>=4.5,F40>=500),"Very High Opportunity", IF(AND(K40="No Website",E40>=4.5),"High Opportunity", IF(K40="Social Media","Medium Opportunity","Low Opportunity")))) -> Low Opportunity
A41: Burari, Delhi | B41: salons | C41: The w salon & academy | D41: bus stand, Main road, near union Bank, opp. royal Enfield showroom, Conductor Colony, Burari, New Delhi, Delhi, 110084, India | E41: 4.3 | F41: 413 | H41: 096252 03609 | I41: beauty_salon, makeup_artist, tanning_studio, barber_shop, hair_salon, hair_care, nail_salon, health, point_of_interest, service, establishment | J41: =IF(COUNTIFS($C$2:C41,C41,$D$2:D41,D41)=1,"Unique","Duplicate") -> Unique | K41: =IF(TRIM(G41)="","No Website", IF(OR( ISNUMBER(SEARCH("facebook",LOWER(G41))), ISNUMBER(SEARCH("instagram",LOWER(G41))), ISNUMBER(SEARCH("wa.me",LOWER(G41))), ISNUMBER(SEARCH("whatsapp",LOWER(G41))), ISNUMBER(SEARCH("youtube",LOWER(G41))), ISNUMBER(SEARCH("twitter",LOWER(G41))), ISNUMBER(SEARCH("x.com",LOWER(G41))), ISNUMBER(SEARCH("linkedin",LOWER(G41))), ISNUMBER(SEARCH("linktr.ee",LOWER(G41))), ISNUMBER(SEARCH("g.page",LOWER(G41))), ISNUMBER(SEARCH("maps.app.goo.gl",LOWER(G41))), ISNUMBER(SEARCH("goo.gl",LOWER(G41))) ), "Social Media", "Official Website")) -> No Website | L41: =IF(E41>=4.5,"Excellent", IF(E41>=4,"Good", IF(E41>=3,"Average","Poor"))) -> Good | M41: =IF(F41>=1000,"1000+ Reviews", IF(F41>=500,"500-999 Reviews", IF(F41>=100,"100-499 Reviews", "Below 100 Reviews"))) -> 100-499 Reviews | N41: =IF(K41="Official Website","Low Opportunity", IF(AND(K41="No Website",E41>=4.5,F41>=500),"Very High Opportunity", IF(AND(K41="No Website",E41>=4.5),"High Opportunity", IF(K41="Social Media","Medium Opportunity","Low Opportunity")))) -> Low Opportunity
A42: Burari, Delhi | B42: salons | C42: Devika Salon & Academy - Best Salon in Sant Nagar Burari Delhi | D42: Main Market, Block B, Sant Nagar, Burari, Delhi, 110084, India | E42: 4.8 | F42: 154 | G42: https://www.instagram.com/devikaunisexsaloon/ | I42: beauty_salon, point_of_interest, service, establishment | J42: =IF(COUNTIFS($C$2:C42,C42,$D$2:D42,D42)=1,"Unique","Duplicate") -> Unique | K42: =IF(TRIM(G42)="","No Website", IF(OR( ISNUMBER(SEARCH("facebook",LOWER(G42))), ISNUMBER(SEARCH("instagram",LOWER(G42))), ISNUMBER(SEARCH("wa.me",LOWER(G42))), ISNUMBER(SEARCH("whatsapp",LOWER(G42))), ISNUMBER(SEARCH("youtube",LOWER(G42))), ISNUMBER(SEARCH("twitter",LOWER(G42))), ISNUMBER(SEARCH("x.com",LOWER(G42))), ISNUMBER(SEARCH("linkedin",LOWER(G42))), ISNUMBER(SEARCH("linktr.ee",LOWER(G42))), ISNUMBER(SEARCH("g.page",LOWER(G42))), ISNUMBER(SEARCH("maps.app.goo.gl",LOWER(G42))), ISNUMBER(SEARCH("goo.gl",LOWER(G42))) ), "Social Media", "Official Website")) -> Social Media | L42: =IF(E42>=4.5,"Excellent", IF(E42>=4,"Good", IF(E42>=3,"Average","Poor"))) -> Excellent | M42: =IF(F42>=1000,"1000+ Reviews", IF(F42>=500,"500-999 Reviews", IF(F42>=100,"100-499 Reviews", "Below 100 Reviews"))) -> 100-499 Reviews | N42: =IF(K42="Official Website","Low Opportunity", IF(AND(K42="No Website",E42>=4.5,F42>=500),"Very High Opportunity", IF(AND(K42="No Website",E42>=4.5),"High Opportunity", IF(K42="Social Media","Medium Opportunity","Low Opportunity")))) -> Medium Opportunity
A43: Shalimar Bagh, Delhi | B43: gyms | C43: X Power House Gym | D43: SE-30, First Floor, near DT Cinema Mall, Singalpur Village, West Shalimar Bagh, Shalimar Bagh, New Delhi, Delhi, 110088, India | E43: 5 | F43: 346 | H43: 083686 16635 | I43: gym, sports_activity_location, health, point_of_interest, establishment | J43: =IF(COUNTIFS($C$2:C43,C43,$D$2:D43,D43)=1,"Unique","Duplicate") -> Unique | K43: =IF(TRIM(G43)="","No Website", IF(OR( ISNUMBER(SEARCH("facebook",LOWER(G43))), ISNUMBER(SEARCH("instagram",LOWER(G43))), ISNUMBER(SEARCH("wa.me",LOWER(G43))), ISNUMBER(SEARCH("whatsapp",LOWER(G43))), ISNUMBER(SEARCH("youtube",LOWER(G43))), ISNUMBER(SEARCH("twitter",LOWER(G43))), ISNUMBER(SEARCH("x.com",LOWER(G43))), ISNUMBER(SEARCH("linkedin",LOWER(G43))), ISNUMBER(SEARCH("linktr.ee",LOWER(G43))), ISNUMBER(SEARCH("g.page",LOWER(G43))), ISNUMBER(SEARCH("maps.app.goo.gl",LOWER(G43))), ISNUMBER(SEARCH("goo.gl",LOWER(G43))) ), "Social Media", "Official Website")) -> No Website | L43: =IF(E43>=4.5,"Excellent", IF(E43>=4,"Good", IF(E43>=3,"Average","Poor"))) -> Excellent | M43: =IF(F43>=1000,"1000+ Reviews", IF(F43>=500,"500-999 Reviews", IF(F43>=100,"100-499 Reviews", "Below 100 Reviews"))) -> 100-499 Reviews | N43: =IF(K43="Official Website","Low Opportunity", IF(AND(K43="No Website",E43>=4.5,F43>=500),"Very High Opportunity", IF(AND(K43="No Website",E43>=4.5),"High Opportunity", IF(K43="Social Media","Medium Opportunity","Low Opportunity")))) -> High Opportunity
A44: Uttam Nagar, Delhi | B44: clinics | C44: GOOD HEALTH CLINIC (Dr. ARUN SINGH) | D44: C block, Veer Bazar Rd, Block No B-1, Sanjay Enclave, Uttam Nagar, New Delhi, Delhi, 110059, India | E44: 5 | F44: 334 | H44: 095556 96123 | I44: medical_clinic, health, point_of_interest, establishment | J44: =IF(COUNTIFS($C$2:C44,C44,$D$2:D44,D44)=1,"Unique","Duplicate") -> Unique | K44: =IF(TRIM(G44)="","No Website", IF(OR( ISNUMBER(SEARCH("facebook",LOWER(G44))), ISNUMBER(SEARCH("instagram",LOWER(G44))), ISNUMBER(SEARCH("wa.me",LOWER(G44))), ISNUMBER(SEARCH("whatsapp",LOWER(G44))), ISNUMBER(SEARCH("youtube",LOWER(G44))), ISNUMBER(SEARCH("twitter",LOWER(G44))), ISNUMBER(SEARCH("x.com",LOWER(G44))), ISNUMBER(SEARCH("linkedin",LOWER(G44))), ISNUMBER(SEARCH("linktr.ee",LOWER(G44))), ISNUMBER(SEARCH("g.page",LOWER(G44))), ISNUMBER(SEARCH("maps.app.goo.gl",LOWER(G44))), ISNUMBER(SEARCH("goo.gl",LOWER(G44))) ), "Social Media", "Official Website")) -> No Website | L44: =IF(E44>=4.5,"Excellent", IF(E44>=4,"Good", IF(E44>=3,"Average","Poor"))) -> Excellent | M44: =IF(F44>=1000,"1000+ Reviews", IF(F44>=500,"500-999 Reviews", IF(F44>=100,"100-499 Reviews", "Below 100 Reviews"))) -> 100-499 Reviews | N44: =IF(K44="Official Website","Low Opportunity", IF(AND(K44="No Website",E44>=4.5,F44>=500),"Very High Opportunity", IF(AND(K44="No Website",E44>=4.5),"High Opportunity", IF(K44="Social Media","Medium Opportunity","Low Opportunity")))) -> High Opportunity
A45: Dwarka, Delhi | B45: mobile shops | C45: Connect Mobile Shop | D45: e-554, Ramphal Chowk Rd, Block D, Sector 7 Dwarka, Palam, New Delhi, Delhi, 110077, India | E45: 5 | F45: 292 | H45: 098116 13001 | I45: cell_phone_store, store, point_of_interest, establishment | J45: =IF(COUNTIFS($C$2:C45,C45,$D$2:D45,D45)=1,"Unique","Duplicate") -> Unique | K45: =IF(TRIM(G45)="","No Website", IF(OR( ISNUMBER(SEARCH("facebook",LOWER(G45))), ISNUMBER(SEARCH("instagram",LOWER(G45))), ISNUMBER(SEARCH("wa.me",LOWER(G45))), ISNUMBER(SEARCH("whatsapp",LOWER(G45))), ISNUMBER(SEARCH("youtube",LOWER(G45))), ISNUMBER(SEARCH("twitter",LOWER(G45))), ISNUMBER(SEARCH("x.com",LOWER(G45))), ISNUMBER(SEARCH("linkedin",LOWER(G45))), ISNUMBER(SEARCH("linktr.ee",LOWER(G45))), ISNUMBER(SEARCH("g.page",LOWER(G45))), ISNUMBER(SEARCH("maps.app.goo.gl",LOWER(G45))), ISNUMBER(SEARCH("goo.gl",LOWER(G45))) ), "Social Media", "Official Website")) -> No Website | L45: =IF(E45>=4.5,"Excellent", IF(E45>=4,"Good", IF(E45>=3,"Average","Poor"))) -> Excellent | M45: =IF(F45>=1000,"1000+ Reviews", IF(F45>=500,"500-999 Reviews", IF(F45>=100,"100-499 Reviews", "Below 100 Reviews"))) -> 100-499 Reviews | N45: =IF(K45="Official Website","Low Opportunity", IF(AND(K45="No Website",E45>=4.5,F45>=500),"Very High Opportunity", IF(AND(K45="No Website",E45>=4.5),"High Opportunity", IF(K45="Social Media","Medium Opportunity","Low Opportunity")))) -> High Opportunity
A46: Patel Nagar, Delhi | B46: electronics shops | C46: Tyagi Electronics (Patel Nagar) | D46: 2151/16, New Patel Nagar, Shadipur, New Delhi, Delhi, 110008, India | E46: 5 | F46: 287 | H46: 079820 71296 | I46: home_goods_store, store, point_of_interest, establishment | J46: =IF(COUNTIFS($C$2:C46,C46,$D$2:D46,D46)=1,"Unique","Duplicate") -> Unique | K46: =IF(TRIM(G46)="","No Website", IF(OR( ISNUMBER(SEARCH("facebook",LOWER(G46))), ISNUMBER(SEARCH("instagram",LOWER(G46))), ISNUMBER(SEARCH("wa.me",LOWER(G46))), ISNUMBER(SEARCH("whatsapp",LOWER(G46))), ISNUMBER(SEARCH("youtube",LOWER(G46))), ISNUMBER(SEARCH("twitter",LOWER(G46))), ISNUMBER(SEARCH("x.com",LOWER(G46))), ISNUMBER(SEARCH("linkedin",LOWER(G46))), ISNUMBER(SEARCH("linktr.ee",LOWER(G46))), ISNUMBER(SEARCH("g.page",LOWER(G46))), ISNUMBER(SEARCH("maps.app.goo.gl",LOWER(G46))), ISNUMBER(SEARCH("goo.gl",LOWER(G46))) ), "Social Media", "Official Website")) -> No Website | L46: =IF(E46>=4.5,"Excellent", IF(E46>=4,"Good", IF(E46>=3,"Average","Poor"))) -> Excellent | M46: =IF(F46>=1000,"1000+ Reviews", IF(F46>=500,"500-999 Reviews", IF(F46>=100,"100-499 Reviews", "Below 100 Reviews"))) -> 100-499 Reviews | N46: =IF(K46="Official Website","Low Opportunity", IF(AND(K46="No Website",E46>=4.5,F46>=500),"Very High Opportunity", IF(AND(K46="No Website",E46>=4.5),"High Opportunity", IF(K46="Social Media","Medium Opportunity","Low Opportunity")))) -> High Opportunity
A47: Malviya Nagar, Delhi | B47: gyms | C47: IRON PARADISE MALVIYA NAGAR | D47: Ground floor, K-5A, Block K, Malviya Nagar, New Delhi, Delhi 110017, India | E47: 5 | F47: 277 | H47: 092117 61112 | I47: fitness_center, gym, sports_activity_location, health, point_of_interest, establishment | J47: =IF(COUNTIFS($C$2:C47,C47,$D$2:D47,D47)=1,"Unique","Duplicate") -> Unique | K47: =IF(TRIM(G47)="","No Website", IF(OR( ISNUMBER(SEARCH("facebook",LOWER(G47))), ISNUMBER(SEARCH("instagram",LOWER(G47))), ISNUMBER(SEARCH("wa.me",LOWER(G47))), ISNUMBER(SEARCH("whatsapp",LOWER(G47))), ISNUMBER(SEARCH("youtube",LOWER(G47))), ISNUMBER(SEARCH("twitter",LOWER(G47))), ISNUMBER(SEARCH("x.com",LOWER(G47))), ISNUMBER(SEARCH("linkedin",LOWER(G47))), ISNUMBER(SEARCH("linktr.ee",LOWER(G47))), ISNUMBER(SEARCH("g.page",LOWER(G47))), ISNUMBER(SEARCH("maps.app.goo.gl",LOWER(G47))), ISNUMBER(SEARCH("goo.gl",LOWER(G47))) ), "Social Media", "Official Website")) -> No Website | L47: =IF(E47>=4.5,"Excellent", IF(E47>=4,"Good", IF(E47>=3,"Average","Poor"))) -> Excellent | M47: =IF(F47>=1000,"1000+ Reviews", IF(F47>=500,"500-999 Reviews", IF(F47>=100,"100-499 Reviews", "Below 100 Reviews"))) -> 100-499 Reviews | N47: =IF(K47="Official Website","Low Opportunity", IF(AND(K47="No Website",E47>=4.5,F47>=500),"Very High Opportunity", IF(AND(K47="No Website",E47>=4.5),"High Opportunity", IF(K47="Social Media","Medium Opportunity","Low Opportunity")))) -> High Opportunity
A48: Burari, Delhi | B48: salons | C48: Sudiksha Makeup Studio - Best Makeup Artist | D48: Sudiksha Make-Up Studio kh-No- 658 First Floor Main, Bus Stop, Conductor Colony, Burari, New Delhi, Delhi, 110084, India | E48: 4.7 | F48: 128 | G48: https://sudikshamakeupstudio.com/ | H48: 095824 38998 | I48: beauty_salon, makeup_artist, beautician, hair_salon, hair_care, nail_salon, point_of_interest, service, establishment | J48: =IF(COUNTIFS($C$2:C48,C48,$D$2:D48,D48)=1,"Unique","Duplicate") -> Unique | K48: =IF(TRIM(G48)="","No Website", IF(OR( ISNUMBER(SEARCH("facebook",LOWER(G48))), ISNUMBER(SEARCH("instagram",LOWER(G48))), ISNUMBER(SEARCH("wa.me",LOWER(G48))), ISNUMBER(SEARCH("whatsapp",LOWER(G48))), ISNUMBER(SEARCH("youtube",LOWER(G48))), ISNUMBER(SEARCH("twitter",LOWER(G48))), ISNUMBER(SEARCH("x.com",LOWER(G48))), ISNUMBER(SEARCH("linkedin",LOWER(G48))), ISNUMBER(SEARCH("linktr.ee",LOWER(G48))), ISNUMBER(SEARCH("g.page",LOWER(G48))), ISNUMBER(SEARCH("maps.app.goo.gl",LOWER(G48))), ISNUMBER(SEARCH("goo.gl",LOWER(G48))) ), "Social Media", "Official Website")) -> Official Website | L48: =IF(E48>=4.5,"Excellent", IF(E48>=4,"Good", IF(E48>=3,"Average","Poor"))) -> Excellent | M48: =IF(F48>=1000,"1000+ Reviews", IF(F48>=500,"500-999 Reviews", IF(F48>=100,"100-499 Reviews", "Below 100 Reviews"))) -> 100-499 Reviews | N48: =IF(K48="Official Website","Low Opportunity", IF(AND(K48="No Website",E48>=4.5,F48>=500),"Very High Opportunity", IF(AND(K48="No Website",E48>=4.5),"High Opportunity", IF(K48="Social Media","Medium Opportunity","Low Opportunity")))) -> Low Opportunity
A49: Uttam Nagar, Delhi | B49: gyms | C49: The Workout Zone (Uttam Nagar) | D49: 271,Nawada, near pillar number 718, Phase 1A, Om Vihar, Uttam Nagar, Delhi, 110059, India | E49: 5 | F49: 275 | H49: 085272 62721 | I49: gym, sports_activity_location, health, point_of_interest, establishment | J49: =IF(COUNTIFS($C$2:C49,C49,$D$2:D49,D49)=1,"Unique","Duplicate") -> Unique | K49: =IF(TRIM(G49)="","No Website", IF(OR( ISNUMBER(SEARCH("facebook",LOWER(G49))), ISNUMBER(SEARCH("instagram",LOWER(G49))), ISNUMBER(SEARCH("wa.me",LOWER(G49))), ISNUMBER(SEARCH("whatsapp",LOWER(G49))), ISNUMBER(SEARCH("youtube",LOWER(G49))), ISNUMBER(SEARCH("twitter",LOWER(G49))), ISNUMBER(SEARCH("x.com",LOWER(G49))), ISNUMBER(SEARCH("linkedin",LOWER(G49))), ISNUMBER(SEARCH("linktr.ee",LOWER(G49))), ISNUMBER(SEARCH("g.page",LOWER(G49))), ISNUMBER(SEARCH("maps.app.goo.gl",LOWER(G49))), ISNUMBER(SEARCH("goo.gl",LOWER(G49))) ), "Social Media", "Official Website")) -> No Website | L49: =IF(E49>=4.5,"Excellent", IF(E49>=4,"Good", IF(E49>=3,"Average","Poor"))) -> Excellent | M49: =IF(F49>=1000,"1000+ Reviews", IF(F49>=500,"500-999 Reviews", IF(F49>=100,"100-499 Reviews", "Below 100 Reviews"))) -> 100-499 Reviews | N49: =IF(K49="Official Website","Low Opportunity", IF(AND(K49="No Website",E49>=4.5,F49>=500),"Very High Opportunity", IF(AND(K49="No Website",E49>=4.5),"High Opportunity", IF(K49="Social Media","Medium Opportunity","Low Opportunity")))) -> High Opportunity
A50: Burari, Delhi | B50: salons | C50: BEAUTY LOUNGE BY SRISH MAKEOVER | D50: Mandir Wali Gali, near bikaner Sweets, Vijay Colony, Block B, Kamal Pur, Burari, Delhi, 110084, India | E50: 4.9 | F50: 172 | G50: https://www.instagram.com/srish_makeover_/ | H50: 096508 28677 | I50: beauty_salon, makeup_artist, tanning_studio, massage_spa, massage, spa, hair_salon, hair_care, point_of_interest, service, establishment | J50: =IF(COUNTIFS($C$2:C50,C50,$D$2:D50,D50)=1,"Unique","Duplicate") -> Unique | K50: =IF(TRIM(G50)="","No Website", IF(OR( ISNUMBER(SEARCH("facebook",LOWER(G50))), ISNUMBER(SEARCH("instagram",LOWER(G50))), ISNUMBER(SEARCH("wa.me",LOWER(G50))), ISNUMBER(SEARCH("whatsapp",LOWER(G50))), ISNUMBER(SEARCH("youtube",LOWER(G50))), ISNUMBER(SEARCH("twitter",LOWER(G50))), ISNUMBER(SEARCH("x.com",LOWER(G50))), ISNUMBER(SEARCH("linkedin",LOWER(G50))), ISNUMBER(SEARCH("linktr.ee",LOWER(G50))), ISNUMBER(SEARCH("g.page",LOWER(G50))), ISNUMBER(SEARCH("maps.app.goo.gl",LOWER(G50))), ISNUMBER(SEARCH("goo.gl",LOWER(G50))) ), "Social Media", "Official Website")) -> Social Media | L50: =IF(E50>=4.5,"Excellent", IF(E50>=4,"Good", IF(E50>=3,"Average","Poor"))) -> Excellent | M50: =IF(F50>=1000,"1000+ Reviews", IF(F50>=500,"500-999 Reviews", IF(F50>=100,"100-499 Reviews", "Below 100 Reviews"))) -> 100-499 Reviews | N50: =IF(K50="Official Website","Low Opportunity", IF(AND(K50="No Website",E50>=4.5,F50>=500),"Very High Opportunity", IF(AND(K50="No Website",E50>=4.5),"High Opportunity", IF(K50="Social Media","Medium Opportunity","Low Opportunity")))) -> Medium Opportunity
A51: Burari, Delhi | B51: salons | C51: Nails by Rashika unisex salon | D51: shop no 2, Labour Chowk, 84 khasra no 877, Block B, Sant Nagar, Burari, Delhi, 110084, India | E51: 5 | F51: 48 | G51: https://nails-by-rashika-unisex.grexa.site/ | H51: 096254 10968 | I51: beauty_salon, point_of_interest, service, establishment | J51: =IF(COUNTIFS($C$2:C51,C51,$D$2:D51,D51)=1,"Unique","Duplicate") -> Unique | K51: =IF(TRIM(G51)="","No Website", IF(OR( ISNUMBER(SEARCH("facebook",LOWER(G51))), ISNUMBER(SEARCH("instagram",LOWER(G51))), ISNUMBER(SEARCH("wa.me",LOWER(G51))), ISNUMBER(SEARCH("whatsapp",LOWER(G51))), ISNUMBER(SEARCH("youtube",LOWER(G51))), ISNUMBER(SEARCH("twitter",LOWER(G51))), ISNUMBER(SEARCH("x.com",LOWER(G51))), ISNUMBER(SEARCH("linkedin",LOWER(G51))), ISNUMBER(SEARCH("linktr.ee",LOWER(G51))), ISNUMBER(SEARCH("g.page",LOWER(G51))), ISNUMBER(SEARCH("maps.app.goo.gl",LOWER(G51))), ISNUMBER(SEARCH("goo.gl",LOWER(G51))) ), "Social Media", "Official Website")) -> Official Website | L51: =IF(E51>=4.5,"Excellent", IF(E51>=4,"Good", IF(E51>=3,"Average","Poor"))) -> Excellent | M51: =IF(F51>=1000,"1000+ Reviews", IF(F51>=500,"500-999 Reviews", IF(F51>=100,"100-499 Reviews", "Below 100 Reviews"))) -> Below 100 Reviews | N51: =IF(K51="Official Website","Low Opportunity", IF(AND(K51="No Website",E51>=4.5,F51>=500),"Very High Opportunity", IF(AND(K51="No Website",E51>=4.5),"High Opportunity", IF(K51="Social Media","Medium Opportunity","Low Opportunity")))) -> Low Opportunity
A52: Burari, Delhi | B52: salons | C52: Poonam makeovers | D52: 52 Shop no, 1814, near Kali Mata Mandir or Dal godam, near Laxmi sweets, Shiv Kunj, Sant Nagar, Burari, New Delhi, Delhi, 110084, India | E52: 5 | F52: 37 | G52: https://www.instagram.com/harshitpandey51758 | H52: 085100 63564 | I52: beauty_salon, point_of_interest, service, establishment | J52: =IF(COUNTIFS($C$2:C52,C52,$D$2:D52,D52)=1,"Unique","Duplicate") -> Unique | K52: =IF(TRIM(G52)="","No Website", IF(OR( ISNUMBER(SEARCH("facebook",LOWER(G52))), ISNUMBER(SEARCH("instagram",LOWER(G52))), ISNUMBER(SEARCH("wa.me",LOWER(G52))), ISNUMBER(SEARCH("whatsapp",LOWER(G52))), ISNUMBER(SEARCH("youtube",LOWER(G52))), ISNUMBER(SEARCH("twitter",LOWER(G52))), ISNUMBER(SEARCH("x.com",LOWER(G52))), ISNUMBER(SEARCH("linkedin",LOWER(G52))), ISNUMBER(SEARCH("linktr.ee",LOWER(G52))), ISNUMBER(SEARCH("g.page",LOWER(G52))), ISNUMBER(SEARCH("maps.app.goo.gl",LOWER(G52))), ISNUMBER(SEARCH("goo.gl",LOWER(G52))) ), "Social Media", "Official Website")) -> Social Media | L52: =IF(E52>=4.5,"Excellent", IF(E52>=4,"Good", IF(E52>=3,"Average","Poor"))) -> Excellent | M52: =IF(F52>=1000,"1000+ Reviews", IF(F52>=500,"500-999 Reviews", IF(F52>=100,"100-499 Reviews", "Below 100 Reviews"))) -> Below 100 Reviews | N52: =IF(K52="Official Website","Low Opportunity", IF(AND(K52="No Website",E52>=4.5,F52>=500),"Very High Opportunity", IF(AND(K52="No Website",E52>=4.5),"High Opportunity", IF(K52="Social Media","Medium Opportunity","Low Opportunity")))) -> Medium Opportunity
A53: Rajendra Nagar, Delhi | B53: gyms | C53: TrueFitnessClub | D53: H-475, near camdin bakery, Pocket H, Rajender Nagar Part 1, Rajinder Nagar, New Delhi, Delhi, 110060, India | E53: 5 | F53: 270 | H53: 098184 02507 | I53: gym, sports_activity_location, health, point_of_interest, establishment | J53: =IF(COUNTIFS($C$2:C53,C53,$D$2:D53,D53)=1,"Unique","Duplicate") -> Unique | K53: =IF(TRIM(G53)="","No Website", IF(OR( ISNUMBER(SEARCH("facebook",LOWER(G53))), ISNUMBER(SEARCH("instagram",LOWER(G53))), ISNUMBER(SEARCH("wa.me",LOWER(G53))), ISNUMBER(SEARCH("whatsapp",LOWER(G53))), ISNUMBER(SEARCH("youtube",LOWER(G53))), ISNUMBER(SEARCH("twitter",LOWER(G53))), ISNUMBER(SEARCH("x.com",LOWER(G53))), ISNUMBER(SEARCH("linkedin",LOWER(G53))), ISNUMBER(SEARCH("linktr.ee",LOWER(G53))), ISNUMBER(SEARCH("g.page",LOWER(G53))), ISNUMBER(SEARCH("maps.app.goo.gl",LOWER(G53))), ISNUMBER(SEARCH("goo.gl",LOWER(G53))) ), "Social Media", "Official Website")) -> No Website | L53: =IF(E53>=4.5,"Excellent", IF(E53>=4,"Good", IF(E53>=3,"Average","Poor"))) -> Excellent | M53: =IF(F53>=1000,"1000+ Reviews", IF(F53>=500,"500-999 Reviews", IF(F53>=100,"100-499 Reviews", "Below 100 Reviews"))) -> 100-499 Reviews | N53: =IF(K53="Official Website","Low Opportunity", IF(AND(K53="No Website",E53>=4.5,F53>=500),"Very High Opportunity", IF(AND(K53="No Website",E53>=4.5),"High Opportunity", IF(K53="Social Media","Medium Opportunity","Low Opportunity")))) -> High Opportunity
A54: Dwarka, Delhi | B54: gyms | C54: Fitness Engineer Gym | Dwarka | D54: 124A Shiv park, Old palam road kakrola, opposite shiv property, Raju Parak Extension, Dwarka, New delhi, Delhi, 110078, India | E54: 5 | F54: 268 | H54: 099900 36755 | I54: gym, sports_activity_location, health, point_of_interest, establishment | J54: =IF(COUNTIFS($C$2:C54,C54,$D$2:D54,D54)=1,"Unique","Duplicate") -> Unique | K54: =IF(TRIM(G54)="","No Website", IF(OR( ISNUMBER(SEARCH("facebook",LOWER(G54))), ISNUMBER(SEARCH("instagram",LOWER(G54))), ISNUMBER(SEARCH("wa.me",LOWER(G54))), ISNUMBER(SEARCH("whatsapp",LOWER(G54))), ISNUMBER(SEARCH("youtube",LOWER(G54))), ISNUMBER(SEARCH("twitter",LOWER(G54))), ISNUMBER(SEARCH("x.com",LOWER(G54))), ISNUMBER(SEARCH("linkedin",LOWER(G54))), ISNUMBER(SEARCH("linktr.ee",LOWER(G54))), ISNUMBER(SEARCH("g.page",LOWER(G54))), ISNUMBER(SEARCH("maps.app.goo.gl",LOWER(G54))), ISNUMBER(SEARCH("goo.gl",LOWER(G54))) ), "Social Media", "Official Website")) -> No Website | L54: =IF(E54>=4.5,"Excellent", IF(E54>=4,"Good", IF(E54>=3,"Average","Poor"))) -> Excellent | M54: =IF(F54>=1000,"1000+ Reviews", IF(F54>=500,"500-999 Reviews", IF(F54>=100,"100-499 Reviews", "Below 100 Reviews"))) -> 100-499 Reviews | N54: =IF(K54="Official Website","Low Opportunity", IF(AND(K54="No Website",E54>=4.5,F54>=500),"Very High Opportunity", IF(AND(K54="No Website",E54>=4.5),"High Opportunity", IF(K54="Social Media","Medium Opportunity","Low Opportunity")))) -> High Opportunity
A55: Burari, Delhi | B55: salons | C55: Adonize The Family Salon | D55: First Floor Of, Bank Of Baroda, 760, Main Road, opposite Neelkanth Appartment, Vijay Colony, Block B, Sant Nagar, Burrari, Delhi, 110084, India | E55: 4.5 | F55: 30 | G55: https://adonizethesalon.wixsite.com/salon-1/ | I55: beauty_salon, point_of_interest, service, establishment | J55: =IF(COUNTIFS($C$2:C55,C55,$D$2:D55,D55)=1,"Unique","Duplicate") -> Unique | K55: =IF(TRIM(G55)="","No Website", IF(OR( ISNUMBER(SEARCH("facebook",LOWER(G55))), ISNUMBER(SEARCH("instagram",LOWER(G55))), ISNUMBER(SEARCH("wa.me",LOWER(G55))), ISNUMBER(SEARCH("whatsapp",LOWER(G55))), ISNUMBER(SEARCH("youtube",LOWER(G55))), ISNUMBER(SEARCH("twitter",LOWER(G55))), ISNUMBER(SEARCH("x.com",LOWER(G55))), ISNUMBER(SEARCH("linkedin",LOWER(G55))), ISNUMBER(SEARCH("linktr.ee",LOWER(G55))), ISNUMBER(SEARCH("g.page",LOWER(G55))), ISNUMBER(SEARCH("maps.app.goo.gl",LOWER(G55))), ISNUMBER(SEARCH("goo.gl",LOWER(G55))) ), "Social Media", "Official Website")) -> Official Website | L55: =IF(E55>=4.5,"Excellent", IF(E55>=4,"Good", IF(E55>=3,"Average","Poor"))) -> Excellent | M55: =IF(F55>=1000,"1000+ Reviews", IF(F55>=500,"500-999 Reviews", IF(F55>=100,"100-499 Reviews", "Below 100 Reviews"))) -> Below 100 Reviews | N55: =IF(K55="Official Website","Low Opportunity", IF(AND(K55="No Website",E55>=4.5,F55>=500),"Very High Opportunity", IF(AND(K55="No Website",E55>=4.5),"High Opportunity", IF(K55="Social Media","Medium Opportunity","Low Opportunity")))) -> Low Opportunity
A56: Burari, Delhi | B56: salons | C56: UNISEX SALON & ACADEMY | D56: KH.NO.760, Main 100, Foota Road, above Bank Of Baroda, Vijay Colony, Block B, Sant Nagar, Burari, Delhi, 110084, India | E56: 2.6 | F56: 10 | G56: https://www.instagram.com/makeupstoriesbyjanvi?igsh=cWM2YWlpOW5oaGl0 | H56: 083684 68300 | I56: makeup_artist, point_of_interest, establishment | J56: =IF(COUNTIFS($C$2:C56,C56,$D$2:D56,D56)=1,"Unique","Duplicate") -> Unique | K56: =IF(TRIM(G56)="","No Website", IF(OR( ISNUMBER(SEARCH("facebook",LOWER(G56))), ISNUMBER(SEARCH("instagram",LOWER(G56))), ISNUMBER(SEARCH("wa.me",LOWER(G56))), ISNUMBER(SEARCH("whatsapp",LOWER(G56))), ISNUMBER(SEARCH("youtube",LOWER(G56))), ISNUMBER(SEARCH("twitter",LOWER(G56))), ISNUMBER(SEARCH("x.com",LOWER(G56))), ISNUMBER(SEARCH("linkedin",LOWER(G56))), ISNUMBER(SEARCH("linktr.ee",LOWER(G56))), ISNUMBER(SEARCH("g.page",LOWER(G56))), ISNUMBER(SEARCH("maps.app.goo.gl",LOWER(G56))), ISNUMBER(SEARCH("goo.gl",LOWER(G56))) ), "Social Media", "Official Website")) -> Social Media | L56: =IF(E56>=4.5,"Excellent", IF(E56>=4,"Good", IF(E56>=3,"Average","Poor"))) -> Poor | M56: =IF(F56>=1000,"1000+ Reviews", IF(F56>=500,"500-999 Reviews", IF(F56>=100,"100-499 Reviews", "Below 100 Reviews"))) -> Below 100 Reviews | N56: =IF(K56="Official Website","Low Opportunity", IF(AND(K56="No Website",E56>=4.5,F56>=500),"Very High Opportunity", IF(AND(K56="No Website",E56>=4.5),"High Opportunity", IF(K56="Social Media","Medium Opportunity","Low Opportunity")))) -> Medium Opportunity
A57: Ashok Vihar, Delhi | B57: electronics shops | C57: Singh Brothers Computers | D57: C-80/A, Double Story, Block C, Sangam Park, Ashok Vihar, Delhi, 110033, India | E57: 5 | F57: 267 | H57: 092665 75565 | I57: electronics_store, store, point_of_interest, establishment | J57: =IF(COUNTIFS($C$2:C57,C57,$D$2:D57,D57)=1,"Unique","Duplicate") -> Unique | K57: =IF(TRIM(G57)="","No Website", IF(OR( ISNUMBER(SEARCH("facebook",LOWER(G57))), ISNUMBER(SEARCH("instagram",LOWER(G57))), ISNUMBER(SEARCH("wa.me",LOWER(G57))), ISNUMBER(SEARCH("whatsapp",LOWER(G57))), ISNUMBER(SEARCH("youtube",LOWER(G57))), ISNUMBER(SEARCH("twitter",LOWER(G57))), ISNUMBER(SEARCH("x.com",LOWER(G57))), ISNUMBER(SEARCH("linkedin",LOWER(G57))), ISNUMBER(SEARCH("linktr.ee",LOWER(G57))), ISNUMBER(SEARCH("g.page",LOWER(G57))), ISNUMBER(SEARCH("maps.app.goo.gl",LOWER(G57))), ISNUMBER(SEARCH("goo.gl",LOWER(G57))) ), "Social Media", "Official Website")) -> No Website | L57: =IF(E57>=4.5,"Excellent", IF(E57>=4,"Good", IF(E57>=3,"Average","Poor"))) -> Excellent | M57: =IF(F57>=1000,"1000+ Reviews", IF(F57>=500,"500-999 Reviews", IF(F57>=100,"100-499 Reviews", "Below 100 Reviews"))) -> 100-499 Reviews | N57: =IF(K57="Official Website","Low Opportunity", IF(AND(K57="No Website",E57>=4.5,F57>=500),"Very High Opportunity", IF(AND(K57="No Website",E57>=4.5),"High Opportunity", IF(K57="Social Media","Medium Opportunity","Low Opportunity")))) -> High Opportunity
A58: Vasant Kunj, Delhi | B58: bakeries | C58: Dessertery Bakery | D58: Shop no.-4, C-18, Kanhiya Market,, Masoodpur, D6, Sector D, Vasant Kunj, New Delhi, Delhi 110070, India | E58: 5 | F58: 264 | I58: bakery, food_store, store, food, point_of_interest, establishment | J58: =IF(COUNTIFS($C$2:C58,C58,$D$2:D58,D58)=1,"Unique","Duplicate") -> Unique | K58: =IF(TRIM(G58)="","No Website", IF(OR( ISNUMBER(SEARCH("facebook",LOWER(G58))), ISNUMBER(SEARCH("instagram",LOWER(G58))), ISNUMBER(SEARCH("wa.me",LOWER(G58))), ISNUMBER(SEARCH("whatsapp",LOWER(G58))), ISNUMBER(SEARCH("youtube",LOWER(G58))), ISNUMBER(SEARCH("twitter",LOWER(G58))), ISNUMBER(SEARCH("x.com",LOWER(G58))), ISNUMBER(SEARCH("linkedin",LOWER(G58))), ISNUMBER(SEARCH("linktr.ee",LOWER(G58))), ISNUMBER(SEARCH("g.page",LOWER(G58))), ISNUMBER(SEARCH("maps.app.goo.gl",LOWER(G58))), ISNUMBER(SEARCH("goo.gl",LOWER(G58))) ), "Social Media", "Official Website")) -> No Website | L58: =IF(E58>=4.5,"Excellent", IF(E58>=4,"Good", IF(E58>=3,"Average","Poor"))) -> Excellent | M58: =IF(F58>=1000,"1000+ Reviews", IF(F58>=500,"500-999 Reviews", IF(F58>=100,"100-499 Reviews", "Below 100 Reviews"))) -> 100-499 Reviews | N58: =IF(K58="Official Website","Low Opportunity", IF(AND(K58="No Website",E58>=4.5,F58>=500),"Very High Opportunity", IF(AND(K58="No Website",E58>=4.5),"High Opportunity", IF(K58="Social Media","Medium Opportunity","Low Opportunity")))) -> High Opportunity
A59: Civil Lines, Delhi | B59: bakeries | C59: Woeser Cafe & Bakery | D59: HOUSE NO, GROUND FLOOR, Block-9, OLD TIBETAN CAMP, 188-C, New Aruna Colony, Majnu-ka-tilla, New Aruna Nagar, Delhi, 110054, India | E59: 5 | F59: 250 | I59: bakery, food_store, store, food, point_of_interest, establishment | J59: =IF(COUNTIFS($C$2:C59,C59,$D$2:D59,D59)=1,"Unique","Duplicate") -> Unique | K59: =IF(TRIM(G59)="","No Website", IF(OR( ISNUMBER(SEARCH("facebook",LOWER(G59))), ISNUMBER(SEARCH("instagram",LOWER(G59))), ISNUMBER(SEARCH("wa.me",LOWER(G59))), ISNUMBER(SEARCH("whatsapp",LOWER(G59))), ISNUMBER(SEARCH("youtube",LOWER(G59))), ISNUMBER(SEARCH("twitter",LOWER(G59))), ISNUMBER(SEARCH("x.com",LOWER(G59))), ISNUMBER(SEARCH("linkedin",LOWER(G59))), ISNUMBER(SEARCH("linktr.ee",LOWER(G59))), ISNUMBER(SEARCH("g.page",LOWER(G59))), ISNUMBER(SEARCH("maps.app.goo.gl",LOWER(G59))), ISNUMBER(SEARCH("goo.gl",LOWER(G59))) ), "Social Media", "Official Website")) -> No Website | L59: =IF(E59>=4.5,"Excellent", IF(E59>=4,"Good", IF(E59>=3,"Average","Poor"))) -> Excellent | M59: =IF(F59>=1000,"1000+ Reviews", IF(F59>=500,"500-999 Reviews", IF(F59>=100,"100-499 Reviews", "Below 100 Reviews"))) -> 100-499 Reviews | N59: =IF(K59="Official Website","Low Opportunity", IF(AND(K59="No Website",E59>=4.5,F59>=500),"Very High Opportunity", IF(AND(K59="No Website",E59>=4.5),"High Opportunity", IF(K59="Social Media","Medium Opportunity","Low Opportunity")))) -> High Opportunity
A60: Rohini, Delhi | B60: mobile shops | C60: MOBILE CAFE | D60: Shop No. 3, M. M. Mall, D. C. Chowk, Sector 9, Rajapur, Sector 9, Rohini, Delhi, 110085, India | E60: 5 | F60: 245 | H60: 087448 72728 | I60: electronics_store, store, point_of_interest, service, establishment | J60: =IF(COUNTIFS($C$2:C60,C60,$D$2:D60,D60)=1,"Unique","Duplicate") -> Unique | K60: =IF(TRIM(G60)="","No Website", IF(OR( ISNUMBER(SEARCH("facebook",LOWER(G60))), ISNUMBER(SEARCH("instagram",LOWER(G60))), ISNUMBER(SEARCH("wa.me",LOWER(G60))), ISNUMBER(SEARCH("whatsapp",LOWER(G60))), ISNUMBER(SEARCH("youtube",LOWER(G60))), ISNUMBER(SEARCH("twitter",LOWER(G60))), ISNUMBER(SEARCH("x.com",LOWER(G60))), ISNUMBER(SEARCH("linkedin",LOWER(G60))), ISNUMBER(SEARCH("linktr.ee",LOWER(G60))), ISNUMBER(SEARCH("g.page",LOWER(G60))), ISNUMBER(SEARCH("maps.app.goo.gl",LOWER(G60))), ISNUMBER(SEARCH("goo.gl",LOWER(G60))) ), "Social Media", "Official Website")) -> No Website | L60: =IF(E60>=4.5,"Excellent", IF(E60>=4,"Good", IF(E60>=3,"Average","Poor"))) -> Excellent | M60: =IF(F60>=1000,"1000+ Reviews", IF(F60>=500,"500-999 Reviews", IF(F60>=100,"100-499 Reviews", "Below 100 Reviews"))) -> 100-499 Reviews | N60: =IF(K60="Official Website","Low Opportunity", IF(AND(K60="No Website",E60>=4.5,F60>=500),"Very High Opportunity", IF(AND(K60="No Website",E60>=4.5),"High Opportunity", IF(K60="Social Media","Medium Opportunity","Low Opportunity")))) -> High Opportunity
A61: Model Town, Delhi | B61: tutoring centers | C61: Vineeta Malani's Classes | D61: F-14/7 First Floor, Model Town Phase 2, Pocket E, Phase 2, Model Town, New Delhi, Delhi, 110033, India | E61: 5 | F61: 243 | H61: 098117 36707 | I61: educational_institution, point_of_interest, establishment | J61: =IF(COUNTIFS($C$2:C61,C61,$D$2:D61,D61)=1,"Unique","Duplicate") -> Unique | K61: =IF(TRIM(G61)="","No Website", IF(OR( ISNUMBER(SEARCH("facebook",LOWER(G61))), ISNUMBER(SEARCH("instagram",LOWER(G61))), ISNUMBER(SEARCH("wa.me",LOWER(G61))), ISNUMBER(SEARCH("whatsapp",LOWER(G61))), ISNUMBER(SEARCH("youtube",LOWER(G61))), ISNUMBER(SEARCH("twitter",LOWER(G61))), ISNUMBER(SEARCH("x.com",LOWER(G61))), ISNUMBER(SEARCH("linkedin",LOWER(G61))), ISNUMBER(SEARCH("linktr.ee",LOWER(G61))), ISNUMBER(SEARCH("g.page",LOWER(G61))), ISNUMBER(SEARCH("maps.app.goo.gl",LOWER(G61))), ISNUMBER(SEARCH("goo.gl",LOWER(G61))) ), "Social Media", "Official Website")) -> No Website | L61: =IF(E61>=4.5,"Excellent", IF(E61>=4,"Good", IF(E61>=3,"Average","Poor"))) -> Excellent | M61: =IF(F61>=1000,"1000+ Reviews", IF(F61>=500,"500-999 Reviews", IF(F61>=100,"100-499 Reviews", "Below 100 Reviews"))) -> 100-499 Reviews | N61: =IF(K61="Official Website","Low Opportunity", IF(AND(K61="No Website",E61>=4.5,F61>=500),"Very High Opportunity", IF(AND(K61="No Website",E61>=4.5),"High Opportunity", IF(K61="Social Media","Medium Opportunity","Low Opportunity")))) -> High Opportunity
A62: Burari, Delhi | B62: gyms | C62: The Gym | D62: Near Bank Of Baroda ,Main Road, Sant Nagar Marg, Vijay Colony, Block B, Sant Nagar, Burari, Delhi, 110084, India | E62: 4.3 | F62: 264 | G62: https://www.dronacharyathegym.com/contact-us/ | I62: gym, sports_activity_location, health, point_of_interest, establishment | J62: =IF(COUNTIFS($C$2:C62,C62,$D$2:D62,D62)=1,"Unique","Duplicate") -> Unique | K62: =IF(TRIM(G62)="","No Website", IF(OR( ISNUMBER(SEARCH("facebook",LOWER(G62))), ISNUMBER(SEARCH("instagram",LOWER(G62))), ISNUMBER(SEARCH("wa.me",LOWER(G62))), ISNUMBER(SEARCH("whatsapp",LOWER(G62))), ISNUMBER(SEARCH("youtube",LOWER(G62))), ISNUMBER(SEARCH("twitter",LOWER(G62))), ISNUMBER(SEARCH("x.com",LOWER(G62))), ISNUMBER(SEARCH("linkedin",LOWER(G62))), ISNUMBER(SEARCH("linktr.ee",LOWER(G62))), ISNUMBER(SEARCH("g.page",LOWER(G62))), ISNUMBER(SEARCH("maps.app.goo.gl",LOWER(G62))), ISNUMBER(SEARCH("goo.gl",LOWER(G62))) ), "Social Media", "Official Website")) -> Official Website | L62: =IF(E62>=4.5,"Excellent", IF(E62>=4,"Good", IF(E62>=3,"Average","Poor"))) -> Good | M62: =IF(F62>=1000,"1000+ Reviews", IF(F62>=500,"500-999 Reviews", IF(F62>=100,"100-499 Reviews", "Below 100 Reviews"))) -> 100-499 Reviews | N62: =IF(K62="Official Website","Low Opportunity", IF(AND(K62="No Website",E62>=4.5,F62>=500),"Very High Opportunity", IF(AND(K62="No Website",E62>=4.5),"High Opportunity", IF(K62="Social Media","Medium Opportunity","Low Opportunity")))) -> Low Opportunity
A63: Uttam Nagar, Delhi | B63: salons | C63: Elegant Style By Upasana Rajput - Makeup Studio & Unisex Salon | D63: E-5, Arya Samaj Rd, near Scoops, Block E, F Block, Uttam Nagar, New Delhi, Delhi, 110059, India | E63: 5 | F63: 238 | H63: 085271 18833 | I63: beauty_salon, point_of_interest, service, establishment | J63: =IF(COUNTIFS($C$2:C63,C63,$D$2:D63,D63)=1,"Unique","Duplicate") -> Unique | K63: =IF(TRIM(G63)="","No Website", IF(OR( ISNUMBER(SEARCH("facebook",LOWER(G63))), ISNUMBER(SEARCH("instagram",LOWER(G63))), ISNUMBER(SEARCH("wa.me",LOWER(G63))), ISNUMBER(SEARCH("whatsapp",LOWER(G63))), ISNUMBER(SEARCH("youtube",LOWER(G63))), ISNUMBER(SEARCH("twitter",LOWER(G63))), ISNUMBER(SEARCH("x.com",LOWER(G63))), ISNUMBER(SEARCH("linkedin",LOWER(G63))), ISNUMBER(SEARCH("linktr.ee",LOWER(G63))), ISNUMBER(SEARCH("g.page",LOWER(G63))), ISNUMBER(SEARCH("maps.app.goo.gl",LOWER(G63))), ISNUMBER(SEARCH("goo.gl",LOWER(G63))) ), "Social Media", "Official Website")) -> No Website | L63: =IF(E63>=4.5,"Excellent", IF(E63>=4,"Good", IF(E63>=3,"Average","Poor"))) -> Excellent | M63: =IF(F63>=1000,"1000+ Reviews", IF(F63>=500,"500-999 Reviews", IF(F63>=100,"100-499 Reviews", "Below 100 Reviews"))) -> 100-499 Reviews | N63: =IF(K63="Official Website","Low Opportunity", IF(AND(K63="No Website",E63>=4.5,F63>=500),"Very High Opportunity", IF(AND(K63="No Website",E63>=4.5),"High Opportunity", IF(K63="Social Media","Medium Opportunity","Low Opportunity")))) -> High Opportunity
A64: Dwarka, Delhi | B64: tutoring centers | C64: Maths Tutor In Dwarka | D64: 700, Shaheed Bhagat Singh Appartment, Pocket 1, Sector 14 Dwarka, Dwarka, New Delhi, Delhi, 110078, India | E64: 5 | F64: 237 | H64: 083685 96448 | I64: point_of_interest, establishment | J64: =IF(COUNTIFS($C$2:C64,C64,$D$2:D64,D64)=1,"Unique","Duplicate") -> Unique | K64: =IF(TRIM(G64)="","No Website", IF(OR( ISNUMBER(SEARCH("facebook",LOWER(G64))), ISNUMBER(SEARCH("instagram",LOWER(G64))), ISNUMBER(SEARCH("wa.me",LOWER(G64))), ISNUMBER(SEARCH("whatsapp",LOWER(G64))), ISNUMBER(SEARCH("youtube",LOWER(G64))), ISNUMBER(SEARCH("twitter",LOWER(G64))), ISNUMBER(SEARCH("x.com",LOWER(G64))), ISNUMBER(SEARCH("linkedin",LOWER(G64))), ISNUMBER(SEARCH("linktr.ee",LOWER(G64))), ISNUMBER(SEARCH("g.page",LOWER(G64))), ISNUMBER(SEARCH("maps.app.goo.gl",LOWER(G64))), ISNUMBER(SEARCH("goo.gl",LOWER(G64))) ), "Social Media", "Official Website")) -> No Website | L64: =IF(E64>=4.5,"Excellent", IF(E64>=4,"Good", IF(E64>=3,"Average","Poor"))) -> Excellent | M64: =IF(F64>=1000,"1000+ Reviews", IF(F64>=500,"500-999 Reviews", IF(F64>=100,"100-499 Reviews", "Below 100 Reviews"))) -> 100-499 Reviews | N64: =IF(K64="Official Website","Low Opportunity", IF(AND(K64="No Website",E64>=4.5,F64>=500),"Very High Opportunity", IF(AND(K64="No Website",E64>=4.5),"High Opportunity", IF(K64="Social Media","Medium Opportunity","Low Opportunity")))) -> High Opportunity
A65: Burari, Delhi | B65: gyms | C65: Country Fitness Gym sant nagar burari | D65: 863/3 main, Burari Rd, above ashokis garment, opposite vijay sales, Parvatiya Anchal, Maurya Enclave, Sant Nagar, Burari, New Delhi, Delhi, 110084, India | E65: 4.1 | F65: 478 | G65: http://www.countryfitness.in/ | H65: 088029 99902 | I65: gym, sports_activity_location, health, point_of_interest, establishment | J65: =IF(COUNTIFS($C$2:C65,C65,$D$2:D65,D65)=1,"Unique","Duplicate") -> Unique | K65: =IF(TRIM(G65)="","No Website", IF(OR( ISNUMBER(SEARCH("facebook",LOWER(G65))), ISNUMBER(SEARCH("instagram",LOWER(G65))), ISNUMBER(SEARCH("wa.me",LOWER(G65))), ISNUMBER(SEARCH("whatsapp",LOWER(G65))), ISNUMBER(SEARCH("youtube",LOWER(G65))), ISNUMBER(SEARCH("twitter",LOWER(G65))), ISNUMBER(SEARCH("x.com",LOWER(G65))), ISNUMBER(SEARCH("linkedin",LOWER(G65))), ISNUMBER(SEARCH("linktr.ee",LOWER(G65))), ISNUMBER(SEARCH("g.page",LOWER(G65))), ISNUMBER(SEARCH("maps.app.goo.gl",LOWER(G65))), ISNUMBER(SEARCH("goo.gl",LOWER(G65))) ), "Social Media", "Official Website")) -> Official Website | L65: =IF(E65>=4.5,"Excellent", IF(E65>=4,"Good", IF(E65>=3,"Average","Poor"))) -> Good | M65: =IF(F65>=1000,"1000+ Reviews", IF(F65>=500,"500-999 Reviews", IF(F65>=100,"100-499 Reviews", "Below 100 Reviews"))) -> 100-499 Reviews | N65: =IF(K65="Official Website","Low Opportunity", IF(AND(K65="No Website",E65>=4.5,F65>=500),"Very High Opportunity", IF(AND(K65="No Website",E65>=4.5),"High Opportunity", IF(K65="Social Media","Medium Opportunity","Low Opportunity")))) -> Low Opportunity
A66: Janakpuri, Delhi | B66: tutoring centers | C66: S2 Classes for school Education(9th and 10th Maths and science | D66: 237B pkt, flat no, 2, Major P Srikumar Marg, Block C2C, Janakpuri, New Delhi, Delhi, 110058, India | E66: 5 | F66: 235 | H66: 073031 20430 | I66: service, point_of_interest, establishment | J66: =IF(COUNTIFS($C$2:C66,C66,$D$2:D66,D66)=1,"Unique","Duplicate") -> Unique | K66: =IF(TRIM(G66)="","No Website", IF(OR( ISNUMBER(SEARCH("facebook",LOWER(G66))), ISNUMBER(SEARCH("instagram",LOWER(G66))), ISNUMBER(SEARCH("wa.me",LOWER(G66))), ISNUMBER(SEARCH("whatsapp",LOWER(G66))), ISNUMBER(SEARCH("youtube",LOWER(G66))), ISNUMBER(SEARCH("twitter",LOWER(G66))), ISNUMBER(SEARCH("x.com",LOWER(G66))), ISNUMBER(SEARCH("linkedin",LOWER(G66))), ISNUMBER(SEARCH("linktr.ee",LOWER(G66))), ISNUMBER(SEARCH("g.page",LOWER(G66))), ISNUMBER(SEARCH("maps.app.goo.gl",LOWER(G66))), ISNUMBER(SEARCH("goo.gl",LOWER(G66))) ), "Social Media", "Official Website")) -> No Website | L66: =IF(E66>=4.5,"Excellent", IF(E66>=4,"Good", IF(E66>=3,"Average","Poor"))) -> Excellent | M66: =IF(F66>=1000,"1000+ Reviews", IF(F66>=500,"500-999 Reviews", IF(F66>=100,"100-499 Reviews", "Below 100 Reviews"))) -> 100-499 Reviews | N66: =IF(K66="Official Website","Low Opportunity", IF(AND(K66="No Website",E66>=4.5,F66>=500),"Very High Opportunity", IF(AND(K66="No Website",E66>=4.5),"High Opportunity", IF(K66="Social Media","Medium Opportunity","Low Opportunity")))) -> High Opportunity
A67: Preet Vihar, Delhi | B67: tutoring centers | C67: Jigyasa tutors bureau - Maths Home Tuition Tutor in Preet Vihar, Laxmi Nagar East Delhi | D67: c, 16/2, Street No. 7, New Govindpura, Swasthya Vihar, Delhi, 110092, India | E67: 5 | F67: 229 | H67: 098112 38316 | I67: consultant, educational_institution, service, point_of_interest, establishment | J67: =IF(COUNTIFS($C$2:C67,C67,$D$2:D67,D67)=1,"Unique","Duplicate") -> Unique | K67: =IF(TRIM(G67)="","No Website", IF(OR( ISNUMBER(SEARCH("facebook",LOWER(G67))), ISNUMBER(SEARCH("instagram",LOWER(G67))), ISNUMBER(SEARCH("wa.me",LOWER(G67))), ISNUMBER(SEARCH("whatsapp",LOWER(G67))), ISNUMBER(SEARCH("youtube",LOWER(G67))), ISNUMBER(SEARCH("twitter",LOWER(G67))), ISNUMBER(SEARCH("x.com",LOWER(G67))), ISNUMBER(SEARCH("linkedin",LOWER(G67))), ISNUMBER(SEARCH("linktr.ee",LOWER(G67))), ISNUMBER(SEARCH("g.page",LOWER(G67))), ISNUMBER(SEARCH("maps.app.goo.gl",LOWER(G67))), ISNUMBER(SEARCH("goo.gl",LOWER(G67))) ), "Social Media", "Official Website")) -> No Website | L67: =IF(E67>=4.5,"Excellent", IF(E67>=4,"Good", IF(E67>=3,"Average","Poor"))) -> Excellent | M67: =IF(F67>=1000,"1000+ Reviews", IF(F67>=500,"500-999 Reviews", IF(F67>=100,"100-499 Reviews", "Below 100 Reviews"))) -> 100-499 Reviews | N67: =IF(K67="Official Website","Low Opportunity", IF(AND(K67="No Website",E67>=4.5,F67>=500),"Very High Opportunity", IF(AND(K67="No Website",E67>=4.5),"High Opportunity", IF(K67="Social Media","Medium Opportunity","Low Opportunity")))) -> High Opportunity
A68: Mayapuri, Delhi | B68: tutoring centers | C68: ARISTOTELIAN AKADEMIA (RPC) | D68: near clock tower, A Block, Nanak Pura, Hari Nagar, New Delhi, Delhi, 110064, India | E68: 5 | F68: 226 | I68: point_of_interest, establishment | J68: =IF(COUNTIFS($C$2:C68,C68,$D$2:D68,D68)=1,"Unique","Duplicate") -> Unique | K68: =IF(TRIM(G68)="","No Website", IF(OR( ISNUMBER(SEARCH("facebook",LOWER(G68))), ISNUMBER(SEARCH("instagram",LOWER(G68))), ISNUMBER(SEARCH("wa.me",LOWER(G68))), ISNUMBER(SEARCH("whatsapp",LOWER(G68))), ISNUMBER(SEARCH("youtube",LOWER(G68))), ISNUMBER(SEARCH("twitter",LOWER(G68))), ISNUMBER(SEARCH("x.com",LOWER(G68))), ISNUMBER(SEARCH("linkedin",LOWER(G68))), ISNUMBER(SEARCH("linktr.ee",LOWER(G68))), ISNUMBER(SEARCH("g.page",LOWER(G68))), ISNUMBER(SEARCH("maps.app.goo.gl",LOWER(G68))), ISNUMBER(SEARCH("goo.gl",LOWER(G68))) ), "Social Media", "Official Website")) -> No Website | L68: =IF(E68>=4.5,"Excellent", IF(E68>=4,"Good", IF(E68>=3,"Average","Poor"))) -> Excellent | M68: =IF(F68>=1000,"1000+ Reviews", IF(F68>=500,"500-999 Reviews", IF(F68>=100,"100-499 Reviews", "Below 100 Reviews"))) -> 100-499 Reviews | N68: =IF(K68="Official Website","Low Opportunity", IF(AND(K68="No Website",E68>=4.5,F68>=500),"Very High Opportunity", IF(AND(K68="No Website",E68>=4.5),"High Opportunity", IF(K68="Social Media","Medium Opportunity","Low Opportunity")))) -> High Opportunity
A69: Uttam Nagar, Delhi | B69: tutoring centers | C69: Pathak Tutorials - Best Coaching and Tuition Center | D69: WZ 14B, Om Vihar Phase 1 Rd, Phase 1, Om Vihar, Uttam Nagar, Delhi, 110059, India | E69: 5 | F69: 220 | H69: 098112 55935 | I69: educational_institution, health, service, point_of_interest, establishment | J69: =IF(COUNTIFS($C$2:C69,C69,$D$2:D69,D69)=1,"Unique","Duplicate") -> Unique | K69: =IF(TRIM(G69)="","No Website", IF(OR( ISNUMBER(SEARCH("facebook",LOWER(G69))), ISNUMBER(SEARCH("instagram",LOWER(G69))), ISNUMBER(SEARCH("wa.me",LOWER(G69))), ISNUMBER(SEARCH("whatsapp",LOWER(G69))), ISNUMBER(SEARCH("youtube",LOWER(G69))), ISNUMBER(SEARCH("twitter",LOWER(G69))), ISNUMBER(SEARCH("x.com",LOWER(G69))), ISNUMBER(SEARCH("linkedin",LOWER(G69))), ISNUMBER(SEARCH("linktr.ee",LOWER(G69))), ISNUMBER(SEARCH("g.page",LOWER(G69))), ISNUMBER(SEARCH("maps.app.goo.gl",LOWER(G69))), ISNUMBER(SEARCH("goo.gl",LOWER(G69))) ), "Social Media", "Official Website")) -> No Website | L69: =IF(E69>=4.5,"Excellent", IF(E69>=4,"Good", IF(E69>=3,"Average","Poor"))) -> Excellent | M69: =IF(F69>=1000,"1000+ Reviews", IF(F69>=500,"500-999 Reviews", IF(F69>=100,"100-499 Reviews", "Below 100 Reviews"))) -> 100-499 Reviews | N69: =IF(K69="Official Website","Low Opportunity", IF(AND(K69="No Website",E69>=4.5,F69>=500),"Very High Opportunity", IF(AND(K69="No Website",E69>=4.5),"High Opportunity", IF(K69="Social Media","Medium Opportunity","Low Opportunity")))) -> High Opportunity
A70: Uttam Nagar, Delhi | B70: mobile shops | C70: Rewy Mobile Store - Patel Nagar | D70: Shivaji Marg, Block C, Kiran Garden, Uttam Nagar, Delhi, 110059, India | E70: 5 | F70: 218 | H70: 078272 60260 | I70: cell_phone_store, wholesaler, point_of_interest, store, service, establishment | J70: =IF(COUNTIFS($C$2:C70,C70,$D$2:D70,D70)=1,"Unique","Duplicate") -> Unique | K70: =IF(TRIM(G70)="","No Website", IF(OR( ISNUMBER(SEARCH("facebook",LOWER(G70))), ISNUMBER(SEARCH("instagram",LOWER(G70))), ISNUMBER(SEARCH("wa.me",LOWER(G70))), ISNUMBER(SEARCH("whatsapp",LOWER(G70))), ISNUMBER(SEARCH("youtube",LOWER(G70))), ISNUMBER(SEARCH("twitter",LOWER(G70))), ISNUMBER(SEARCH("x.com",LOWER(G70))), ISNUMBER(SEARCH("linkedin",LOWER(G70))), ISNUMBER(SEARCH("linktr.ee",LOWER(G70))), ISNUMBER(SEARCH("g.page",LOWER(G70))), ISNUMBER(SEARCH("maps.app.goo.gl",LOWER(G70))), ISNUMBER(SEARCH("goo.gl",LOWER(G70))) ), "Social Media", "Official Website")) -> No Website | L70: =IF(E70>=4.5,"Excellent", IF(E70>=4,"Good", IF(E70>=3,"Average","Poor"))) -> Excellent | M70: =IF(F70>=1000,"1000+ Reviews", IF(F70>=500,"500-999 Reviews", IF(F70>=100,"100-499 Reviews", "Below 100 Reviews"))) -> 100-499 Reviews | N70: =IF(K70="Official Website","Low Opportunity", IF(AND(K70="No Website",E70>=4.5,F70>=500),"Very High Opportunity", IF(AND(K70="No Website",E70>=4.5),"High Opportunity", IF(K70="Social Media","Medium Opportunity","Low Opportunity")))) -> High Opportunity
A71: Burari, Delhi | B71: gyms | C71: Fitness Arena Unisex Gym | D71: 5220, 2nd floor, 25 Feet Rd, Satya Vihar, Baba Colony, Burari, Delhi, 110084, India | E71: 5 | F71: 26 | G71: https://www.instagram.com/fitness_arena_unisex_gym/ | H71: 080107 10551 | I71: gym, sports_activity_location, health, point_of_interest, establishment | J71: =IF(COUNTIFS($C$2:C71,C71,$D$2:D71,D71)=1,"Unique","Duplicate") -> Unique | K71: =IF(TRIM(G71)="","No Website", IF(OR( ISNUMBER(SEARCH("facebook",LOWER(G71))), ISNUMBER(SEARCH("instagram",LOWER(G71))), ISNUMBER(SEARCH("wa.me",LOWER(G71))), ISNUMBER(SEARCH("whatsapp",LOWER(G71))), ISNUMBER(SEARCH("youtube",LOWER(G71))), ISNUMBER(SEARCH("twitter",LOWER(G71))), ISNUMBER(SEARCH("x.com",LOWER(G71))), ISNUMBER(SEARCH("linkedin",LOWER(G71))), ISNUMBER(SEARCH("linktr.ee",LOWER(G71))), ISNUMBER(SEARCH("g.page",LOWER(G71))), ISNUMBER(SEARCH("maps.app.goo.gl",LOWER(G71))), ISNUMBER(SEARCH("goo.gl",LOWER(G71))) ), "Social Media", "Official Website")) -> Social Media | L71: =IF(E71>=4.5,"Excellent", IF(E71>=4,"Good", IF(E71>=3,"Average","Poor"))) -> Excellent | M71: =IF(F71>=1000,"1000+ Reviews", IF(F71>=500,"500-999 Reviews", IF(F71>=100,"100-499 Reviews", "Below 100 Reviews"))) -> Below 100 Reviews | N71: =IF(K71="Official Website","Low Opportunity", IF(AND(K71="No Website",E71>=4.5,F71>=500),"Very High Opportunity", IF(AND(K71="No Website",E71>=4.5),"High Opportunity", IF(K71="Social Media","Medium Opportunity","Low Opportunity")))) -> Medium Opportunity
A72: Burari, Delhi | B72: gyms | C72: Pack Physique | D72: 86/3, Sant Nagar Marg, Parvatiya Anchal, Maurya Enclave, Baba Colony, Burari, Delhi, 110084, India | E72: 4.4 | F72: 167 | I72: gym, sports_activity_location, health, point_of_interest, establishment | J72: =IF(COUNTIFS($C$2:C72,C72,$D$2:D72,D72)=1,"Unique","Duplicate") -> Unique | K72: =IF(TRIM(G72)="","No Website", IF(OR( ISNUMBER(SEARCH("facebook",LOWER(G72))), ISNUMBER(SEARCH("instagram",LOWER(G72))), ISNUMBER(SEARCH("wa.me",LOWER(G72))), ISNUMBER(SEARCH("whatsapp",LOWER(G72))), ISNUMBER(SEARCH("youtube",LOWER(G72))), ISNUMBER(SEARCH("twitter",LOWER(G72))), ISNUMBER(SEARCH("x.com",LOWER(G72))), ISNUMBER(SEARCH("linkedin",LOWER(G72))), ISNUMBER(SEARCH("linktr.ee",LOWER(G72))), ISNUMBER(SEARCH("g.page",LOWER(G72))), ISNUMBER(SEARCH("maps.app.goo.gl",LOWER(G72))), ISNUMBER(SEARCH("goo.gl",LOWER(G72))) ), "Social Media", "Official Website")) -> No Website | L72: =IF(E72>=4.5,"Excellent", IF(E72>=4,"Good", IF(E72>=3,"Average","Poor"))) -> Good | M72: =IF(F72>=1000,"1000+ Reviews", IF(F72>=500,"500-999 Reviews", IF(F72>=100,"100-499 Reviews", "Below 100 Reviews"))) -> 100-499 Reviews | N72: =IF(K72="Official Website","Low Opportunity", IF(AND(K72="No Website",E72>=4.5,F72>=500),"Very High Opportunity", IF(AND(K72="No Website",E72>=4.5),"High Opportunity", IF(K72="Social Media","Medium Opportunity","Low Opportunity")))) -> Low Opportunity
A73: Rohini, Delhi | B73: tutoring centers | C73: Edu-Maths (Coaching Centre Rohini Sec 18 ) | D73: First floor, B-9/3, opposite Mother dairy street, above Dwarka Namkeen, Pocket 11, Sector 18, Rohini, Delhi, 110089, India | E73: 5 | F73: 215 | H73: 095601 73540 | I73: school, educational_institution, point_of_interest, establishment | J73: =IF(COUNTIFS($C$2:C73,C73,$D$2:D73,D73)=1,"Unique","Duplicate") -> Unique | K73: =IF(TRIM(G73)="","No Website", IF(OR( ISNUMBER(SEARCH("facebook",LOWER(G73))), ISNUMBER(SEARCH("instagram",LOWER(G73))), ISNUMBER(SEARCH("wa.me",LOWER(G73))), ISNUMBER(SEARCH("whatsapp",LOWER(G73))), ISNUMBER(SEARCH("youtube",LOWER(G73))), ISNUMBER(SEARCH("twitter",LOWER(G73))), ISNUMBER(SEARCH("x.com",LOWER(G73))), ISNUMBER(SEARCH("linkedin",LOWER(G73))), ISNUMBER(SEARCH("linktr.ee",LOWER(G73))), ISNUMBER(SEARCH("g.page",LOWER(G73))), ISNUMBER(SEARCH("maps.app.goo.gl",LOWER(G73))), ISNUMBER(SEARCH("goo.gl",LOWER(G73))) ), "Social Media", "Official Website")) -> No Website | L73: =IF(E73>=4.5,"Excellent", IF(E73>=4,"Good", IF(E73>=3,"Average","Poor"))) -> Excellent | M73: =IF(F73>=1000,"1000+ Reviews", IF(F73>=500,"500-999 Reviews", IF(F73>=100,"100-499 Reviews", "Below 100 Reviews"))) -> 100-499 Reviews | N73: =IF(K73="Official Website","Low Opportunity", IF(AND(K73="No Website",E73>=4.5,F73>=500),"Very High Opportunity", IF(AND(K73="No Website",E73>=4.5),"High Opportunity", IF(K73="Social Media","Medium Opportunity","Low Opportunity")))) -> High Opportunity
A74: Shahdara, Delhi | B74: clinics | C74: DIABETES, SKIN & HAIR CLINIC(Dr Ritesh Bansal & Dr Candy Garg) | D74: H-36/A, near Shanti Nursing Home, P Block, Block H, Navin Shahdara, Shahdara, Delhi, 110032, India | E74: 5 | F74: 214 | H74: 098717 00935 | I74: skin_care_clinic, hair_care, doctor, beauty_salon, medical_clinic, health, service, point_of_interest, establishment | J74: =IF(COUNTIFS($C$2:C74,C74,$D$2:D74,D74)=1,"Unique","Duplicate") -> Unique | K74: =IF(TRIM(G74)="","No Website", IF(OR( ISNUMBER(SEARCH("facebook",LOWER(G74))), ISNUMBER(SEARCH("instagram",LOWER(G74))), ISNUMBER(SEARCH("wa.me",LOWER(G74))), ISNUMBER(SEARCH("whatsapp",LOWER(G74))), ISNUMBER(SEARCH("youtube",LOWER(G74))), ISNUMBER(SEARCH("twitter",LOWER(G74))), ISNUMBER(SEARCH("x.com",LOWER(G74))), ISNUMBER(SEARCH("linkedin",LOWER(G74))), ISNUMBER(SEARCH("linktr.ee",LOWER(G74))), ISNUMBER(SEARCH("g.page",LOWER(G74))), ISNUMBER(SEARCH("maps.app.goo.gl",LOWER(G74))), ISNUMBER(SEARCH("goo.gl",LOWER(G74))) ), "Social Media", "Official Website")) -> No Website | L74: =IF(E74>=4.5,"Excellent", IF(E74>=4,"Good", IF(E74>=3,"Average","Poor"))) -> Excellent | M74: =IF(F74>=1000,"1000+ Reviews", IF(F74>=500,"500-999 Reviews", IF(F74>=100,"100-499 Reviews", "Below 100 Reviews"))) -> 100-499 Reviews | N74: =IF(K74="Official Website","Low Opportunity", IF(AND(K74="No Website",E74>=4.5,F74>=500),"Very High Opportunity", IF(AND(K74="No Website",E74>=4.5),"High Opportunity", IF(K74="Social Media","Medium Opportunity","Low Opportunity")))) -> High Opportunity
A75: Burari, Delhi | B75: gyms | C75: Fitness Law Gym | D75: Shree Rama Dharam Kanta, near shalimar palace, Indraprasth Colony, Burari, Delhi, 110084, India | E75: 4.4 | F75: 70 | H75: 092100 09979 | I75: gym, sports_activity_location, health, point_of_interest, establishment | J75: =IF(COUNTIFS($C$2:C75,C75,$D$2:D75,D75)=1,"Unique","Duplicate") -> Unique | K75: =IF(TRIM(G75)="","No Website", IF(OR( ISNUMBER(SEARCH("facebook",LOWER(G75))), ISNUMBER(SEARCH("instagram",LOWER(G75))), ISNUMBER(SEARCH("wa.me",LOWER(G75))), ISNUMBER(SEARCH("whatsapp",LOWER(G75))), ISNUMBER(SEARCH("youtube",LOWER(G75))), ISNUMBER(SEARCH("twitter",LOWER(G75))), ISNUMBER(SEARCH("x.com",LOWER(G75))), ISNUMBER(SEARCH("linkedin",LOWER(G75))), ISNUMBER(SEARCH("linktr.ee",LOWER(G75))), ISNUMBER(SEARCH("g.page",LOWER(G75))), ISNUMBER(SEARCH("maps.app.goo.gl",LOWER(G75))), ISNUMBER(SEARCH("goo.gl",LOWER(G75))) ), "Social Media", "Official Website")) -> No Website | L75: =IF(E75>=4.5,"Excellent", IF(E75>=4,"Good", IF(E75>=3,"Average","Poor"))) -> Good | M75: =IF(F75>=1000,"1000+ Reviews", IF(F75>=500,"500-999 Reviews", IF(F75>=100,"100-499 Reviews", "Below 100 Reviews"))) -> Below 100 Reviews | N75: =IF(K75="Official Website","Low Opportunity", IF(AND(K75="No Website",E75>=4.5,F75>=500),"Very High Opportunity", IF(AND(K75="No Website",E75>=4.5),"High Opportunity", IF(K75="Social Media","Medium Opportunity","Low Opportunity")))) -> Low Opportunity
A76: Malviya Nagar, Delhi | B76: gyms | C76: FWS Transformation Studio | D76: JE -12 Basement Tikona Park, Khirki Extension, Malviya Nagar, New Delhi, Delhi 110017, India | E76: 5 | F76: 205 | H76: 098915 55143 | I76: fitness_center, gym, sports_activity_location, health, point_of_interest, establishment | J76: =IF(COUNTIFS($C$2:C76,C76,$D$2:D76,D76)=1,"Unique","Duplicate") -> Unique | K76: =IF(TRIM(G76)="","No Website", IF(OR( ISNUMBER(SEARCH("facebook",LOWER(G76))), ISNUMBER(SEARCH("instagram",LOWER(G76))), ISNUMBER(SEARCH("wa.me",LOWER(G76))), ISNUMBER(SEARCH("whatsapp",LOWER(G76))), ISNUMBER(SEARCH("youtube",LOWER(G76))), ISNUMBER(SEARCH("twitter",LOWER(G76))), ISNUMBER(SEARCH("x.com",LOWER(G76))), ISNUMBER(SEARCH("linkedin",LOWER(G76))), ISNUMBER(SEARCH("linktr.ee",LOWER(G76))), ISNUMBER(SEARCH("g.page",LOWER(G76))), ISNUMBER(SEARCH("maps.app.goo.gl",LOWER(G76))), ISNUMBER(SEARCH("goo.gl",LOWER(G76))) ), "Social Media", "Official Website")) -> No Website | L76: =IF(E76>=4.5,"Excellent", IF(E76>=4,"Good", IF(E76>=3,"Average","Poor"))) -> Excellent | M76: =IF(F76>=1000,"1000+ Reviews", IF(F76>=500,"500-999 Reviews", IF(F76>=100,"100-499 Reviews", "Below 100 Reviews"))) -> 100-499 Reviews | N76: =IF(K76="Official Website","Low Opportunity", IF(AND(K76="No Website",E76>=4.5,F76>=500),"Very High Opportunity", IF(AND(K76="No Website",E76>=4.5),"High Opportunity", IF(K76="Social Media","Medium Opportunity","Low Opportunity")))) -> High Opportunity
A77: Burari, Delhi | B77: clothing stores | C77: V-Mart - Delhi-Burari | D77: Virendar Nagar, Block B, Sant Nagar, 100 feet Road, North, near Axis Bank, Block B, Sant Nagar, Burari, Delhi, 110084, India | E77: 4.9 | F77: 7647 | G77: https://stores.vmartretail.com/clothing-mart-burari-north-delhi-32949/home | H77: 092895 51045 | I77: clothing_store, convenience_store, department_store, food_store, store, food, point_of_interest, establishment | J77: =IF(COUNTIFS($C$2:C77,C77,$D$2:D77,D77)=1,"Unique","Duplicate") -> Unique | K77: =IF(TRIM(G77)="","No Website", IF(OR( ISNUMBER(SEARCH("facebook",LOWER(G77))), ISNUMBER(SEARCH("instagram",LOWER(G77))), ISNUMBER(SEARCH("wa.me",LOWER(G77))), ISNUMBER(SEARCH("whatsapp",LOWER(G77))), ISNUMBER(SEARCH("youtube",LOWER(G77))), ISNUMBER(SEARCH("twitter",LOWER(G77))), ISNUMBER(SEARCH("x.com",LOWER(G77))), ISNUMBER(SEARCH("linkedin",LOWER(G77))), ISNUMBER(SEARCH("linktr.ee",LOWER(G77))), ISNUMBER(SEARCH("g.page",LOWER(G77))), ISNUMBER(SEARCH("maps.app.goo.gl",LOWER(G77))), ISNUMBER(SEARCH("goo.gl",LOWER(G77))) ), "Social Media", "Official Website")) -> Official Website | L77: =IF(E77>=4.5,"Excellent", IF(E77>=4,"Good", IF(E77>=3,"Average","Poor"))) -> Excellent | M77: =IF(F77>=1000,"1000+ Reviews", IF(F77>=500,"500-999 Reviews", IF(F77>=100,"100-499 Reviews", "Below 100 Reviews"))) -> 1000+ Reviews | N77: =IF(K77="Official Website","Low Opportunity", IF(AND(K77="No Website",E77>=4.5,F77>=500),"Very High Opportunity", IF(AND(K77="No Website",E77>=4.5),"High Opportunity", IF(K77="Social Media","Medium Opportunity","Low Opportunity")))) -> Low Opportunity
A78: Burari, Delhi | B78: clothing stores | C78: GROVER GARMENTS | D78: P5RX+HCX, A-458, 100 Feet Rd, Block B, Sant Nagar, Burari, Delhi, 110084, India | E78: 4.3 | F78: 1021 | H78: 099993 33002 | I78: clothing_store, store, point_of_interest, establishment | J78: =IF(COUNTIFS($C$2:C78,C78,$D$2:D78,D78)=1,"Unique","Duplicate") -> Unique | K78: =IF(TRIM(G78)="","No Website", IF(OR( ISNUMBER(SEARCH("facebook",LOWER(G78))), ISNUMBER(SEARCH("instagram",LOWER(G78))), ISNUMBER(SEARCH("wa.me",LOWER(G78))), ISNUMBER(SEARCH("whatsapp",LOWER(G78))), ISNUMBER(SEARCH("youtube",LOWER(G78))), ISNUMBER(SEARCH("twitter",LOWER(G78))), ISNUMBER(SEARCH("x.com",LOWER(G78))), ISNUMBER(SEARCH("linkedin",LOWER(G78))), ISNUMBER(SEARCH("linktr.ee",LOWER(G78))), ISNUMBER(SEARCH("g.page",LOWER(G78))), ISNUMBER(SEARCH("maps.app.goo.gl",LOWER(G78))), ISNUMBER(SEARCH("goo.gl",LOWER(G78))) ), "Social Media", "Official Website")) -> No Website | L78: =IF(E78>=4.5,"Excellent", IF(E78>=4,"Good", IF(E78>=3,"Average","Poor"))) -> Good | M78: =IF(F78>=1000,"1000+ Reviews", IF(F78>=500,"500-999 Reviews", IF(F78>=100,"100-499 Reviews", "Below 100 Reviews"))) -> 1000+ Reviews | N78: =IF(K78="Official Website","Low Opportunity", IF(AND(K78="No Website",E78>=4.5,F78>=500),"Very High Opportunity", IF(AND(K78="No Website",E78>=4.5),"High Opportunity", IF(K78="Social Media","Medium Opportunity","Low Opportunity")))) -> Low Opportunity
A79: Burari, Delhi | B79: clothing stores | C79: Picola Vastra Bhandar- Sant Nagar, Burari | Womens | Mens | Kids | Wedding | Ethnic | Party | Casual | Western | Plus Size | D79: 775, 100, foota road, Vijay Colony, Block B, Sant Nagar, Burari, Delhi, 110084, India | E79: 4.9 | F79: 819 | G79: http://picolavastrabhandar.com/ | H79: 093184 92967 | I79: clothing_store, womens_clothing_store, store, point_of_interest, establishment | J79: =IF(COUNTIFS($C$2:C79,C79,$D$2:D79,D79)=1,"Unique","Duplicate") -> Unique | K79: =IF(TRIM(G79)="","No Website", IF(OR( ISNUMBER(SEARCH("facebook",LOWER(G79))), ISNUMBER(SEARCH("instagram",LOWER(G79))), ISNUMBER(SEARCH("wa.me",LOWER(G79))), ISNUMBER(SEARCH("whatsapp",LOWER(G79))), ISNUMBER(SEARCH("youtube",LOWER(G79))), ISNUMBER(SEARCH("twitter",LOWER(G79))), ISNUMBER(SEARCH("x.com",LOWER(G79))), ISNUMBER(SEARCH("linkedin",LOWER(G79))), ISNUMBER(SEARCH("linktr.ee",LOWER(G79))), ISNUMBER(SEARCH("g.page",LOWER(G79))), ISNUMBER(SEARCH("maps.app.goo.gl",LOWER(G79))), ISNUMBER(SEARCH("goo.gl",LOWER(G79))) ), "Social Media", "Official Website")) -> Official Website | L79: =IF(E79>=4.5,"Excellent", IF(E79>=4,"Good", IF(E79>=3,"Average","Poor"))) -> Excellent | M79: =IF(F79>=1000,"1000+ Reviews", IF(F79>=500,"500-999 Reviews", IF(F79>=100,"100-499 Reviews", "Below 100 Reviews"))) -> 500-999 Reviews | N79: =IF(K79="Official Website","Low Opportunity", IF(AND(K79="No Website",E79>=4.5,F79>=500),"Very High Opportunity", IF(AND(K79="No Website",E79>=4.5),"High Opportunity", IF(K79="Social Media","Medium Opportunity","Low Opportunity")))) -> Low Opportunity
A80: Rohini, Delhi | B80: pharmacies | C80: MAHADEV PHARMACY | MEDICINE AVAILABLE IN ROHINI,NEW DELHI | | D80: SHOP NO 45, CSC -6, opposite Shakti Apartments, DDA Market, Pocket 5, Sector 9, Rohini, New Delhi, Delhi, 110085, India | E80: 5 | F80: 194 | H80: 070429 55904 | I80: pharmacy, drugstore, cosmetics_store, health, store, point_of_interest, establishment | J80: =IF(COUNTIFS($C$2:C80,C80,$D$2:D80,D80)=1,"Unique","Duplicate") -> Unique | K80: =IF(TRIM(G80)="","No Website", IF(OR( ISNUMBER(SEARCH("facebook",LOWER(G80))), ISNUMBER(SEARCH("instagram",LOWER(G80))), ISNUMBER(SEARCH("wa.me",LOWER(G80))), ISNUMBER(SEARCH("whatsapp",LOWER(G80))), ISNUMBER(SEARCH("youtube",LOWER(G80))), ISNUMBER(SEARCH("twitter",LOWER(G80))), ISNUMBER(SEARCH("x.com",LOWER(G80))), ISNUMBER(SEARCH("linkedin",LOWER(G80))), ISNUMBER(SEARCH("linktr.ee",LOWER(G80))), ISNUMBER(SEARCH("g.page",LOWER(G80))), ISNUMBER(SEARCH("maps.app.goo.gl",LOWER(G80))), ISNUMBER(SEARCH("goo.gl",LOWER(G80))) ), "Social Media", "Official Website")) -> No Website | L80: =IF(E80>=4.5,"Excellent", IF(E80>=4,"Good", IF(E80>=3,"Average","Poor"))) -> Excellent | M80: =IF(F80>=1000,"1000+ Reviews", IF(F80>=500,"500-999 Reviews", IF(F80>=100,"100-499 Reviews", "Below 100 Reviews"))) -> 100-499 Reviews | N80: =IF(K80="Official Website","Low Opportunity", IF(AND(K80="No Website",E80>=4.5,F80>=500),"Very High Opportunity", IF(AND(K80="No Website",E80>=4.5),"High Opportunity", IF(K80="Social Media","Medium Opportunity","Low Opportunity")))) -> High Opportunity
A81: Greater Kailash, Delhi | B81: furniture stores | C81: Bespoke home furniture | D81: Hansraj Gupta Rd, near HSBC BANK, Greater Kailash-1, Block R, Greater Kailash I, Greater Kailash, New Delhi, Delhi 110048, India | E81: 5 | F81: 193 | H81: 098712 74657 | I81: furniture_store, home_improvement_store, home_goods_store, store, manufacturer, service, point_of_interest, establishment | J81: =IF(COUNTIFS($C$2:C81,C81,$D$2:D81,D81)=1,"Unique","Duplicate") -> Unique | K81: =IF(TRIM(G81)="","No Website", IF(OR( ISNUMBER(SEARCH("facebook",LOWER(G81))), ISNUMBER(SEARCH("instagram",LOWER(G81))), ISNUMBER(SEARCH("wa.me",LOWER(G81))), ISNUMBER(SEARCH("whatsapp",LOWER(G81))), ISNUMBER(SEARCH("youtube",LOWER(G81))), ISNUMBER(SEARCH("twitter",LOWER(G81))), ISNUMBER(SEARCH("x.com",LOWER(G81))), ISNUMBER(SEARCH("linkedin",LOWER(G81))), ISNUMBER(SEARCH("linktr.ee",LOWER(G81))), ISNUMBER(SEARCH("g.page",LOWER(G81))), ISNUMBER(SEARCH("maps.app.goo.gl",LOWER(G81))), ISNUMBER(SEARCH("goo.gl",LOWER(G81))) ), "Social Media", "Official Website")) -> No Website | L81: =IF(E81>=4.5,"Excellent", IF(E81>=4,"Good", IF(E81>=3,"Average","Poor"))) -> Excellent | M81: =IF(F81>=1000,"1000+ Reviews", IF(F81>=500,"500-999 Reviews", IF(F81>=100,"100-499 Reviews", "Below 100 Reviews"))) -> 100-499 Reviews | N81: =IF(K81="Official Website","Low Opportunity", IF(AND(K81="No Website",E81>=4.5,F81>=500),"Very High Opportunity", IF(AND(K81="No Website",E81>=4.5),"High Opportunity", IF(K81="Social Media","Medium Opportunity","Low Opportunity")))) -> High Opportunity
A82: Burari, Delhi | B82: clothing stores | C82: Cantabil | D82: Khasra No 863/2, Maurya Enclave, Sant Nagar, Burari, New Delhi, Delhi, 110084, India | E82: 4.8 | F82: 175 | G82: https://stores.cantabilinternational.com/cantabil-cantabil-retail-india-limited-clothing-stores-burari-new-delhi-306003/Home?utm_source=locator&utm_medium=googleplaces | H82: 092666 29468 | I82: clothing_store, womens_clothing_store, store, point_of_interest, establishment | J82: =IF(COUNTIFS($C$2:C82,C82,$D$2:D82,D82)=1,"Unique","Duplicate") -> Unique | K82: =IF(TRIM(G82)="","No Website", IF(OR( ISNUMBER(SEARCH("facebook",LOWER(G82))), ISNUMBER(SEARCH("instagram",LOWER(G82))), ISNUMBER(SEARCH("wa.me",LOWER(G82))), ISNUMBER(SEARCH("whatsapp",LOWER(G82))), ISNUMBER(SEARCH("youtube",LOWER(G82))), ISNUMBER(SEARCH("twitter",LOWER(G82))), ISNUMBER(SEARCH("x.com",LOWER(G82))), ISNUMBER(SEARCH("linkedin",LOWER(G82))), ISNUMBER(SEARCH("linktr.ee",LOWER(G82))), ISNUMBER(SEARCH("g.page",LOWER(G82))), ISNUMBER(SEARCH("maps.app.goo.gl",LOWER(G82))), ISNUMBER(SEARCH("goo.gl",LOWER(G82))) ), "Social Media", "Official Website")) -> Official Website | L82: =IF(E82>=4.5,"Excellent", IF(E82>=4,"Good", IF(E82>=3,"Average","Poor"))) -> Excellent | M82: =IF(F82>=1000,"1000+ Reviews", IF(F82>=500,"500-999 Reviews", IF(F82>=100,"100-499 Reviews", "Below 100 Reviews"))) -> 100-499 Reviews | N82: =IF(K82="Official Website","Low Opportunity", IF(AND(K82="No Website",E82>=4.5,F82>=500),"Very High Opportunity", IF(AND(K82="No Website",E82>=4.5),"High Opportunity", IF(K82="Social Media","Medium Opportunity","Low Opportunity")))) -> Low Opportunity
A83: Burari, Delhi | B83: clothing stores | C83: Janta Vastra Bhandar | D83: Darshan Vihar Colony, A Block, Shankarpura, Burari, Delhi, 110084, India | E83: 3.8 | F83: 346 | H83: 075035 23782 | I83: clothing_store, store, point_of_interest, establishment | J83: =IF(COUNTIFS($C$2:C83,C83,$D$2:D83,D83)=1,"Unique","Duplicate") -> Unique | K83: =IF(TRIM(G83)="","No Website", IF(OR( ISNUMBER(SEARCH("facebook",LOWER(G83))), ISNUMBER(SEARCH("instagram",LOWER(G83))), ISNUMBER(SEARCH("wa.me",LOWER(G83))), ISNUMBER(SEARCH("whatsapp",LOWER(G83))), ISNUMBER(SEARCH("youtube",LOWER(G83))), ISNUMBER(SEARCH("twitter",LOWER(G83))), ISNUMBER(SEARCH("x.com",LOWER(G83))), ISNUMBER(SEARCH("linkedin",LOWER(G83))), ISNUMBER(SEARCH("linktr.ee",LOWER(G83))), ISNUMBER(SEARCH("g.page",LOWER(G83))), ISNUMBER(SEARCH("maps.app.goo.gl",LOWER(G83))), ISNUMBER(SEARCH("goo.gl",LOWER(G83))) ), "Social Media", "Official Website")) -> No Website | L83: =IF(E83>=4.5,"Excellent", IF(E83>=4,"Good", IF(E83>=3,"Average","Poor"))) -> Average | M83: =IF(F83>=1000,"1000+ Reviews", IF(F83>=500,"500-999 Reviews", IF(F83>=100,"100-499 Reviews", "Below 100 Reviews"))) -> 100-499 Reviews | N83: =IF(K83="Official Website","Low Opportunity", IF(AND(K83="No Website",E83>=4.5,F83>=500),"Very High Opportunity", IF(AND(K83="No Website",E83>=4.5),"High Opportunity", IF(K83="Social Media","Medium Opportunity","Low Opportunity")))) -> Low Opportunity
A84: Burari, Delhi | B84: clothing stores | C84: Richlook Store Burari | D84: Khasra No. 863/3, Maurya Enclave, Sant Nagar, near Nalanda Modern Public School, Maurya Enclave, Laldora Village, Burari, Delhi, 110084, India | E84: 4.8 | F84: 25 | G84: https://www.richlook.in/ | H84: 099906 99786 | I84: clothing_store, store, point_of_interest, establishment | J84: =IF(COUNTIFS($C$2:C84,C84,$D$2:D84,D84)=1,"Unique","Duplicate") -> Unique | K84: =IF(TRIM(G84)="","No Website", IF(OR( ISNUMBER(SEARCH("facebook",LOWER(G84))), ISNUMBER(SEARCH("instagram",LOWER(G84))), ISNUMBER(SEARCH("wa.me",LOWER(G84))), ISNUMBER(SEARCH("whatsapp",LOWER(G84))), ISNUMBER(SEARCH("youtube",LOWER(G84))), ISNUMBER(SEARCH("twitter",LOWER(G84))), ISNUMBER(SEARCH("x.com",LOWER(G84))), ISNUMBER(SEARCH("linkedin",LOWER(G84))), ISNUMBER(SEARCH("linktr.ee",LOWER(G84))), ISNUMBER(SEARCH("g.page",LOWER(G84))), ISNUMBER(SEARCH("maps.app.goo.gl",LOWER(G84))), ISNUMBER(SEARCH("goo.gl",LOWER(G84))) ), "Social Media", "Official Website")) -> Official Website | L84: =IF(E84>=4.5,"Excellent", IF(E84>=4,"Good", IF(E84>=3,"Average","Poor"))) -> Excellent | M84: =IF(F84>=1000,"1000+ Reviews", IF(F84>=500,"500-999 Reviews", IF(F84>=100,"100-499 Reviews", "Below 100 Reviews"))) -> Below 100 Reviews | N84: =IF(K84="Official Website","Low Opportunity", IF(AND(K84="No Website",E84>=4.5,F84>=500),"Very High Opportunity", IF(AND(K84="No Website",E84>=4.5),"High Opportunity", IF(K84="Social Media","Medium Opportunity","Low Opportunity")))) -> Low Opportunity
A85: Burari, Delhi | B85: gyms | C85: SK Fitness | D85: khasra no 5, bus stand, 16/1, main road, near nathupura, Shastri Park Extension Colony, Garhi Khasru, Shankarpura, Burari, Delhi, 110084, India | E85: 5 | F85: 190 | H85: 085279 76366 | I85: fitness_center, gym, sports_activity_location, health, point_of_interest, establishment | J85: =IF(COUNTIFS($C$2:C85,C85,$D$2:D85,D85)=1,"Unique","Duplicate") -> Unique | K85: =IF(TRIM(G85)="","No Website", IF(OR( ISNUMBER(SEARCH("facebook",LOWER(G85))), ISNUMBER(SEARCH("instagram",LOWER(G85))), ISNUMBER(SEARCH("wa.me",LOWER(G85))), ISNUMBER(SEARCH("whatsapp",LOWER(G85))), ISNUMBER(SEARCH("youtube",LOWER(G85))), ISNUMBER(SEARCH("twitter",LOWER(G85))), ISNUMBER(SEARCH("x.com",LOWER(G85))), ISNUMBER(SEARCH("linkedin",LOWER(G85))), ISNUMBER(SEARCH("linktr.ee",LOWER(G85))), ISNUMBER(SEARCH("g.page",LOWER(G85))), ISNUMBER(SEARCH("maps.app.goo.gl",LOWER(G85))), ISNUMBER(SEARCH("goo.gl",LOWER(G85))) ), "Social Media", "Official Website")) -> No Website | L85: =IF(E85>=4.5,"Excellent", IF(E85>=4,"Good", IF(E85>=3,"Average","Poor"))) -> Excellent | M85: =IF(F85>=1000,"1000+ Reviews", IF(F85>=500,"500-999 Reviews", IF(F85>=100,"100-499 Reviews", "Below 100 Reviews"))) -> 100-499 Reviews | N85: =IF(K85="Official Website","Low Opportunity", IF(AND(K85="No Website",E85>=4.5,F85>=500),"Very High Opportunity", IF(AND(K85="No Website",E85>=4.5),"High Opportunity", IF(K85="Social Media","Medium Opportunity","Low Opportunity")))) -> High Opportunity
A86: Burari, Delhi | B86: clothing stores | C86: CityKart Burari | D86: Shri Ram Residency Tower, 100 Feet Rd, opp. Gravis, Conductor Colony, Burari, New Delhi, Delhi, 110084, India | E86: 4.7 | F86: 534 | G86: https://citykart.co.in/ | H86: 096504 07082 | I86: clothing_store, shopping_mall, womens_clothing_store, shoe_store, store, point_of_interest, establishment | J86: =IF(COUNTIFS($C$2:C86,C86,$D$2:D86,D86)=1,"Unique","Duplicate") -> Unique | K86: =IF(TRIM(G86)="","No Website", IF(OR( ISNUMBER(SEARCH("facebook",LOWER(G86))), ISNUMBER(SEARCH("instagram",LOWER(G86))), ISNUMBER(SEARCH("wa.me",LOWER(G86))), ISNUMBER(SEARCH("whatsapp",LOWER(G86))), ISNUMBER(SEARCH("youtube",LOWER(G86))), ISNUMBER(SEARCH("twitter",LOWER(G86))), ISNUMBER(SEARCH("x.com",LOWER(G86))), ISNUMBER(SEARCH("linkedin",LOWER(G86))), ISNUMBER(SEARCH("linktr.ee",LOWER(G86))), ISNUMBER(SEARCH("g.page",LOWER(G86))), ISNUMBER(SEARCH("maps.app.goo.gl",LOWER(G86))), ISNUMBER(SEARCH("goo.gl",LOWER(G86))) ), "Social Media", "Official Website")) -> Official Website | L86: =IF(E86>=4.5,"Excellent", IF(E86>=4,"Good", IF(E86>=3,"Average","Poor"))) -> Excellent | M86: =IF(F86>=1000,"1000+ Reviews", IF(F86>=500,"500-999 Reviews", IF(F86>=100,"100-499 Reviews", "Below 100 Reviews"))) -> 500-999 Reviews | N86: =IF(K86="Official Website","Low Opportunity", IF(AND(K86="No Website",E86>=4.5,F86>=500),"Very High Opportunity", IF(AND(K86="No Website",E86>=4.5),"High Opportunity", IF(K86="Social Media","Medium Opportunity","Low Opportunity")))) -> Low Opportunity
A87: Burari, Delhi | B87: clothing stores | C87: Riwaaz Selection | D87: Shop No:5, Main Market, Cross Road, Block B, West Sant Nagar, Burari, Delhi, 110084, India | E87: 3.9 | F87: 81 | H87: 096548 01480 | I87: clothing_store, store, point_of_interest, establishment | J87: =IF(COUNTIFS($C$2:C87,C87,$D$2:D87,D87)=1,"Unique","Duplicate") -> Unique | K87: =IF(TRIM(G87)="","No Website", IF(OR( ISNUMBER(SEARCH("facebook",LOWER(G87))), ISNUMBER(SEARCH("instagram",LOWER(G87))), ISNUMBER(SEARCH("wa.me",LOWER(G87))), ISNUMBER(SEARCH("whatsapp",LOWER(G87))), ISNUMBER(SEARCH("youtube",LOWER(G87))), ISNUMBER(SEARCH("twitter",LOWER(G87))), ISNUMBER(SEARCH("x.com",LOWER(G87))), ISNUMBER(SEARCH("linkedin",LOWER(G87))), ISNUMBER(SEARCH("linktr.ee",LOWER(G87))), ISNUMBER(SEARCH("g.page",LOWER(G87))), ISNUMBER(SEARCH("maps.app.goo.gl",LOWER(G87))), ISNUMBER(SEARCH("goo.gl",LOWER(G87))) ), "Social Media", "Official Website")) -> No Website | L87: =IF(E87>=4.5,"Excellent", IF(E87>=4,"Good", IF(E87>=3,"Average","Poor"))) -> Average | M87: =IF(F87>=1000,"1000+ Reviews", IF(F87>=500,"500-999 Reviews", IF(F87>=100,"100-499 Reviews", "Below 100 Reviews"))) -> Below 100 Reviews | N87: =IF(K87="Official Website","Low Opportunity", IF(AND(K87="No Website",E87>=4.5,F87>=500),"Very High Opportunity", IF(AND(K87="No Website",E87>=4.5),"High Opportunity", IF(K87="Social Media","Medium Opportunity","Low Opportunity")))) -> Low Opportunity
A88: Burari, Delhi | B88: clothing stores | C88: Klub Fox | Burari | Factory Outlet | D88: Khasra No 348, Burari Village Marg, Maurya Enclave, Baba Colony, Burari, New Delhi, Delhi, 110084, India | E88: 4.3 | F88: 33 | G88: https://www.klubfox.com/ | H88: 095825 17077 | I88: clothing_store, store, point_of_interest, establishment | J88: =IF(COUNTIFS($C$2:C88,C88,$D$2:D88,D88)=1,"Unique","Duplicate") -> Unique | K88: =IF(TRIM(G88)="","No Website", IF(OR( ISNUMBER(SEARCH("facebook",LOWER(G88))), ISNUMBER(SEARCH("instagram",LOWER(G88))), ISNUMBER(SEARCH("wa.me",LOWER(G88))), ISNUMBER(SEARCH("whatsapp",LOWER(G88))), ISNUMBER(SEARCH("youtube",LOWER(G88))), ISNUMBER(SEARCH("twitter",LOWER(G88))), ISNUMBER(SEARCH("x.com",LOWER(G88))), ISNUMBER(SEARCH("linkedin",LOWER(G88))), ISNUMBER(SEARCH("linktr.ee",LOWER(G88))), ISNUMBER(SEARCH("g.page",LOWER(G88))), ISNUMBER(SEARCH("maps.app.goo.gl",LOWER(G88))), ISNUMBER(SEARCH("goo.gl",LOWER(G88))) ), "Social Media", "Official Website")) -> Social Media | L88: =IF(E88>=4.5,"Excellent", IF(E88>=4,"Good", IF(E88>=3,"Average","Poor"))) -> Good | M88: =IF(F88>=1000,"1000+ Reviews", IF(F88>=500,"500-999 Reviews", IF(F88>=100,"100-499 Reviews", "Below 100 Reviews"))) -> Below 100 Reviews | N88: =IF(K88="Official Website","Low Opportunity", IF(AND(K88="No Website",E88>=4.5,F88>=500),"Very High Opportunity", IF(AND(K88="No Website",E88>=4.5),"High Opportunity", IF(K88="Social Media","Medium Opportunity","Low Opportunity")))) -> Medium Opportunity
A89: Burari, Delhi | B89: clothing stores | C89: V2 Retail - Sant Nagar | D89: KHASRA NO, 863/1, Sant Nagar Marg, Parvatiya Anchal, Maurya Enclave, Sant Nagar, Burari, New Delhi, Delhi, 110084, India | E89: 3.7 | F89: 18 | G89: https://v2retail.com/ | H89: 081309 07705 | I89: clothing_store, shopping_mall, womens_clothing_store, service, store, point_of_interest, establishment | J89: =IF(COUNTIFS($C$2:C89,C89,$D$2:D89,D89)=1,"Unique","Duplicate") -> Unique | K89: =IF(TRIM(G89)="","No Website", IF(OR( ISNUMBER(SEARCH("facebook",LOWER(G89))), ISNUMBER(SEARCH("instagram",LOWER(G89))), ISNUMBER(SEARCH("wa.me",LOWER(G89))), ISNUMBER(SEARCH("whatsapp",LOWER(G89))), ISNUMBER(SEARCH("youtube",LOWER(G89))), ISNUMBER(SEARCH("twitter",LOWER(G89))), ISNUMBER(SEARCH("x.com",LOWER(G89))), ISNUMBER(SEARCH("linkedin",LOWER(G89))), ISNUMBER(SEARCH("linktr.ee",LOWER(G89))), ISNUMBER(SEARCH("g.page",LOWER(G89))), ISNUMBER(SEARCH("maps.app.goo.gl",LOWER(G89))), ISNUMBER(SEARCH("goo.gl",LOWER(G89))) ), "Social Media", "Official Website")) -> Official Website | L89: =IF(E89>=4.5,"Excellent", IF(E89>=4,"Good", IF(E89>=3,"Average","Poor"))) -> Average | M89: =IF(F89>=1000,"1000+ Reviews", IF(F89>=500,"500-999 Reviews", IF(F89>=100,"100-499 Reviews", "Below 100 Reviews"))) -> Below 100 Reviews | N89: =IF(K89="Official Website","Low Opportunity", IF(AND(K89="No Website",E89>=4.5,F89>=500),"Very High Opportunity", IF(AND(K89="No Website",E89>=4.5),"High Opportunity", IF(K89="Social Media","Medium Opportunity","Low Opportunity")))) -> Low Opportunity
A90: Mukherjee Nagar, Delhi | B90: clinics | C90: Vardaan to heal you…Physiotherapy Clinic+PEMF Therapy | D90: N-9, N Block, Mukherjee Nagar, Delhi, 110033, India | E90: 5 | F90: 177 | H90: 098687 22603 | I90: physiotherapist, health, point_of_interest, establishment | J90: =IF(COUNTIFS($C$2:C90,C90,$D$2:D90,D90)=1,"Unique","Duplicate") -> Unique | K90: =IF(TRIM(G90)="","No Website", IF(OR( ISNUMBER(SEARCH("facebook",LOWER(G90))), ISNUMBER(SEARCH("instagram",LOWER(G90))), ISNUMBER(SEARCH("wa.me",LOWER(G90))), ISNUMBER(SEARCH("whatsapp",LOWER(G90))), ISNUMBER(SEARCH("youtube",LOWER(G90))), ISNUMBER(SEARCH("twitter",LOWER(G90))), ISNUMBER(SEARCH("x.com",LOWER(G90))), ISNUMBER(SEARCH("linkedin",LOWER(G90))), ISNUMBER(SEARCH("linktr.ee",LOWER(G90))), ISNUMBER(SEARCH("g.page",LOWER(G90))), ISNUMBER(SEARCH("maps.app.goo.gl",LOWER(G90))), ISNUMBER(SEARCH("goo.gl",LOWER(G90))) ), "Social Media", "Official Website")) -> No Website | L90: =IF(E90>=4.5,"Excellent", IF(E90>=4,"Good", IF(E90>=3,"Average","Poor"))) -> Excellent | M90: =IF(F90>=1000,"1000+ Reviews", IF(F90>=500,"500-999 Reviews", IF(F90>=100,"100-499 Reviews", "Below 100 Reviews"))) -> 100-499 Reviews | N90: =IF(K90="Official Website","Low Opportunity", IF(AND(K90="No Website",E90>=4.5,F90>=500),"Very High Opportunity", IF(AND(K90="No Website",E90>=4.5),"High Opportunity", IF(K90="Social Media","Medium Opportunity","Low Opportunity")))) -> High Opportunity
A91: Burari, Delhi | B91: clothing stores | C91: KRAZE Raymond Showroom | D91: Main Market, opposite Sant Nagar Marg, Block B, Sant Nagar, Burari, Delhi, 110084, India | E91: 4.6 | F91: 29 | G91: https://www.instagram.com/kraze_couture/ | H91: 092050 30117 | I91: clothing_store, store, point_of_interest, establishment | J91: =IF(COUNTIFS($C$2:C91,C91,$D$2:D91,D91)=1,"Unique","Duplicate") -> Unique | K91: =IF(TRIM(G91)="","No Website", IF(OR( ISNUMBER(SEARCH("facebook",LOWER(G91))), ISNUMBER(SEARCH("instagram",LOWER(G91))), ISNUMBER(SEARCH("wa.me",LOWER(G91))), ISNUMBER(SEARCH("whatsapp",LOWER(G91))), ISNUMBER(SEARCH("youtube",LOWER(G91))), ISNUMBER(SEARCH("twitter",LOWER(G91))), ISNUMBER(SEARCH("x.com",LOWER(G91))), ISNUMBER(SEARCH("linkedin",LOWER(G91))), ISNUMBER(SEARCH("linktr.ee",LOWER(G91))), ISNUMBER(SEARCH("g.page",LOWER(G91))), ISNUMBER(SEARCH("maps.app.goo.gl",LOWER(G91))), ISNUMBER(SEARCH("goo.gl",LOWER(G91))) ), "Social Media", "Official Website")) -> Social Media | L91: =IF(E91>=4.5,"Excellent", IF(E91>=4,"Good", IF(E91>=3,"Average","Poor"))) -> Excellent | M91: =IF(F91>=1000,"1000+ Reviews", IF(F91>=500,"500-999 Reviews", IF(F91>=100,"100-499 Reviews", "Below 100 Reviews"))) -> Below 100 Reviews | N91: =IF(K91="Official Website","Low Opportunity", IF(AND(K91="No Website",E91>=4.5,F91>=500),"Very High Opportunity", IF(AND(K91="No Website",E91>=4.5),"High Opportunity", IF(K91="Social Media","Medium Opportunity","Low Opportunity")))) -> Medium Opportunity
A92: Burari, Delhi | B92: clothing stores | C92: Intimissi Lingerie Store Burari | D92: Shop No. 850, extended lal dora, Maurya Enclave, Sant Nagar, Burari, Delhi, 110084, India | E92: 4.8 | F92: 183 | G92: https://intimissionline.com/ | H92: 092127 87310 | I92: clothing_store, store, point_of_interest, establishment | J92: =IF(COUNTIFS($C$2:C92,C92,$D$2:D92,D92)=1,"Unique","Duplicate") -> Unique | K92: =IF(TRIM(G92)="","No Website", IF(OR( ISNUMBER(SEARCH("facebook",LOWER(G92))), ISNUMBER(SEARCH("instagram",LOWER(G92))), ISNUMBER(SEARCH("wa.me",LOWER(G92))), ISNUMBER(SEARCH("whatsapp",LOWER(G92))), ISNUMBER(SEARCH("youtube",LOWER(G92))), ISNUMBER(SEARCH("twitter",LOWER(G92))), ISNUMBER(SEARCH("x.com",LOWER(G92))), ISNUMBER(SEARCH("linkedin",LOWER(G92))), ISNUMBER(SEARCH("linktr.ee",LOWER(G92))), ISNUMBER(SEARCH("g.page",LOWER(G92))), ISNUMBER(SEARCH("maps.app.goo.gl",LOWER(G92))), ISNUMBER(SEARCH("goo.gl",LOWER(G92))) ), "Social Media", "Official Website")) -> Official Website | L92: =IF(E92>=4.5,"Excellent", IF(E92>=4,"Good", IF(E92>=3,"Average","Poor"))) -> Excellent | M92: =IF(F92>=1000,"1000+ Reviews", IF(F92>=500,"500-999 Reviews", IF(F92>=100,"100-499 Reviews", "Below 100 Reviews"))) -> 100-499 Reviews | N92: =IF(K92="Official Website","Low Opportunity", IF(AND(K92="No Website",E92>=4.5,F92>=500),"Very High Opportunity", IF(AND(K92="No Website",E92>=4.5),"High Opportunity", IF(K92="Social Media","Medium Opportunity","Low Opportunity")))) -> Low Opportunity
A93: Moti Nagar, Delhi | B93: clothing stores | C93: Sudershan Cloth House | D93: Shop no. 6, Nanak Pura, Moti Bagh, New Delhi, Delhi 110021, India | E93: 5 | F93: 175 | H93: 092124 13223 | I93: clothing_store, point_of_interest, store, establishment | J93: =IF(COUNTIFS($C$2:C93,C93,$D$2:D93,D93)=1,"Unique","Duplicate") -> Unique | K93: =IF(TRIM(G93)="","No Website", IF(OR( ISNUMBER(SEARCH("facebook",LOWER(G93))), ISNUMBER(SEARCH("instagram",LOWER(G93))), ISNUMBER(SEARCH("wa.me",LOWER(G93))), ISNUMBER(SEARCH("whatsapp",LOWER(G93))), ISNUMBER(SEARCH("youtube",LOWER(G93))), ISNUMBER(SEARCH("twitter",LOWER(G93))), ISNUMBER(SEARCH("x.com",LOWER(G93))), ISNUMBER(SEARCH("linkedin",LOWER(G93))), ISNUMBER(SEARCH("linktr.ee",LOWER(G93))), ISNUMBER(SEARCH("g.page",LOWER(G93))), ISNUMBER(SEARCH("maps.app.goo.gl",LOWER(G93))), ISNUMBER(SEARCH("goo.gl",LOWER(G93))) ), "Social Media", "Official Website")) -> No Website | L93: =IF(E93>=4.5,"Excellent", IF(E93>=4,"Good", IF(E93>=3,"Average","Poor"))) -> Excellent | M93: =IF(F93>=1000,"1000+ Reviews", IF(F93>=500,"500-999 Reviews", IF(F93>=100,"100-499 Reviews", "Below 100 Reviews"))) -> 100-499 Reviews | N93: =IF(K93="Official Website","Low Opportunity", IF(AND(K93="No Website",E93>=4.5,F93>=500),"Very High Opportunity", IF(AND(K93="No Website",E93>=4.5),"High Opportunity", IF(K93="Social Media","Medium Opportunity","Low Opportunity")))) -> High Opportunity
A94: Burari, Delhi | B94: clothing stores | C94: Lifestyle Fashion | D94: KHASRA NO. 19/20 GROUND FLOOR VILLAG BURARI BLK-A-1 AMRIT VIHAR LANDMARK OPPST. JOSI KOUTHI, Amirt Vihar, Nathupura, Burari, Delhi, 110084, India | E94: 5 | F94: 5 | G94: https://lifestyle-fashion.grexa.site/ | I94: clothing_store, store, point_of_interest, establishment | J94: =IF(COUNTIFS($C$2:C94,C94,$D$2:D94,D94)=1,"Unique","Duplicate") -> Unique | K94: =IF(TRIM(G94)="","No Website", IF(OR( ISNUMBER(SEARCH("facebook",LOWER(G94))), ISNUMBER(SEARCH("instagram",LOWER(G94))), ISNUMBER(SEARCH("wa.me",LOWER(G94))), ISNUMBER(SEARCH("whatsapp",LOWER(G94))), ISNUMBER(SEARCH("youtube",LOWER(G94))), ISNUMBER(SEARCH("twitter",LOWER(G94))), ISNUMBER(SEARCH("x.com",LOWER(G94))), ISNUMBER(SEARCH("linkedin",LOWER(G94))), ISNUMBER(SEARCH("linktr.ee",LOWER(G94))), ISNUMBER(SEARCH("g.page",LOWER(G94))), ISNUMBER(SEARCH("maps.app.goo.gl",LOWER(G94))), ISNUMBER(SEARCH("goo.gl",LOWER(G94))) ), "Social Media", "Official Website")) -> Official Website | L94: =IF(E94>=4.5,"Excellent", IF(E94>=4,"Good", IF(E94>=3,"Average","Poor"))) -> Excellent | M94: =IF(F94>=1000,"1000+ Reviews", IF(F94>=500,"500-999 Reviews", IF(F94>=100,"100-499 Reviews", "Below 100 Reviews"))) -> Below 100 Reviews | N94: =IF(K94="Official Website","Low Opportunity", IF(AND(K94="No Website",E94>=4.5,F94>=500),"Very High Opportunity", IF(AND(K94="No Website",E94>=4.5),"High Opportunity", IF(K94="Social Media","Medium Opportunity","Low Opportunity")))) -> Low Opportunity
A95: Burari, Delhi | B95: clothing stores | C95: Zudio - Burari, Delhi | D95: Khasra No - 738, Landmark, Main Rd, opposite Telephone Exchange 2, Block D, Kamal Pur, Burari, Delhi, 110084, India | E95: 4 | F95: 670 | G95: https://www.zudio.com/ | H95: 077009 37043 | I95: shopping_mall, point_of_interest, establishment | J95: =IF(COUNTIFS($C$2:C95,C95,$D$2:D95,D95)=1,"Unique","Duplicate") -> Unique | K95: =IF(TRIM(G95)="","No Website", IF(OR( ISNUMBER(SEARCH("facebook",LOWER(G95))), ISNUMBER(SEARCH("instagram",LOWER(G95))), ISNUMBER(SEARCH("wa.me",LOWER(G95))), ISNUMBER(SEARCH("whatsapp",LOWER(G95))), ISNUMBER(SEARCH("youtube",LOWER(G95))), ISNUMBER(SEARCH("twitter",LOWER(G95))), ISNUMBER(SEARCH("x.com",LOWER(G95))), ISNUMBER(SEARCH("linkedin",LOWER(G95))), ISNUMBER(SEARCH("linktr.ee",LOWER(G95))), ISNUMBER(SEARCH("g.page",LOWER(G95))), ISNUMBER(SEARCH("maps.app.goo.gl",LOWER(G95))), ISNUMBER(SEARCH("goo.gl",LOWER(G95))) ), "Social Media", "Official Website")) -> Official Website | L95: =IF(E95>=4.5,"Excellent", IF(E95>=4,"Good", IF(E95>=3,"Average","Poor"))) -> Good | M95: =IF(F95>=1000,"1000+ Reviews", IF(F95>=500,"500-999 Reviews", IF(F95>=100,"100-499 Reviews", "Below 100 Reviews"))) -> 500-999 Reviews | N95: =IF(K95="Official Website","Low Opportunity", IF(AND(K95="No Website",E95>=4.5,F95>=500),"Very High Opportunity", IF(AND(K95="No Website",E95>=4.5),"High Opportunity", IF(K95="Social Media","Medium Opportunity","Low Opportunity")))) -> Low Opportunity
A96: Burari, Delhi | B96: clothing stores | C96: Shri Keshav Cloths & Readymade Garments | D96: Unnamed Road, Uttarakhand Enclave, Kaushik Enclave, Shankarpura, Burari, Delhi, 110084, India | E96: 4.4 | F96: 15 | H96: 098718 51707 | I96: clothing_store, store, point_of_interest, establishment | J96: =IF(COUNTIFS($C$2:C96,C96,$D$2:D96,D96)=1,"Unique","Duplicate") -> Unique | K96: =IF(TRIM(G96)="","No Website", IF(OR( ISNUMBER(SEARCH("facebook",LOWER(G96))), ISNUMBER(SEARCH("instagram",LOWER(G96))), ISNUMBER(SEARCH("wa.me",LOWER(G96))), ISNUMBER(SEARCH("whatsapp",LOWER(G96))), ISNUMBER(SEARCH("youtube",LOWER(G96))), ISNUMBER(SEARCH("twitter",LOWER(G96))), ISNUMBER(SEARCH("x.com",LOWER(G96))), ISNUMBER(SEARCH("linkedin",LOWER(G96))), ISNUMBER(SEARCH("linktr.ee",LOWER(G96))), ISNUMBER(SEARCH("g.page",LOWER(G96))), ISNUMBER(SEARCH("maps.app.goo.gl",LOWER(G96))), ISNUMBER(SEARCH("goo.gl",LOWER(G96))) ), "Social Media", "Official Website")) -> No Website | L96: =IF(E96>=4.5,"Excellent", IF(E96>=4,"Good", IF(E96>=3,"Average","Poor"))) -> Good | M96: =IF(F96>=1000,"1000+ Reviews", IF(F96>=500,"500-999 Reviews", IF(F96>=100,"100-499 Reviews", "Below 100 Reviews"))) -> Below 100 Reviews | N96: =IF(K96="Official Website","Low Opportunity", IF(AND(K96="No Website",E96>=4.5,F96>=500),"Very High Opportunity", IF(AND(K96="No Website",E96>=4.5),"High Opportunity", IF(K96="Social Media","Medium Opportunity","Low Opportunity")))) -> Low Opportunity
A97: Burari, Delhi | B97: grocery stores | C97: Rajmandir Hypermarket Burari | D97: 15, Sant Nagar Marg, Block B, Sant Nagar, Burari, Delhi, 110084, India | E97: 4 | F97: 1319 | G97: https://www.rajmandirhypermarket.com/ | H97: 093112 39211 | I97: grocery_store, food_store, store, food, point_of_interest, establishment | J97: =IF(COUNTIFS($C$2:C97,C97,$D$2:D97,D97)=1,"Unique","Duplicate") -> Unique | K97: =IF(TRIM(G97)="","No Website", IF(OR( ISNUMBER(SEARCH("facebook",LOWER(G97))), ISNUMBER(SEARCH("instagram",LOWER(G97))), ISNUMBER(SEARCH("wa.me",LOWER(G97))), ISNUMBER(SEARCH("whatsapp",LOWER(G97))), ISNUMBER(SEARCH("youtube",LOWER(G97))), ISNUMBER(SEARCH("twitter",LOWER(G97))), ISNUMBER(SEARCH("x.com",LOWER(G97))), ISNUMBER(SEARCH("linkedin",LOWER(G97))), ISNUMBER(SEARCH("linktr.ee",LOWER(G97))), ISNUMBER(SEARCH("g.page",LOWER(G97))), ISNUMBER(SEARCH("maps.app.goo.gl",LOWER(G97))), ISNUMBER(SEARCH("goo.gl",LOWER(G97))) ), "Social Media", "Official Website")) -> Official Website | L97: =IF(E97>=4.5,"Excellent", IF(E97>=4,"Good", IF(E97>=3,"Average","Poor"))) -> Good | M97: =IF(F97>=1000,"1000+ Reviews", IF(F97>=500,"500-999 Reviews", IF(F97>=100,"100-499 Reviews", "Below 100 Reviews"))) -> 1000+ Reviews | N97: =IF(K97="Official Website","Low Opportunity", IF(AND(K97="No Website",E97>=4.5,F97>=500),"Very High Opportunity", IF(AND(K97="No Website",E97>=4.5),"High Opportunity", IF(K97="Social Media","Medium Opportunity","Low Opportunity")))) -> Low Opportunity
A98: Burari, Delhi | B98: grocery stores | C98: Max Bazaar | D98: kh no :830/1/2/2,830/2/2 831/1 extended lal dora village, upkar colony, Sant Nagar, Burari, New Delhi, Delhi, 110084, India | E98: 4.2 | F98: 3199 | H98: 1800 102 3171 | I98: asian_grocery_store, hypermarket, supermarket, grocery_store, food_store, store, food, point_of_interest, establishment | J98: =IF(COUNTIFS($C$2:C98,C98,$D$2:D98,D98)=1,"Unique","Duplicate") -> Unique | K98: =IF(TRIM(G98)="","No Website", IF(OR( ISNUMBER(SEARCH("facebook",LOWER(G98))), ISNUMBER(SEARCH("instagram",LOWER(G98))), ISNUMBER(SEARCH("wa.me",LOWER(G98))), ISNUMBER(SEARCH("whatsapp",LOWER(G98))), ISNUMBER(SEARCH("youtube",LOWER(G98))), ISNUMBER(SEARCH("twitter",LOWER(G98))), ISNUMBER(SEARCH("x.com",LOWER(G98))), ISNUMBER(SEARCH("linkedin",LOWER(G98))), ISNUMBER(SEARCH("linktr.ee",LOWER(G98))), ISNUMBER(SEARCH("g.page",LOWER(G98))), ISNUMBER(SEARCH("maps.app.goo.gl",LOWER(G98))), ISNUMBER(SEARCH("goo.gl",LOWER(G98))) ), "Social Media", "Official Website")) -> No Website | L98: =IF(E98>=4.5,"Excellent", IF(E98>=4,"Good", IF(E98>=3,"Average","Poor"))) -> Good | M98: =IF(F98>=1000,"1000+ Reviews", IF(F98>=500,"500-999 Reviews", IF(F98>=100,"100-499 Reviews", "Below 100 Reviews"))) -> 1000+ Reviews | N98: =IF(K98="Official Website","Low Opportunity", IF(AND(K98="No Website",E98>=4.5,F98>=500),"Very High Opportunity", IF(AND(K98="No Website",E98>=4.5),"High Opportunity", IF(K98="Social Media","Medium Opportunity","Low Opportunity")))) -> Low Opportunity
A99: Burari, Delhi | B99: grocery stores | C99: Vishal Mega Mart | D99: MAIN, 100 Feet Rd, opp. BHAGAT COLONY GATE, Block B, Sant Nagar, Burari, New Delhi, Delhi, 110084, India | E99: 3.8 | F99: 7583 | G99: https://stores.vishalmegamart.com/shopping-mart-burari-north-delhi-30567/home?utm_source=GMB | H99: 072178 87901 | I99: hypermarket, supermarket, grocery_store, service, food_store, clothing_store, store, food, point_of_interest, establishment | J99: =IF(COUNTIFS($C$2:C99,C99,$D$2:D99,D99)=1,"Unique","Duplicate") -> Unique | K99: =IF(TRIM(G99)="","No Website", IF(OR( ISNUMBER(SEARCH("facebook",LOWER(G99))), ISNUMBER(SEARCH("instagram",LOWER(G99))), ISNUMBER(SEARCH("wa.me",LOWER(G99))), ISNUMBER(SEARCH("whatsapp",LOWER(G99))), ISNUMBER(SEARCH("youtube",LOWER(G99))), ISNUMBER(SEARCH("twitter",LOWER(G99))), ISNUMBER(SEARCH("x.com",LOWER(G99))), ISNUMBER(SEARCH("linkedin",LOWER(G99))), ISNUMBER(SEARCH("linktr.ee",LOWER(G99))), ISNUMBER(SEARCH("g.page",LOWER(G99))), ISNUMBER(SEARCH("maps.app.goo.gl",LOWER(G99))), ISNUMBER(SEARCH("goo.gl",LOWER(G99))) ), "Social Media", "Official Website")) -> Official Website | L99: =IF(E99>=4.5,"Excellent", IF(E99>=4,"Good", IF(E99>=3,"Average","Poor"))) -> Average | M99: =IF(F99>=1000,"1000+ Reviews", IF(F99>=500,"500-999 Reviews", IF(F99>=100,"100-499 Reviews", "Below 100 Reviews"))) -> 1000+ Reviews | N99: =IF(K99="Official Website","Low Opportunity", IF(AND(K99="No Website",E99>=4.5,F99>=500),"Very High Opportunity", IF(AND(K99="No Website",E99>=4.5),"High Opportunity", IF(K99="Social Media","Medium Opportunity","Low Opportunity")))) -> Low Opportunity
A100: Burari, Delhi | B100: grocery stores | C100: JR MART | D100: Labour Chowk, 876, Labour Chowk, Parvatiya Anchal, Block B, Sant Nagar, Burari, Delhi, 110084, India | E100: 4.4 | F100: 76 | H100: 070111 37350 | I100: supermarket, gift_shop, shopping_mall, grocery_store, home_goods_store, building_materials_store, food_store, store, food, point_of_interest, establishment | J100: =IF(COUNTIFS($C$2:C100,C100,$D$2:D100,D100)=1,"Unique","Duplicate") -> Unique | K100: =IF(TRIM(G100)="","No Website", IF(OR( ISNUMBER(SEARCH("facebook",LOWER(G100))), ISNUMBER(SEARCH("instagram",LOWER(G100))), ISNUMBER(SEARCH("wa.me",LOWER(G100))), ISNUMBER(SEARCH("whatsapp",LOWER(G100))), ISNUMBER(SEARCH("youtube",LOWER(G100))), ISNUMBER(SEARCH("twitter",LOWER(G100))), ISNUMBER(SEARCH("x.com",LOWER(G100))), ISNUMBER(SEARCH("linkedin",LOWER(G100))), ISNUMBER(SEARCH("linktr.ee",LOWER(G100))), ISNUMBER(SEARCH("g.page",LOWER(G100))), ISNUMBER(SEARCH("maps.app.goo.gl",LOWER(G100))), ISNUMBER(SEARCH("goo.gl",LOWER(G100))) ), "Social Media", "Official Website")) -> No Website | L100: =IF(E100>=4.5,"Excellent", IF(E100>=4,"Good", IF(E100>=3,"Average","Poor"))) -> Good | M100: =IF(F100>=1000,"1000+ Reviews", IF(F100>=500,"500-999 Reviews", IF(F100>=100,"100-499 Reviews", "Below 100 Reviews"))) -> Below 100 Reviews | N100: =IF(K100="Official Website","Low Opportunity", IF(AND(K100="No Website",E100>=4.5,F100>=500),"Very High Opportunity", IF(AND(K100="No Website",E100>=4.5),"High Opportunity", IF(K100="Social Media","Medium Opportunity","Low Opportunity")))) -> Low Opportunity
...

Sheet Business_Summary
A1: Business Summary Delhi Businesses Digital Presence Analysis
A3: Dataset Overview:
A4: Metric | D4: Value
A5: Total Businesses | D5: =COUNTA(delhi_business_cleaned!C2:C1000)-1 -> 10041
A6: Average Rating | D6: =ROUND(AVERAGE(delhi_business_cleaned!E2:E1000),2) -> 4.52
A7: Average Review Count per Business | D7: =ROUND(AVERAGE(delhi_business_cleaned!F2:F1000),0) -> 681
A9: Digital Presence:
A10: Category | D10: Count | F10: Percentage
A11: Official Website | D11: =COUNTIF(delhi_business_cleaned!K2:K1000,"Official Website") -> 4434 | F11: =D11/D5 -> 0.44158948
A12: Social Media | D12: =COUNTIF(delhi_business_cleaned!K2:K1000,"Social Media") -> 525 | F12: =D12/D5 -> 0.052285629
A13: No Website | D13: =COUNTIF(delhi_business_cleaned!K2:K1000,"No Website") -> 5082 | F13: =D13/D5 -> 0.50612489
A15: Opportunity Summary:
A16: Opportunity Level | D16: Business Count
A17: Very High | D17: =COUNTIF(delhi_business_cleaned!N:N,"Very High Opportunity") -> 183
A18: High | D18: =COUNTIF(delhi_business_cleaned!N:N,"High Opportunity") -> 2671
A19: Medium | D19: =COUNTIF(delhi_business_cleaned!N:N,"Medium Opportunity") -> 525
A20: Low | D20: =COUNTIF(delhi_business_cleaned!N:N,"Low Opportunity") -> 6662
A22: Key Observations:
A23: 1. Approximately 50.6% of businesses do not have an official website, indicating significant opportunities for digital transformation.
A24: 2. Only 44.2% of businesses maintain an official website, while the remaining businesses depend on social media or have no online presence.
A25: 3. Businesses classified as High and Very High Opportunity should be prioritized for website development due to their strong customer ratings.
A26: 4. Customer ratings remain consistently high across the dataset, suggesting many businesses have established reputations despite lacking dedicated websites.
A28: Conclusion:
A29: The cleaned dataset provides a reliable foundation for business intelligence analysis. More than half of the businesses either lack an official website or rely solely on
A30: social media, highlighting substantial opportunities for improving digital presence. The prepared dataset is now suitable for dashboard development and opportunity
A31: identification.

Sheet top_10_business_opportunities
A1: Top 10 Business Opportunities for Website Development
A3: Businesses with strong customer ratings and digital growth potential:
A4: Rank | B4: Business Name | C4: Category | D4: Area | E4: Rating | F4: Reviews | G4: Current Digital Presence | H4: Recommendation
A5: 1 | B5: Vardaan Mobile | C5: mobile shops | D5: Saket, Delhi | E5: 5 | F5: 1017 | G5: No Website | H5: Develop a responsive website showcasing products, contact information, and Google Maps integration.
A6: 2 | B6: Fashion Craft | C6: clothing stores | D6: Connaught Place, New Delhi | E6: 5 | F6: 987 | G6: No Website | H6: Create an e-commerce enabled website to showcase clothing collections and improve online visibility.
A7: 3 | B7: GUPTA MOBILE TELECOM | C7: mobile shops | D7: Pitampura, Delhi | E7: 5 | F7: 814 | G7: No Website | H7: Build a website with product catalog, service details, and customer enquiry options.
A8: 4 | B8: Libas | C8: clothing stores | D8: Kamla Nagar, Delhi | E8: 5 | F8: 782 | G8: No Website | H8: Launch an official website featuring products, offers, and social media integration.
A9: 5 | B9: Bakingham - The Bake Town | C9: bakeries | D9: Mayur Vihar, Delhi | E9: 5 | F9: 679 | G9: No Website | H9: Develop a website with online ordering, menu display, and customer reviews.
A10: 6 | B10: GURU NANAK GEMS & JEWELS | C10: jewellery shops | D10: Kalkaji, Delhi | E10: 5 | F10: 654 | G10: No Website | H10: Create a secure website highlighting jewellery collections and enquiry forms.
A11: 7 | B11: Mathematics Specialist- Dwar (@RatanKumarGupta) | C11: tutoring centers | D11: Uttam Nagar, Delhi | E11: 5 | F11: 516 | G11: No Website | H11: Build a website for course details, admissions, and online registration.
A12: 8 | B12: AD BEAUTY LOUNGE LADIES PARLOUR | C12: salons | D12: Burari, Delhi | E12: 5 | F12: 506 | G12: No Website | H12: Develop a salon website with appointment booking and service catalog.
A13: 9 | B13: Maths Mantra Best Maths Institute(Maths by Puneet chaudhary) | C13: tutoring centers | D13: Mukherjee Nagar, Delhi | E13: 5 | F13: 499 | G13: No Website | H13: Launch an educational website featuring courses, schedules, and enquiry forms.
A14: 10 | B14: Shresth PCS Academy, Best PCS Test Series Coaching in Mukharjee nagar delhi | C14: tutoring centers | D14: Mukherjee Nagar, Delhi | E14: 5 | F14: 447 | G14: No Website | H14: Create a website to promote coaching programs, admission details, and study resources.
